Workbook
Name WeekEndDay: SETTINGS!$B$4
Name DefaultWindow: SETTINGS!$B$5
Name RAG_Green: SETTINGS!$B$6
Name RAG_Amber: SETTINGS!$B$7
Name UtilLow: SETTINGS!$B$8
Name UtilHigh: SETTINGS!$B$9
Name UtilLowWeeks: SETTINGS!$B$10
Name Cap_FT: SETTINGS!$B$11
Name Cap_Coaster: SETTINGS!$B$12
Name Cap_Electric: SETTINGS!$B$13
Name Cap_Big: SETTINGS!$B$14
Name CurrencySymbol: SETTINGS!$B$15
Name WSF_SelectList: OFFSET(CALC_SEARCH!$C$2,0,0,MAX(1,MIN(250,CALC_SEARCH!$D$2)),1)
Name WSF_WeekList: OFFSET(CALC_LISTS!$A$1,0,0,1+CALC_LISTS!$B$6,1)
Name TRANSPORT_SelectList: OFFSET(CALC_SEARCH!$H$2,0,0,MAX(1,MIN(250,CALC_SEARCH!$I$2)),1)
Name TRANSPORT_WeekList: OFFSET(CALC_LISTS!$C$1,0,0,1+CALC_LISTS!$D$6,1)

Sheet HOME
B1: OPERATIONS REPORTING & ANALYSIS | L1: ⌂ HOME
B2: Central · 92 Areas · Zones · Cells · Community Churches · Transport
B4: Dashboards
B6: MASTER DASHBOARD | F6: WSF DASHBOARD | J6: MIDWEEK DASHBOARD
B7: All streams side by side | F7: Saturday cell services | J7: Zonal midweek services
B10: CHOP DASHBOARD | F10: COMMUNITY CHURCH DASHBOARD | J10: TRANSPORT DASHBOARD
B11: Covenant Hour of Prayer | F11: Sunday service first | J11: Operations, finance, optimisation
B14: AREA SCORECARD | F14: ZONE SCORECARD | J14: DATA QUALITY
B15: One Area across every stream | F15: One Zone across every stream | J15: Rejected rows and missing weeks
B19: Data status
B20: Last data loaded | E20: =IF(MAX(DATA_WSF!$N:$N,DATA_MIDWEEK!$K:$K,DATA_CHOP!$K:$K,DATA_COMMUNITY!$K:$K,DATA_TRANSPORT!$AA:$AA,DATA_TRANSPORT_COSTS!$P:$P,DATA_TRANSPORT_BUDGET!$J:$J)=0,"No data yet",MAX(DATA_WSF!$N:$N,DATA_MIDWEEK!$K:$K,DATA_CHOP!$K:$K,DATA_COMMUNITY!$K:$K,DATA_TRANSPORT!$AA:$AA,DATA_TRANSPORT_COSTS!$P:$P,DATA_TRANSPORT_BUDGET!$J:$J)) | J20: How to use
J21: 1. Choose a dashboard above. Every dashboard has the same control strip at the top.
B22: Stream | E22: Latest week | G22: Rows in workbook | J22: 2. SCOPE: Global for everything, Area for one Area, Zone for one Zone.
B23: WSF | E23: =IF(MAX(DATA_WSF!$A:$A)=0,"–",MAX(DATA_WSF!$A:$A)) | G23: =COUNT(DATA_WSF!$A:$A) | J23: 3. SEARCH: type part of a name (e.g. 'ikeja'), then open SELECT: it lists only the matching Areas or Zones.
B24: Midweek | E24: =IF(MAX(DATA_MIDWEEK!$A:$A)=0,"–",MAX(DATA_MIDWEEK!$A:$A)) | G24: =COUNT(DATA_MIDWEEK!$A:$A) | J24: 4. WEEK ENDING: 'Latest' follows new data automatically; pick an older week to look back.
B25: CHOP | E25: =IF(MAX(DATA_CHOP!$A:$A)=0,"–",MAX(DATA_CHOP!$A:$A)) | G25: =COUNT(DATA_CHOP!$A:$A) | J25: 5. COMPARE (WEEKS): the averaging window, 1 to 52 weeks. '–' means there is no data for that figure.
B26: Community Church | E26: =IF(MAX(DATA_COMMUNITY!$A:$A)=0,"–",MAX(DATA_COMMUNITY!$A:$A)) | G26: =COUNT(DATA_COMMUNITY!$A:$A) | J26: 6. New data never goes into these sheets by hand: drop the files in the inbox folder and run ingest.py (see README).
B27: Transport bus runs | E27: =IF(MAX(DATA_TRANSPORT!$A:$A)=0,"–",MAX(DATA_TRANSPORT!$A:$A)) | G27: =COUNT(DATA_TRANSPORT!$A:$A)
B28: Transport coaster fuel | E28: =IF(MAX(DATA_TRANSPORT_COSTS!$A:$A)=0,"–",MAX(DATA_TRANSPORT_COSTS!$A:$A)) | G28: =COUNT(DATA_TRANSPORT_COSTS!$A:$A)
B29: Transport FT budget | E29: =IF(MAX(DATA_TRANSPORT_BUDGET!$A:$A)=0,"–",MAX(DATA_TRANSPORT_BUDGET!$A:$A)) | G29: =COUNT(DATA_TRANSPORT_BUDGET!$A:$A)
B30: Build in progress: the WSF and TRANSPORT dashboards, data tables, masters, Calendar, SETTINGS and DATA QUALITY are complete. Midweek, CHOP, Community, the scorecards and the Master dashboard follow as their sample files arrive.

Sheet MASTER DASHBOARD
B1: MASTER DASHBOARD | N1: ⌂ HOME
B2: Global view of every stream side by side
B4: Stage 2: this dashboard is built after the WSF DASHBOARD is reviewed, using the same control strip, KPI cards, time analysis, rankings and non-reporting layout. Its data is already loaded in the all DATA_* sheet.

Sheet WSF DASHBOARD
B1: WSF DASHBOARD | N1: ⌂ HOME
B2: Worship Service Fellowship · Saturday cell services · attendance and cell reporting compliance
B3: SCOPE | C3: SEARCH (type part of a name) | E3: SELECT AREA / ZONE ▼ | H3: STREAM | I3: WEEK ENDING ▼ | K3: COMPARE (WEEKS) | L3: SHOWING
B4: Global | H4: WSF | I4: Latest | K4: 4 | L4: =CALC_WSF!$B$16&IF(CALC_WSF!$B$10=0,""," · w/e "&TEXT(CALC_WSF!$B$10,"dd mmm yyyy"))&" · "&CALC_WSF!$B$11&"-wk window"
B5: =IF(CALC_WSF!$B$9=0,"No WSF data loaded yet. Put files in the inbox folder and run ingest.py.",IF(NOT(CALC_WSF!$B$5),"⚠ Pick "&IF(CALC_WSF!$B$3="Area","an Area","a Zone")&" from SELECT (type part of the name in SEARCH first to narrow the list).",IF(CALC_WSF!$Q$21=0,"No WSF reports in this scope for the selected week.","Numbers compare the selected week with the previous week and with the average of the "&CALC_WSF!$B$11&" weeks before it.")))
B7: GRAND TOTAL ATTENDANCE | D7: ADULTS (M + F) | F7: CHILDREN | H7: % CELLS REPORTING | J7: CELLS REPORTED | L7: AVG PER REPORTING CELL | N7: ZONES WITH NO CELL REPORT
B8: =IF(CALC_WSF!$B$90="","–",CALC_WSF!$B$90) | D8: =IF(CALC_WSF!$B$91="","–",CALC_WSF!$B$91) | F8: =IF(CALC_WSF!$B$94="","–",CALC_WSF!$B$94) | H8: =IF(CALC_WSF!$B$98="","–",CALC_WSF!$B$98) | J8: =IF(CALC_WSF!$B$96="","–",CALC_WSF!$B$96) | L8: =IF(CALC_WSF!$B$100="","–",CALC_WSF!$B$100) | N8: =IF(CALC_WSF!$Q$21=0,"–",CALC_WSF!$B$17)
B9: =IF(CALC_WSF!$E$90="","– vs prev wk",IF(CALC_WSF!$E$90>=0,"▲ ","▼ ")&TEXT(ABS(CALC_WSF!$E$90),"0.0%")&" vs prev wk") | D9: =IF(CALC_WSF!$E$91="","– vs prev wk",IF(CALC_WSF!$E$91>=0,"▲ ","▼ ")&TEXT(ABS(CALC_WSF!$E$91),"0.0%")&" vs prev wk") | F9: =IF(CALC_WSF!$E$94="","– vs prev wk",IF(CALC_WSF!$E$94>=0,"▲ ","▼ ")&TEXT(ABS(CALC_WSF!$E$94),"0.0%")&" vs prev wk") | H9: =IF(CALC_WSF!$D$98="","– vs prev wk",IF(CALC_WSF!$D$98>=0,"▲ ","▼ ")&TEXT(ABS(CALC_WSF!$D$98)*100,"0.0")&" pts vs prev wk") | J9: =IF(CALC_WSF!$E$96="","– vs prev wk",IF(CALC_WSF!$E$96>=0,"▲ ","▼ ")&TEXT(ABS(CALC_WSF!$E$96),"0.0%")&" vs prev wk") | L9: =IF(CALC_WSF!$E$100="","– vs prev wk",IF(CALC_WSF!$E$100>=0,"▲ ","▼ ")&TEXT(ABS(CALC_WSF!$E$100),"0.0%")&" vs prev wk") | N9: =IF(CALC_WSF!$Q$21=0,"","of "&TEXT(COUNTIFS(DATA_WSF!$A:$A,CALC_WSF!$B$10,DATA_WSF!$C:$C,CALC_WSF!$B$6,DATA_WSF!$D:$D,CALC_WSF!$B$7),"#,##0")&" zones")
B10: ="Avg last "&CALC_WSF!$B$11&" wks: "&IF(CALC_WSF!$F$90="","–",TEXT(CALC_WSF!$F$90,"#,##0")) | D10: ="Avg last "&CALC_WSF!$B$11&" wks: "&IF(CALC_WSF!$F$91="","–",TEXT(CALC_WSF!$F$91,"#,##0")) | F10: ="Avg last "&CALC_WSF!$B$11&" wks: "&IF(CALC_WSF!$F$94="","–",TEXT(CALC_WSF!$F$94,"#,##0")) | H10: ="Avg last "&CALC_WSF!$B$11&" wks: "&IF(CALC_WSF!$F$98="","–",TEXT(CALC_WSF!$F$98,"0.0%")) | J10: ="Avg last "&CALC_WSF!$B$11&" wks: "&IF(CALC_WSF!$F$96="","–",TEXT(CALC_WSF!$F$96,"#,##0")) | L10: ="Avg last "&CALC_WSF!$B$11&" wks: "&IF(CALC_WSF!$F$100="","–",TEXT(CALC_WSF!$F$100,"#,##0.0")) | N10: ="Zones where not one cell reported"
B12: Time analysis — selected week against previous week, the N-week average and period-to-date
B13: KPI | D13: Selected week | E13: Previous week | F13: Change | G13: % change | H13: ="Avg last "&CALC_WSF!$B$11&" wks" | I13: ="vs "&CALC_WSF!$B$11&"-wk avg" | J13: MTD total | K13: QTD total | L13: YTD total | M13: Wkly avg (month) | N13: Wkly avg (qtr) | O13: Wkly avg (year)
B14: Grand total attendance | D14: =IF(CALC_WSF!$B$90="","–",CALC_WSF!$B$90) | E14: =IF(CALC_WSF!$C$90="","–",CALC_WSF!$C$90) | F14: =IF(CALC_WSF!$D$90="","–",CALC_WSF!$D$90) | G14: =IF(CALC_WSF!$E$90="","–",CALC_WSF!$E$90) | H14: =IF(CALC_WSF!$F$90="","–",CALC_WSF!$F$90) | I14: =IF(CALC_WSF!$G$90="","–",CALC_WSF!$G$90) | J14: =IF(CALC_WSF!$H$90="","–",CALC_WSF!$H$90) | K14: =IF(CALC_WSF!$I$90="","–",CALC_WSF!$I$90) | L14: =IF(CALC_WSF!$J$90="","–",CALC_WSF!$J$90) | M14: =IF(CALC_WSF!$K$90="","–",CALC_WSF!$K$90) | N14: =IF(CALC_WSF!$L$90="","–",CALC_WSF!$L$90) | O14: =IF(CALC_WSF!$M$90="","–",CALC_WSF!$M$90)
B15: Adult total (Male + Female) | D15: =IF(CALC_WSF!$B$91="","–",CALC_WSF!$B$91) | E15: =IF(CALC_WSF!$C$91="","–",CALC_WSF!$C$91) | F15: =IF(CALC_WSF!$D$91="","–",CALC_WSF!$D$91) | G15: =IF(CALC_WSF!$E$91="","–",CALC_WSF!$E$91) | H15: =IF(CALC_WSF!$F$91="","–",CALC_WSF!$F$91) | I15: =IF(CALC_WSF!$G$91="","–",CALC_WSF!$G$91) | J15: =IF(CALC_WSF!$H$91="","–",CALC_WSF!$H$91) | K15: =IF(CALC_WSF!$I$91="","–",CALC_WSF!$I$91) | L15: =IF(CALC_WSF!$J$91="","–",CALC_WSF!$J$91) | M15: =IF(CALC_WSF!$K$91="","–",CALC_WSF!$K$91) | N15: =IF(CALC_WSF!$L$91="","–",CALC_WSF!$L$91) | O15: =IF(CALC_WSF!$M$91="","–",CALC_WSF!$M$91)
B16: Male | D16: =IF(CALC_WSF!$B$92="","–",CALC_WSF!$B$92) | E16: =IF(CALC_WSF!$C$92="","–",CALC_WSF!$C$92) | F16: =IF(CALC_WSF!$D$92="","–",CALC_WSF!$D$92) | G16: =IF(CALC_WSF!$E$92="","–",CALC_WSF!$E$92) | H16: =IF(CALC_WSF!$F$92="","–",CALC_WSF!$F$92) | I16: =IF(CALC_WSF!$G$92="","–",CALC_WSF!$G$92) | J16: =IF(CALC_WSF!$H$92="","–",CALC_WSF!$H$92) | K16: =IF(CALC_WSF!$I$92="","–",CALC_WSF!$I$92) | L16: =IF(CALC_WSF!$J$92="","–",CALC_WSF!$J$92) | M16: =IF(CALC_WSF!$K$92="","–",CALC_WSF!$K$92) | N16: =IF(CALC_WSF!$L$92="","–",CALC_WSF!$L$92) | O16: =IF(CALC_WSF!$M$92="","–",CALC_WSF!$M$92)
B17: Female | D17: =IF(CALC_WSF!$B$93="","–",CALC_WSF!$B$93) | E17: =IF(CALC_WSF!$C$93="","–",CALC_WSF!$C$93) | F17: =IF(CALC_WSF!$D$93="","–",CALC_WSF!$D$93) | G17: =IF(CALC_WSF!$E$93="","–",CALC_WSF!$E$93) | H17: =IF(CALC_WSF!$F$93="","–",CALC_WSF!$F$93) | I17: =IF(CALC_WSF!$G$93="","–",CALC_WSF!$G$93) | J17: =IF(CALC_WSF!$H$93="","–",CALC_WSF!$H$93) | K17: =IF(CALC_WSF!$I$93="","–",CALC_WSF!$I$93) | L17: =IF(CALC_WSF!$J$93="","–",CALC_WSF!$J$93) | M17: =IF(CALC_WSF!$K$93="","–",CALC_WSF!$K$93) | N17: =IF(CALC_WSF!$L$93="","–",CALC_WSF!$L$93) | O17: =IF(CALC_WSF!$M$93="","–",CALC_WSF!$M$93)
B18: Children | D18: =IF(CALC_WSF!$B$94="","–",CALC_WSF!$B$94) | E18: =IF(CALC_WSF!$C$94="","–",CALC_WSF!$C$94) | F18: =IF(CALC_WSF!$D$94="","–",CALC_WSF!$D$94) | G18: =IF(CALC_WSF!$E$94="","–",CALC_WSF!$E$94) | H18: =IF(CALC_WSF!$F$94="","–",CALC_WSF!$F$94) | I18: =IF(CALC_WSF!$G$94="","–",CALC_WSF!$G$94) | J18: =IF(CALC_WSF!$H$94="","–",CALC_WSF!$H$94) | K18: =IF(CALC_WSF!$I$94="","–",CALC_WSF!$I$94) | L18: =IF(CALC_WSF!$J$94="","–",CALC_WSF!$J$94) | M18: =IF(CALC_WSF!$K$94="","–",CALC_WSF!$K$94) | N18: =IF(CALC_WSF!$L$94="","–",CALC_WSF!$L$94) | O18: =IF(CALC_WSF!$M$94="","–",CALC_WSF!$M$94)
B19: Operational cells | D19: =IF(CALC_WSF!$B$95="","–",CALC_WSF!$B$95) | E19: =IF(CALC_WSF!$C$95="","–",CALC_WSF!$C$95) | F19: =IF(CALC_WSF!$D$95="","–",CALC_WSF!$D$95) | G19: =IF(CALC_WSF!$E$95="","–",CALC_WSF!$E$95) | H19: =IF(CALC_WSF!$F$95="","–",CALC_WSF!$F$95) | I19: =IF(CALC_WSF!$G$95="","–",CALC_WSF!$G$95) | J19: =IF(CALC_WSF!$H$95="","–",CALC_WSF!$H$95) | K19: =IF(CALC_WSF!$I$95="","–",CALC_WSF!$I$95) | L19: =IF(CALC_WSF!$J$95="","–",CALC_WSF!$J$95) | M19: =IF(CALC_WSF!$K$95="","–",CALC_WSF!$K$95) | N19: =IF(CALC_WSF!$L$95="","–",CALC_WSF!$L$95) | O19: =IF(CALC_WSF!$M$95="","–",CALC_WSF!$M$95)
B20: Cells that reported | D20: =IF(CALC_WSF!$B$96="","–",CALC_WSF!$B$96) | E20: =IF(CALC_WSF!$C$96="","–",CALC_WSF!$C$96) | F20: =IF(CALC_WSF!$D$96="","–",CALC_WSF!$D$96) | G20: =IF(CALC_WSF!$E$96="","–",CALC_WSF!$E$96) | H20: =IF(CALC_WSF!$F$96="","–",CALC_WSF!$F$96) | I20: =IF(CALC_WSF!$G$96="","–",CALC_WSF!$G$96) | J20: =IF(CALC_WSF!$H$96="","–",CALC_WSF!$H$96) | K20: =IF(CALC_WSF!$I$96="","–",CALC_WSF!$I$96) | L20: =IF(CALC_WSF!$J$96="","–",CALC_WSF!$J$96) | M20: =IF(CALC_WSF!$K$96="","–",CALC_WSF!$K$96) | N20: =IF(CALC_WSF!$L$96="","–",CALC_WSF!$L$96) | O20: =IF(CALC_WSF!$M$96="","–",CALC_WSF!$M$96)
B21: Cells with no report | D21: =IF(CALC_WSF!$B$97="","–",CALC_WSF!$B$97) | E21: =IF(CALC_WSF!$C$97="","–",CALC_WSF!$C$97) | F21: =IF(CALC_WSF!$D$97="","–",CALC_WSF!$D$97) | G21: =IF(CALC_WSF!$E$97="","–",CALC_WSF!$E$97) | H21: =IF(CALC_WSF!$F$97="","–",CALC_WSF!$F$97) | I21: =IF(CALC_WSF!$G$97="","–",CALC_WSF!$G$97) | J21: =IF(CALC_WSF!$H$97="","–",CALC_WSF!$H$97) | K21: =IF(CALC_WSF!$I$97="","–",CALC_WSF!$I$97) | L21: =IF(CALC_WSF!$J$97="","–",CALC_WSF!$J$97) | M21: =IF(CALC_WSF!$K$97="","–",CALC_WSF!$K$97) | N21: =IF(CALC_WSF!$L$97="","–",CALC_WSF!$L$97) | O21: =IF(CALC_WSF!$M$97="","–",CALC_WSF!$M$97)
B22: % cells reporting | D22: =IF(CALC_WSF!$B$98="","–",CALC_WSF!$B$98) | E22: =IF(CALC_WSF!$C$98="","–",CALC_WSF!$C$98) | F22: =IF(CALC_WSF!$D$98="","–",CALC_WSF!$D$98*100) | G22: =IF(CALC_WSF!$E$98="","–",CALC_WSF!$E$98) | H22: =IF(CALC_WSF!$F$98="","–",CALC_WSF!$F$98) | I22: =IF(CALC_WSF!$G$98="","–",CALC_WSF!$G$98) | J22: =IF(CALC_WSF!$H$98="","–",CALC_WSF!$H$98) | K22: =IF(CALC_WSF!$I$98="","–",CALC_WSF!$I$98) | L22: =IF(CALC_WSF!$J$98="","–",CALC_WSF!$J$98) | M22: =IF(CALC_WSF!$K$98="","–",CALC_WSF!$K$98) | N22: =IF(CALC_WSF!$L$98="","–",CALC_WSF!$L$98) | O22: =IF(CALC_WSF!$M$98="","–",CALC_WSF!$M$98)
B23: Reporting : non-reporting | D23: =IF(CALC_WSF!$B$99="","–",CALC_WSF!$B$99) | E23: =IF(CALC_WSF!$C$99="","–",CALC_WSF!$C$99) | F23: =IF(CALC_WSF!$D$99="","–",CALC_WSF!$D$99) | G23: =IF(CALC_WSF!$E$99="","–",CALC_WSF!$E$99) | H23: =IF(CALC_WSF!$F$99="","–",CALC_WSF!$F$99) | I23: =IF(CALC_WSF!$G$99="","–",CALC_WSF!$G$99) | J23: =IF(CALC_WSF!$H$99="","–",CALC_WSF!$H$99) | K23: =IF(CALC_WSF!$I$99="","–",CALC_WSF!$I$99) | L23: =IF(CALC_WSF!$J$99="","–",CALC_WSF!$J$99) | M23: =IF(CALC_WSF!$K$99="","–",CALC_WSF!$K$99) | N23: =IF(CALC_WSF!$L$99="","–",CALC_WSF!$L$99) | O23: =IF(CALC_WSF!$M$99="","–",CALC_WSF!$M$99)
B24: Avg attendance per reporting cell | D24: =IF(CALC_WSF!$B$100="","–",CALC_WSF!$B$100) | E24: =IF(CALC_WSF!$C$100="","–",CALC_WSF!$C$100) | F24: =IF(CALC_WSF!$D$100="","–",CALC_WSF!$D$100) | G24: =IF(CALC_WSF!$E$100="","–",CALC_WSF!$E$100) | H24: =IF(CALC_WSF!$F$100="","–",CALC_WSF!$F$100) | I24: =IF(CALC_WSF!$G$100="","–",CALC_WSF!$G$100) | J24: =IF(CALC_WSF!$H$100="","–",CALC_WSF!$H$100) | K24: =IF(CALC_WSF!$I$100="","–",CALC_WSF!$I$100) | L24: =IF(CALC_WSF!$J$100="","–",CALC_WSF!$J$100) | M24: =IF(CALC_WSF!$K$100="","–",CALC_WSF!$K$100) | N24: =IF(CALC_WSF!$L$100="","–",CALC_WSF!$L$100) | O24: =IF(CALC_WSF!$M$100="","–",CALC_WSF!$M$100)
B25: Averages use only weeks that have data. MTD/QTD/YTD run to the selected week; for ratio rows the period columns show the ratio of the period's totals. Cell counts in period columns are cell-weeks.
B27: Trends
B44: Area rankings — selected week | O44: Growth = selected week vs previous week
B45: Top 10 · attendance | D45: Bottom 10 · attendance | F45: Top 10 · % reporting | H45: Bottom 10 · % reporting | J45: Top 10 · growth | L45: Bottom 10 · growth | N45: Selected Area rank
B46: =IF(CALC_WSF!$B$3="Zone","n/a at Zone scope",IF(CALC_WSF!$AJ$3="","–",1&". "&CALC_WSF!$AJ$3)) | C46: =IF(OR(CALC_WSF!$B$3="Zone",CALC_WSF!$AJ$3=""),"",CALC_WSF!$AK$3) | D46: =IF(CALC_WSF!$B$3="Zone","n/a at Zone scope",IF(CALC_WSF!$AL$3="","–",1&". "&CALC_WSF!$AL$3)) | E46: =IF(OR(CALC_WSF!$B$3="Zone",CALC_WSF!$AL$3=""),"",CALC_WSF!$AM$3) | F46: =IF(CALC_WSF!$B$3="Zone","n/a at Zone scope",IF(CALC_WSF!$AN$3="","–",1&". "&CALC_WSF!$AN$3)) | G46: =IF(OR(CALC_WSF!$B$3="Zone",CALC_WSF!$AN$3=""),"",CALC_WSF!$AO$3) | H46: =IF(CALC_WSF!$B$3="Zone","n/a at Zone scope",IF(CALC_WSF!$AP$3="","–",1&". "&CALC_WSF!$AP$3)) | I46: =IF(OR(CALC_WSF!$B$3="Zone",CALC_WSF!$AP$3=""),"",CALC_WSF!$AQ$3) | J46: =IF(CALC_WSF!$B$3="Zone","n/a at Zone scope",IF(CALC_WSF!$AR$3="","–",1&". "&CALC_WSF!$AR$3)) | K46: =IF(OR(CALC_WSF!$B$3="Zone",CALC_WSF!$AR$3=""),"",CALC_WSF!$AS$3) | L46: =IF(CALC_WSF!$B$3="Zone","n/a at Zone scope",IF(CALC_WSF!$AT$3="","–",1&". "&CALC_WSF!$AT$3)) | M46: =IF(OR(CALC_WSF!$B$3="Zone",CALC_WSF!$AT$3=""),"",CALC_WSF!$AU$3) | N46: Attendance | O46: =IF(CALC_WSF!$B$3<>"Area","n/a",IF(CALC_WSF!$AJ$15="","–",CALC_WSF!$AJ$15&" of "&CALC_WSF!$AJ$18))
B47: =IF(CALC_WSF!$B$3="Zone","",IF(CALC_WSF!$AJ$4="","",2&". "&CALC_WSF!$AJ$4)) | C47: =IF(OR(CALC_WSF!$B$3="Zone",CALC_WSF!$AJ$4=""),"",CALC_WSF!$AK$4) | D47: =IF(CALC_WSF!$B$3="Zone","",IF(CALC_WSF!$AL$4="","",2&". "&CALC_WSF!$AL$4)) | E47: =IF(OR(CALC_WSF!$B$3="Zone",CALC_WSF!$AL$4=""),"",CALC_WSF!$AM$4) | F47: =IF(CALC_WSF!$B$3="Zone","",IF(CALC_WSF!$AN$4="","",2&". "&CALC_WSF!$AN$4)) | G47: =IF(OR(CALC_WSF!$B$3="Zone",CALC_WSF!$AN$4=""),"",CALC_WSF!$AO$4) | H47: =IF(CALC_WSF!$B$3="Zone","",IF(CALC_WSF!$AP$4="","",2&". "&CALC_WSF!$AP$4)) | I47: =IF(OR(CALC_WSF!$B$3="Zone",CALC_WSF!$AP$4=""),"",CALC_WSF!$AQ$4) | J47: =IF(CALC_WSF!$B$3="Zone","",IF(CALC_WSF!$AR$4="","",2&". "&CALC_WSF!$AR$4)) | K47: =IF(OR(CALC_WSF!$B$3="Zone",CALC_WSF!$AR$4=""),"",CALC_WSF!$AS$4) | L47: =IF(CALC_WSF!$B$3="Zone","",IF(CALC_WSF!$AT$4="","",2&". "&CALC_WSF!$AT$4)) | M47: =IF(OR(CALC_WSF!$B$3="Zone",CALC_WSF!$AT$4=""),"",CALC_WSF!$AU$4) | N47: % reporting | O47: =IF(CALC_WSF!$B$3<>"Area","n/a",IF(CALC_WSF!$AJ$16="","–",CALC_WSF!$AJ$16&" of "&CALC_WSF!$AJ$18))
B48: =IF(CALC_WSF!$B$3="Zone","",IF(CALC_WSF!$AJ$5="","",3&". "&CALC_WSF!$AJ$5)) | C48: =IF(OR(CALC_WSF!$B$3="Zone",CALC_WSF!$AJ$5=""),"",CALC_WSF!$AK$5) | D48: =IF(CALC_WSF!$B$3="Zone","",IF(CALC_WSF!$AL$5="","",3&". "&CALC_WSF!$AL$5)) | E48: =IF(OR(CALC_WSF!$B$3="Zone",CALC_WSF!$AL$5=""),"",CALC_WSF!$AM$5) | F48: =IF(CALC_WSF!$B$3="Zone","",IF(CALC_WSF!$AN$5="","",3&". "&CALC_WSF!$AN$5)) | G48: =IF(OR(CALC_WSF!$B$3="Zone",CALC_WSF!$AN$5=""),"",CALC_WSF!$AO$5) | H48: =IF(CALC_WSF!$B$3="Zone","",IF(CALC_WSF!$AP$5="","",3&". "&CALC_WSF!$AP$5)) | I48: =IF(OR(CALC_WSF!$B$3="Zone",CALC_WSF!$AP$5=""),"",CALC_WSF!$AQ$5) | J48: =IF(CALC_WSF!$B$3="Zone","",IF(CALC_WSF!$AR$5="","",3&". "&CALC_WSF!$AR$5)) | K48: =IF(OR(CALC_WSF!$B$3="Zone",CALC_WSF!$AR$5=""),"",CALC_WSF!$AS$5) | L48: =IF(CALC_WSF!$B$3="Zone","",IF(CALC_WSF!$AT$5="","",3&". "&CALC_WSF!$AT$5)) | M48: =IF(OR(CALC_WSF!$B$3="Zone",CALC_WSF!$AT$5=""),"",CALC_WSF!$AU$5) | N48: Growth | O48: =IF(CALC_WSF!$B$3<>"Area","n/a",IF(CALC_WSF!$AJ$17="","–",CALC_WSF!$AJ$17&" of "&CALC_WSF!$AJ$18))
B49: =IF(CALC_WSF!$B$3="Zone","",IF(CALC_WSF!$AJ$6="","",4&". "&CALC_WSF!$AJ$6)) | C49: =IF(OR(CALC_WSF!$B$3="Zone",CALC_WSF!$AJ$6=""),"",CALC_WSF!$AK$6) | D49: =IF(CALC_WSF!$B$3="Zone","",IF(CALC_WSF!$AL$6="","",4&". "&CALC_WSF!$AL$6)) | E49: =IF(OR(CALC_WSF!$B$3="Zone",CALC_WSF!$AL$6=""),"",CALC_WSF!$AM$6) | F49: =IF(CALC_WSF!$B$3="Zone","",IF(CALC_WSF!$AN$6="","",4&". "&CALC_WSF!$AN$6)) | G49: =IF(OR(CALC_WSF!$B$3="Zone",CALC_WSF!$AN$6=""),"",CALC_WSF!$AO$6) | H49: =IF(CALC_WSF!$B$3="Zone","",IF(CALC_WSF!$AP$6="","",4&". "&CALC_WSF!$AP$6)) | I49: =IF(OR(CALC_WSF!$B$3="Zone",CALC_WSF!$AP$6=""),"",CALC_WSF!$AQ$6) | J49: =IF(CALC_WSF!$B$3="Zone","",IF(CALC_WSF!$AR$6="","",4&". "&CALC_WSF!$AR$6)) | K49: =IF(OR(CALC_WSF!$B$3="Zone",CALC_WSF!$AR$6=""),"",CALC_WSF!$AS$6) | L49: =IF(CALC_WSF!$B$3="Zone","",IF(CALC_WSF!$AT$6="","",4&". "&CALC_WSF!$AT$6)) | M49: =IF(OR(CALC_WSF!$B$3="Zone",CALC_WSF!$AT$6=""),"",CALC_WSF!$AU$6)
B50: =IF(CALC_WSF!$B$3="Zone","",IF(CALC_WSF!$AJ$7="","",5&". "&CALC_WSF!$AJ$7)) | C50: =IF(OR(CALC_WSF!$B$3="Zone",CALC_WSF!$AJ$7=""),"",CALC_WSF!$AK$7) | D50: =IF(CALC_WSF!$B$3="Zone","",IF(CALC_WSF!$AL$7="","",5&". "&CALC_WSF!$AL$7)) | E50: =IF(OR(CALC_WSF!$B$3="Zone",CALC_WSF!$AL$7=""),"",CALC_WSF!$AM$7) | F50: =IF(CALC_WSF!$B$3="Zone","",IF(CALC_WSF!$AN$7="","",5&". "&CALC_WSF!$AN$7)) | G50: =IF(OR(CALC_WSF!$B$3="Zone",CALC_WSF!$AN$7=""),"",CALC_WSF!$AO$7) | H50: =IF(CALC_WSF!$B$3="Zone","",IF(CALC_WSF!$AP$7="","",5&". "&CALC_WSF!$AP$7)) | I50: =IF(OR(CALC_WSF!$B$3="Zone",CALC_WSF!$AP$7=""),"",CALC_WSF!$AQ$7) | J50: =IF(CALC_WSF!$B$3="Zone","",IF(CALC_WSF!$AR$7="","",5&". "&CALC_WSF!$AR$7)) | K50: =IF(OR(CALC_WSF!$B$3="Zone",CALC_WSF!$AR$7=""),"",CALC_WSF!$AS$7) | L50: =IF(CALC_WSF!$B$3="Zone","",IF(CALC_WSF!$AT$7="","",5&". "&CALC_WSF!$AT$7)) | M50: =IF(OR(CALC_WSF!$B$3="Zone",CALC_WSF!$AT$7=""),"",CALC_WSF!$AU$7) | N50: Shown when Scope = Area. Rank 1 = highest.
B51: =IF(CALC_WSF!$B$3="Zone","",IF(CALC_WSF!$AJ$8="","",6&". "&CALC_WSF!$AJ$8)) | C51: =IF(OR(CALC_WSF!$B$3="Zone",CALC_WSF!$AJ$8=""),"",CALC_WSF!$AK$8) | D51: =IF(CALC_WSF!$B$3="Zone","",IF(CALC_WSF!$AL$8="","",6&". "&CALC_WSF!$AL$8)) | E51: =IF(OR(CALC_WSF!$B$3="Zone",CALC_WSF!$AL$8=""),"",CALC_WSF!$AM$8) | F51: =IF(CALC_WSF!$B$3="Zone","",IF(CALC_WSF!$AN$8="","",6&". "&CALC_WSF!$AN$8)) | G51: =IF(OR(CALC_WSF!$B$3="Zone",CALC_WSF!$AN$8=""),"",CALC_WSF!$AO$8) | H51: =IF(CALC_WSF!$B$3="Zone","",IF(CALC_WSF!$AP$8="","",6&". "&CALC_WSF!$AP$8)) | I51: =IF(OR(CALC_WSF!$B$3="Zone",CALC_WSF!$AP$8=""),"",CALC_WSF!$AQ$8) | J51: =IF(CALC_WSF!$B$3="Zone","",IF(CALC_WSF!$AR$8="","",6&". "&CALC_WSF!$AR$8)) | K51: =IF(OR(CALC_WSF!$B$3="Zone",CALC_WSF!$AR$8=""),"",CALC_WSF!$AS$8) | L51: =IF(CALC_WSF!$B$3="Zone","",IF(CALC_WSF!$AT$8="","",6&". "&CALC_WSF!$AT$8)) | M51: =IF(OR(CALC_WSF!$B$3="Zone",CALC_WSF!$AT$8=""),"",CALC_WSF!$AU$8)
B52: =IF(CALC_WSF!$B$3="Zone","",IF(CALC_WSF!$AJ$9="","",7&". "&CALC_WSF!$AJ$9)) | C52: =IF(OR(CALC_WSF!$B$3="Zone",CALC_WSF!$AJ$9=""),"",CALC_WSF!$AK$9) | D52: =IF(CALC_WSF!$B$3="Zone","",IF(CALC_WSF!$AL$9="","",7&". "&CALC_WSF!$AL$9)) | E52: =IF(OR(CALC_WSF!$B$3="Zone",CALC_WSF!$AL$9=""),"",CALC_WSF!$AM$9) | F52: =IF(CALC_WSF!$B$3="Zone","",IF(CALC_WSF!$AN$9="","",7&". "&CALC_WSF!$AN$9)) | G52: =IF(OR(CALC_WSF!$B$3="Zone",CALC_WSF!$AN$9=""),"",CALC_WSF!$AO$9) | H52: =IF(CALC_WSF!$B$3="Zone","",IF(CALC_WSF!$AP$9="","",7&". "&CALC_WSF!$AP$9)) | I52: =IF(OR(CALC_WSF!$B$3="Zone",CALC_WSF!$AP$9=""),"",CALC_WSF!$AQ$9) | J52: =IF(CALC_WSF!$B$3="Zone","",IF(CALC_WSF!$AR$9="","",7&". "&CALC_WSF!$AR$9)) | K52: =IF(OR(CALC_WSF!$B$3="Zone",CALC_WSF!$AR$9=""),"",CALC_WSF!$AS$9) | L52: =IF(CALC_WSF!$B$3="Zone","",IF(CALC_WSF!$AT$9="","",7&". "&CALC_WSF!$AT$9)) | M52: =IF(OR(CALC_WSF!$B$3="Zone",CALC_WSF!$AT$9=""),"",CALC_WSF!$AU$9)
B53: =IF(CALC_WSF!$B$3="Zone","",IF(CALC_WSF!$AJ$10="","",8&". "&CALC_WSF!$AJ$10)) | C53: =IF(OR(CALC_WSF!$B$3="Zone",CALC_WSF!$AJ$10=""),"",CALC_WSF!$AK$10) | D53: =IF(CALC_WSF!$B$3="Zone","",IF(CALC_WSF!$AL$10="","",8&". "&CALC_WSF!$AL$10)) | E53: =IF(OR(CALC_WSF!$B$3="Zone",CALC_WSF!$AL$10=""),"",CALC_WSF!$AM$10) | F53: =IF(CALC_WSF!$B$3="Zone","",IF(CALC_WSF!$AN$10="","",8&". "&CALC_WSF!$AN$10)) | G53: =IF(OR(CALC_WSF!$B$3="Zone",CALC_WSF!$AN$10=""),"",CALC_WSF!$AO$10) | H53: =IF(CALC_WSF!$B$3="Zone","",IF(CALC_WSF!$AP$10="","",8&". "&CALC_WSF!$AP$10)) | I53: =IF(OR(CALC_WSF!$B$3="Zone",CALC_WSF!$AP$10=""),"",CALC_WSF!$AQ$10) | J53: =IF(CALC_WSF!$B$3="Zone","",IF(CALC_WSF!$AR$10="","",8&". "&CALC_WSF!$AR$10)) | K53: =IF(OR(CALC_WSF!$B$3="Zone",CALC_WSF!$AR$10=""),"",CALC_WSF!$AS$10) | L53: =IF(CALC_WSF!$B$3="Zone","",IF(CALC_WSF!$AT$10="","",8&". "&CALC_WSF!$AT$10)) | M53: =IF(OR(CALC_WSF!$B$3="Zone",CALC_WSF!$AT$10=""),"",CALC_WSF!$AU$10)
B54: =IF(CALC_WSF!$B$3="Zone","",IF(CALC_WSF!$AJ$11="","",9&". "&CALC_WSF!$AJ$11)) | C54: =IF(OR(CALC_WSF!$B$3="Zone",CALC_WSF!$AJ$11=""),"",CALC_WSF!$AK$11) | D54: =IF(CALC_WSF!$B$3="Zone","",IF(CALC_WSF!$AL$11="","",9&". "&CALC_WSF!$AL$11)) | E54: =IF(OR(CALC_WSF!$B$3="Zone",CALC_WSF!$AL$11=""),"",CALC_WSF!$AM$11) | F54: =IF(CALC_WSF!$B$3="Zone","",IF(CALC_WSF!$AN$11="","",9&". "&CALC_WSF!$AN$11)) | G54: =IF(OR(CALC_WSF!$B$3="Zone",CALC_WSF!$AN$11=""),"",CALC_WSF!$AO$11) | H54: =IF(CALC_WSF!$B$3="Zone","",IF(CALC_WSF!$AP$11="","",9&". "&CALC_WSF!$AP$11)) | I54: =IF(OR(CALC_WSF!$B$3="Zone",CALC_WSF!$AP$11=""),"",CALC_WSF!$AQ$11) | J54: =IF(CALC_WSF!$B$3="Zone","",IF(CALC_WSF!$AR$11="","",9&". "&CALC_WSF!$AR$11)) | K54: =IF(OR(CALC_WSF!$B$3="Zone",CALC_WSF!$AR$11=""),"",CALC_WSF!$AS$11) | L54: =IF(CALC_WSF!$B$3="Zone","",IF(CALC_WSF!$AT$11="","",9&". "&CALC_WSF!$AT$11)) | M54: =IF(OR(CALC_WSF!$B$3="Zone",CALC_WSF!$AT$11=""),"",CALC_WSF!$AU$11)
B55: =IF(CALC_WSF!$B$3="Zone","",IF(CALC_WSF!$AJ$12="","",10&". "&CALC_WSF!$AJ$12)) | C55: =IF(OR(CALC_WSF!$B$3="Zone",CALC_WSF!$AJ$12=""),"",CALC_WSF!$AK$12) | D55: =IF(CALC_WSF!$B$3="Zone","",IF(CALC_WSF!$AL$12="","",10&". "&CALC_WSF!$AL$12)) | E55: =IF(OR(CALC_WSF!$B$3="Zone",CALC_WSF!$AL$12=""),"",CALC_WSF!$AM$12) | F55: =IF(CALC_WSF!$B$3="Zone","",IF(CALC_WSF!$AN$12="","",10&". "&CALC_WSF!$AN$12)) | G55: =IF(OR(CALC_WSF!$B$3="Zone",CALC_WSF!$AN$12=""),"",CALC_WSF!$AO$12) | H55: =IF(CALC_WSF!$B$3="Zone","",IF(CALC_WSF!$AP$12="","",10&". "&CALC_WSF!$AP$12)) | I55: =IF(OR(CALC_WSF!$B$3="Zone",CALC_WSF!$AP$12=""),"",CALC_WSF!$AQ$12) | J55: =IF(CALC_WSF!$B$3="Zone","",IF(CALC_WSF!$AR$12="","",10&". "&CALC_WSF!$AR$12)) | K55: =IF(OR(CALC_WSF!$B$3="Zone",CALC_WSF!$AR$12=""),"",CALC_WSF!$AS$12) | L55: =IF(CALC_WSF!$B$3="Zone","",IF(CALC_WSF!$AT$12="","",10&". "&CALC_WSF!$AT$12)) | M55: =IF(OR(CALC_WSF!$B$3="Zone",CALC_WSF!$AT$12=""),"",CALC_WSF!$AU$12)
B57: Who didn't report — cells with no WSF return for the selected week
B58: =IF(NOT(CALC_WSF!$AX$2),"Cell-level detail is kept in the workbook for the latest "&8&" weeks only; older weeks are in the archive folder (WSF_cells_YYYY.csv).",TEXT(CALC_WSF!$AX$1,"#,##0")&" cells did not report in this scope"&IF(CALC_WSF!$AX$1>50," — showing the first 50. Narrow with Scope = Area or Zone.",".")&" Zones where no cell reported: "&TEXT(CALC_WSF!$B$17,"#,##0")&".")
B59: Area | E59: Zone | I59: Cell | K59: Week ending
B60: =CALC_WSF!$AX$4 | E60: =CALC_WSF!$AY$4 | I60: =CALC_WSF!$AZ$4 | K60: =IF(CALC_WSF!$AW$4="","",CALC_WSF!$B$10)
B61: =CALC_WSF!$AX$5 | E61: =CALC_WSF!$AY$5 | I61: =CALC_WSF!$AZ$5 | K61: =IF(CALC_WSF!$AW$5="","",CALC_WSF!$B$10)
B62: =CALC_WSF!$AX$6 | E62: =CALC_WSF!$AY$6 | I62: =CALC_WSF!$AZ$6 | K62: =IF(CALC_WSF!$AW$6="","",CALC_WSF!$B$10)
B63: =CALC_WSF!$AX$7 | E63: =CALC_WSF!$AY$7 | I63: =CALC_WSF!$AZ$7 | K63: =IF(CALC_WSF!$AW$7="","",CALC_WSF!$B$10)
B64: =CALC_WSF!$AX$8 | E64: =CALC_WSF!$AY$8 | I64: =CALC_WSF!$AZ$8 | K64: =IF(CALC_WSF!$AW$8="","",CALC_WSF!$B$10)
B65: =CALC_WSF!$AX$9 | E65: =CALC_WSF!$AY$9 | I65: =CALC_WSF!$AZ$9 | K65: =IF(CALC_WSF!$AW$9="","",CALC_WSF!$B$10)
B66: =CALC_WSF!$AX$10 | E66: =CALC_WSF!$AY$10 | I66: =CALC_WSF!$AZ$10 | K66: =IF(CALC_WSF!$AW$10="","",CALC_WSF!$B$10)
B67: =CALC_WSF!$AX$11 | E67: =CALC_WSF!$AY$11 | I67: =CALC_WSF!$AZ$11 | K67: =IF(CALC_WSF!$AW$11="","",CALC_WSF!$B$10)
B68: =CALC_WSF!$AX$12 | E68: =CALC_WSF!$AY$12 | I68: =CALC_WSF!$AZ$12 | K68: =IF(CALC_WSF!$AW$12="","",CALC_WSF!$B$10)
B69: =CALC_WSF!$AX$13 | E69: =CALC_WSF!$AY$13 | I69: =CALC_WSF!$AZ$13 | K69: =IF(CALC_WSF!$AW$13="","",CALC_WSF!$B$10)
B70: =CALC_WSF!$AX$14 | E70: =CALC_WSF!$AY$14 | I70: =CALC_WSF!$AZ$14 | K70: =IF(CALC_WSF!$AW$14="","",CALC_WSF!$B$10)
B71: =CALC_WSF!$AX$15 | E71: =CALC_WSF!$AY$15 | I71: =CALC_WSF!$AZ$15 | K71: =IF(CALC_WSF!$AW$15="","",CALC_WSF!$B$10)
B72: =CALC_WSF!$AX$16 | E72: =CALC_WSF!$AY$16 | I72: =CALC_WSF!$AZ$16 | K72: =IF(CALC_WSF!$AW$16="","",CALC_WSF!$B$10)
B73: =CALC_WSF!$AX$17 | E73: =CALC_WSF!$AY$17 | I73: =CALC_WSF!$AZ$17 | K73: =IF(CALC_WSF!$AW$17="","",CALC_WSF!$B$10)
B74: =CALC_WSF!$AX$18 | E74: =CALC_WSF!$AY$18 | I74: =CALC_WSF!$AZ$18 | K74: =IF(CALC_WSF!$AW$18="","",CALC_WSF!$B$10)
B75: =CALC_WSF!$AX$19 | E75: =CALC_WSF!$AY$19 | I75: =CALC_WSF!$AZ$19 | K75: =IF(CALC_WSF!$AW$19="","",CALC_WSF!$B$10)
B76: =CALC_WSF!$AX$20 | E76: =CALC_WSF!$AY$20 | I76: =CALC_WSF!$AZ$20 | K76: =IF(CALC_WSF!$AW$20="","",CALC_WSF!$B$10)
B77: =CALC_WSF!$AX$21 | E77: =CALC_WSF!$AY$21 | I77: =CALC_WSF!$AZ$21 | K77: =IF(CALC_WSF!$AW$21="","",CALC_WSF!$B$10)
B78: =CALC_WSF!$AX$22 | E78: =CALC_WSF!$AY$22 | I78: =CALC_WSF!$AZ$22 | K78: =IF(CALC_WSF!$AW$22="","",CALC_WSF!$B$10)
B79: =CALC_WSF!$AX$23 | E79: =CALC_WSF!$AY$23 | I79: =CALC_WSF!$AZ$23 | K79: =IF(CALC_WSF!$AW$23="","",CALC_WSF!$B$10)
B80: =CALC_WSF!$AX$24 | E80: =CALC_WSF!$AY$24 | I80: =CALC_WSF!$AZ$24 | K80: =IF(CALC_WSF!$AW$24="","",CALC_WSF!$B$10)
B81: =CALC_WSF!$AX$25 | E81: =CALC_WSF!$AY$25 | I81: =CALC_WSF!$AZ$25 | K81: =IF(CALC_WSF!$AW$25="","",CALC_WSF!$B$10)
B82: =CALC_WSF!$AX$26 | E82: =CALC_WSF!$AY$26 | I82: =CALC_WSF!$AZ$26 | K82: =IF(CALC_WSF!$AW$26="","",CALC_WSF!$B$10)
B83: =CALC_WSF!$AX$27 | E83: =CALC_WSF!$AY$27 | I83: =CALC_WSF!$AZ$27 | K83: =IF(CALC_WSF!$AW$27="","",CALC_WSF!$B$10)
B84: =CALC_WSF!$AX$28 | E84: =CALC_WSF!$AY$28 | I84: =CALC_WSF!$AZ$28 | K84: =IF(CALC_WSF!$AW$28="","",CALC_WSF!$B$10)
B85: =CALC_WSF!$AX$29 | E85: =CALC_WSF!$AY$29 | I85: =CALC_WSF!$AZ$29 | K85: =IF(CALC_WSF!$AW$29="","",CALC_WSF!$B$10)
B86: =CALC_WSF!$AX$30 | E86: =CALC_WSF!$AY$30 | I86: =CALC_WSF!$AZ$30 | K86: =IF(CALC_WSF!$AW$30="","",CALC_WSF!$B$10)
B87: =CALC_WSF!$AX$31 | E87: =CALC_WSF!$AY$31 | I87: =CALC_WSF!$AZ$31 | K87: =IF(CALC_WSF!$AW$31="","",CALC_WSF!$B$10)
B88: =CALC_WSF!$AX$32 | E88: =CALC_WSF!$AY$32 | I88: =CALC_WSF!$AZ$32 | K88: =IF(CALC_WSF!$AW$32="","",CALC_WSF!$B$10)
B89: =CALC_WSF!$AX$33 | E89: =CALC_WSF!$AY$33 | I89: =CALC_WSF!$AZ$33 | K89: =IF(CALC_WSF!$AW$33="","",CALC_WSF!$B$10)
B90: =CALC_WSF!$AX$34 | E90: =CALC_WSF!$AY$34 | I90: =CALC_WSF!$AZ$34 | K90: =IF(CALC_WSF!$AW$34="","",CALC_WSF!$B$10)
B91: =CALC_WSF!$AX$35 | E91: =CALC_WSF!$AY$35 | I91: =CALC_WSF!$AZ$35 | K91: =IF(CALC_WSF!$AW$35="","",CALC_WSF!$B$10)
B92: =CALC_WSF!$AX$36 | E92: =CALC_WSF!$AY$36 | I92: =CALC_WSF!$AZ$36 | K92: =IF(CALC_WSF!$AW$36="","",CALC_WSF!$B$10)
B93: =CALC_WSF!$AX$37 | E93: =CALC_WSF!$AY$37 | I93: =CALC_WSF!$AZ$37 | K93: =IF(CALC_WSF!$AW$37="","",CALC_WSF!$B$10)
B94: =CALC_WSF!$AX$38 | E94: =CALC_WSF!$AY$38 | I94: =CALC_WSF!$AZ$38 | K94: =IF(CALC_WSF!$AW$38="","",CALC_WSF!$B$10)
B95: =CALC_WSF!$AX$39 | E95: =CALC_WSF!$AY$39 | I95: =CALC_WSF!$AZ$39 | K95: =IF(CALC_WSF!$AW$39="","",CALC_WSF!$B$10)
B96: =CALC_WSF!$AX$40 | E96: =CALC_WSF!$AY$40 | I96: =CALC_WSF!$AZ$40 | K96: =IF(CALC_WSF!$AW$40="","",CALC_WSF!$B$10)
B97: =CALC_WSF!$AX$41 | E97: =CALC_WSF!$AY$41 | I97: =CALC_WSF!$AZ$41 | K97: =IF(CALC_WSF!$AW$41="","",CALC_WSF!$B$10)
B98: =CALC_WSF!$AX$42 | E98: =CALC_WSF!$AY$42 | I98: =CALC_WSF!$AZ$42 | K98: =IF(CALC_WSF!$AW$42="","",CALC_WSF!$B$10)
B99: =CALC_WSF!$AX$43 | E99: =CALC_WSF!$AY$43 | I99: =CALC_WSF!$AZ$43 | K99: =IF(CALC_WSF!$AW$43="","",CALC_WSF!$B$10)
B100: =CALC_WSF!$AX$44 | E100: =CALC_WSF!$AY$44 | I100: =CALC_WSF!$AZ$44 | K100: =IF(CALC_WSF!$AW$44="","",CALC_WSF!$B$10)
B101: =CALC_WSF!$AX$45 | E101: =CALC_WSF!$AY$45 | I101: =CALC_WSF!$AZ$45 | K101: =IF(CALC_WSF!$AW$45="","",CALC_WSF!$B$10)
B102: =CALC_WSF!$AX$46 | E102: =CALC_WSF!$AY$46 | I102: =CALC_WSF!$AZ$46 | K102: =IF(CALC_WSF!$AW$46="","",CALC_WSF!$B$10)
B103: =CALC_WSF!$AX$47 | E103: =CALC_WSF!$AY$47 | I103: =CALC_WSF!$AZ$47 | K103: =IF(CALC_WSF!$AW$47="","",CALC_WSF!$B$10)
B104: =CALC_WSF!$AX$48 | E104: =CALC_WSF!$AY$48 | I104: =CALC_WSF!$AZ$48 | K104: =IF(CALC_WSF!$AW$48="","",CALC_WSF!$B$10)
B105: =CALC_WSF!$AX$49 | E105: =CALC_WSF!$AY$49 | I105: =CALC_WSF!$AZ$49 | K105: =IF(CALC_WSF!$AW$49="","",CALC_WSF!$B$10)
B106: =CALC_WSF!$AX$50 | E106: =CALC_WSF!$AY$50 | I106: =CALC_WSF!$AZ$50 | K106: =IF(CALC_WSF!$AW$50="","",CALC_WSF!$B$10)
B107: =CALC_WSF!$AX$51 | E107: =CALC_WSF!$AY$51 | I107: =CALC_WSF!$AZ$51 | K107: =IF(CALC_WSF!$AW$51="","",CALC_WSF!$B$10)
B108: =CALC_WSF!$AX$52 | E108: =CALC_WSF!$AY$52 | I108: =CALC_WSF!$AZ$52 | K108: =IF(CALC_WSF!$AW$52="","",CALC_WSF!$B$10)
B109: =CALC_WSF!$AX$53 | E109: =CALC_WSF!$AY$53 | I109: =CALC_WSF!$AZ$53 | K109: =IF(CALC_WSF!$AW$53="","",CALC_WSF!$B$10)

Sheet MIDWEEK DASHBOARD
B1: MIDWEEK DASHBOARD | N1: ⌂ HOME
B2: Zonal midweek services
B4: Stage 2: this dashboard is built after the WSF DASHBOARD is reviewed, using the same control strip, KPI cards, time analysis, rankings and non-reporting layout. Its data is already loaded in the DATA_MIDWEEK sheet.

Sheet CHOP DASHBOARD
B1: CHOP DASHBOARD | N1: ⌂ HOME
B2: Covenant Hour of Prayer (CHOP zones only)
B4: Stage 2: this dashboard is built after the WSF DASHBOARD is reviewed, using the same control strip, KPI cards, time analysis, rankings and non-reporting layout. Its data is already loaded in the DATA_CHOP sheet.

Sheet COMMUNITY CHURCH DASHBOARD
B1: COMMUNITY CHURCH DASHBOARD | N1: ⌂ HOME
B2: 35 Community Churches · Sunday service first
B4: Stage 2: this dashboard is built after the WSF DASHBOARD is reviewed, using the same control strip, KPI cards, time analysis, rankings and non-reporting layout. Its data is already loaded in the DATA_COMMUNITY sheet.

Sheet TRANSPORT DASHBOARD
B1: TRANSPORT DASHBOARD | N1: ⌂ HOME
B2: FT Procured (hired LT) · church coasters · EV/TATA · WSF Procured (member-paid) · riders, seats, spend and optimisation
B3: SCOPE | C3: SEARCH (type part of a name) | E3: SELECT AREA / ZONE ▼ | H3: STREAM | I3: WEEK ENDING ▼ | K3: COMPARE (WEEKS) | L3: SHOWING
B4: Global | H4: Transport | I4: Latest | K4: 4 | L4: =CALC_TRANSPORT!$B$16&IF(CALC_TRANSPORT!$B$10=0,""," · w/e "&TEXT(CALC_TRANSPORT!$B$10,"dd mmm yyyy"))&" · "&CALC_TRANSPORT!$B$11&"-wk window"
B5: =IF(CALC_TRANSPORT!$B$9=0,"No transport reports loaded yet. Put the weekly transport files in the inbox and run ingest.py.",IF(NOT(CALC_TRANSPORT!$B$5),"⚠ Pick "&IF(CALC_TRANSPORT!$B$3="Area","an Area","a Zone")&" from SELECT (type part of the name in SEARCH first).",IF(CALC_TRANSPORT!$B$3="Zone","Zone scope shows FT Procured and WSF Procured only (coasters, EV/TATA, fuel and budget are by Area).",IF(CALC_TRANSPORT!$X$21=0,"No transport reports in this scope for the selected week.","Utilisation = riders ÷ seats offered, on buses whose capacity is known. Spend = hire cost + coaster fuel paid (hubs only)."))))
B7: RIDERS CARRIED | D7: BUSES THAT RAN | F7: SEAT UTILISATION | H7: TOTAL SPEND | J7: COST PER RIDER | L7: FT SPEND vs BUDGET | N7: BREAKDOWNS
B8: =IF(CALC_TRANSPORT!$B$90="","–",CALC_TRANSPORT!$B$90) | D8: =IF(CALC_TRANSPORT!$B$91="","–",CALC_TRANSPORT!$B$91) | F8: =IF(CALC_TRANSPORT!$B$95="","–",CALC_TRANSPORT!$B$95) | H8: =IF(CALC_TRANSPORT!$B$96="","–",CALC_TRANSPORT!$B$96) | J8: =IF(CALC_TRANSPORT!$B$100="","–",CALC_TRANSPORT!$B$100) | L8: =IF(CALC_TRANSPORT!$B$103="","–",CALC_TRANSPORT!$B$103) | N8: =IF(CALC_TRANSPORT!$B$104="","–",CALC_TRANSPORT!$B$104)
B9: =IF(CALC_TRANSPORT!$E$90="","– vs prev wk",IF(CALC_TRANSPORT!$E$90>=0,"▲ ","▼ ")&TEXT(ABS(CALC_TRANSPORT!$E$90),"0.0%")&" vs prev wk") | D9: =IF(CALC_TRANSPORT!$E$91="","– vs prev wk",IF(CALC_TRANSPORT!$E$91>=0,"▲ ","▼ ")&TEXT(ABS(CALC_TRANSPORT!$E$91),"0.0%")&" vs prev wk") | F9: =IF(CALC_TRANSPORT!$D$95="","– vs prev wk",IF(CALC_TRANSPORT!$D$95>=0,"▲ ","▼ ")&TEXT(ABS(CALC_TRANSPORT!$D$95)*100,"0.0")&" pts vs prev wk") | H9: =IF(CALC_TRANSPORT!$E$96="","– vs prev wk",IF(CALC_TRANSPORT!$E$96>=0,"▲ ","▼ ")&TEXT(ABS(CALC_TRANSPORT!$E$96),"0.0%")&" vs prev wk") | J9: =IF(CALC_TRANSPORT!$E$100="","– vs prev wk",IF(CALC_TRANSPORT!$E$100>=0,"▲ ","▼ ")&TEXT(ABS(CALC_TRANSPORT!$E$100),"0.0%")&" vs prev wk") | L9: =IF(CALC_TRANSPORT!$D$103="","– vs prev wk",IF(CALC_TRANSPORT!$D$103>=0,"▲ ","▼ ")&TEXT(ABS(CALC_TRANSPORT!$D$103)*100,"0.0")&" pts vs prev wk") | N9: =IF(CALC_TRANSPORT!$E$104="","– vs prev wk",IF(CALC_TRANSPORT!$E$104>=0,"▲ ","▼ ")&TEXT(ABS(CALC_TRANSPORT!$E$104),"0.0%")&" vs prev wk")
B10: ="Avg last "&CALC_TRANSPORT!$B$11&" wks: "&IF(CALC_TRANSPORT!$F$90="","–",TEXT(CALC_TRANSPORT!$F$90,"#,##0")) | D10: ="Avg last "&CALC_TRANSPORT!$B$11&" wks: "&IF(CALC_TRANSPORT!$F$91="","–",TEXT(CALC_TRANSPORT!$F$91,"#,##0")) | F10: ="Avg last "&CALC_TRANSPORT!$B$11&" wks: "&IF(CALC_TRANSPORT!$F$95="","–",TEXT(CALC_TRANSPORT!$F$95,"0.0%")) | H10: ="Avg last "&CALC_TRANSPORT!$B$11&" wks: "&IF(CALC_TRANSPORT!$F$96="","–","₦"&TEXT(CALC_TRANSPORT!$F$96,"#,##0")) | J10: ="Avg last "&CALC_TRANSPORT!$B$11&" wks: "&IF(CALC_TRANSPORT!$F$100="","–","₦"&TEXT(CALC_TRANSPORT!$F$100,"#,##0.00")) | L10: ="Avg last "&CALC_TRANSPORT!$B$11&" wks: "&IF(CALC_TRANSPORT!$F$103="","–",TEXT(CALC_TRANSPORT!$F$103,"0.0%")) | N10: ="Avg last "&CALC_TRANSPORT!$B$11&" wks: "&IF(CALC_TRANSPORT!$F$104="","–",TEXT(CALC_TRANSPORT!$F$104,"#,##0"))
B12: By bus category — selected week | O12: Cost per rider shows where money works hardest
B13: Category | D13: Listed | E13: Ran | F13: % ran | G13: Riders | H13: Seats | I13: Utilisation | J13: Spend | K13: Cost / rider | L13: Cost / bus | M13: Cost / seat | N13: Riders WoW | O13: Paid by
B14: =CALC_TRANSPORT!$A$110 | D14: =IF(CALC_TRANSPORT!$B$110="","–",CALC_TRANSPORT!$B$110) | E14: =IF(CALC_TRANSPORT!$C$110="","–",CALC_TRANSPORT!$C$110) | F14: =IF(CALC_TRANSPORT!$D$110="","–",CALC_TRANSPORT!$D$110) | G14: =IF(CALC_TRANSPORT!$E$110="","–",CALC_TRANSPORT!$E$110) | H14: =IF(CALC_TRANSPORT!$F$110="","–",CALC_TRANSPORT!$F$110) | I14: =IF(CALC_TRANSPORT!$H$110="","–",CALC_TRANSPORT!$H$110) | J14: =IF(CALC_TRANSPORT!$K$110="","–",CALC_TRANSPORT!$K$110) | K14: =IF(CALC_TRANSPORT!$L$110="","–",CALC_TRANSPORT!$L$110) | L14: =IF(CALC_TRANSPORT!$M$110="","–",CALC_TRANSPORT!$M$110) | M14: =IF(CALC_TRANSPORT!$N$110="","–",CALC_TRANSPORT!$N$110) | N14: =IF(CALC_TRANSPORT!$P$110="","–",CALC_TRANSPORT!$P$110) | O14: =CALC_TRANSPORT!$Q$110
B15: =CALC_TRANSPORT!$A$111 | D15: =IF(CALC_TRANSPORT!$B$111="","–",CALC_TRANSPORT!$B$111) | E15: =IF(CALC_TRANSPORT!$C$111="","–",CALC_TRANSPORT!$C$111) | F15: =IF(CALC_TRANSPORT!$D$111="","–",CALC_TRANSPORT!$D$111) | G15: =IF(CALC_TRANSPORT!$E$111="","–",CALC_TRANSPORT!$E$111) | H15: =IF(CALC_TRANSPORT!$F$111="","–",CALC_TRANSPORT!$F$111) | I15: =IF(CALC_TRANSPORT!$H$111="","–",CALC_TRANSPORT!$H$111) | J15: =IF(CALC_TRANSPORT!$K$111="","–",CALC_TRANSPORT!$K$111) | K15: =IF(CALC_TRANSPORT!$L$111="","–",CALC_TRANSPORT!$L$111) | L15: =IF(CALC_TRANSPORT!$M$111="","–",CALC_TRANSPORT!$M$111) | M15: =IF(CALC_TRANSPORT!$N$111="","–",CALC_TRANSPORT!$N$111) | N15: =IF(CALC_TRANSPORT!$P$111="","–",CALC_TRANSPORT!$P$111) | O15: =CALC_TRANSPORT!$Q$111
B16: =CALC_TRANSPORT!$A$112 | D16: =IF(CALC_TRANSPORT!$B$112="","–",CALC_TRANSPORT!$B$112) | E16: =IF(CALC_TRANSPORT!$C$112="","–",CALC_TRANSPORT!$C$112) | F16: =IF(CALC_TRANSPORT!$D$112="","–",CALC_TRANSPORT!$D$112) | G16: =IF(CALC_TRANSPORT!$E$112="","–",CALC_TRANSPORT!$E$112) | H16: =IF(CALC_TRANSPORT!$F$112="","–",CALC_TRANSPORT!$F$112) | I16: =IF(CALC_TRANSPORT!$H$112="","–",CALC_TRANSPORT!$H$112) | J16: =IF(CALC_TRANSPORT!$K$112="","–",CALC_TRANSPORT!$K$112) | K16: =IF(CALC_TRANSPORT!$L$112="","–",CALC_TRANSPORT!$L$112) | L16: =IF(CALC_TRANSPORT!$M$112="","–",CALC_TRANSPORT!$M$112) | M16: =IF(CALC_TRANSPORT!$N$112="","–",CALC_TRANSPORT!$N$112) | N16: =IF(CALC_TRANSPORT!$P$112="","–",CALC_TRANSPORT!$P$112) | O16: =CALC_TRANSPORT!$Q$112
B17: =CALC_TRANSPORT!$A$113 | D17: =IF(CALC_TRANSPORT!$B$113="","–",CALC_TRANSPORT!$B$113) | E17: =IF(CALC_TRANSPORT!$C$113="","–",CALC_TRANSPORT!$C$113) | F17: =IF(CALC_TRANSPORT!$D$113="","–",CALC_TRANSPORT!$D$113) | G17: =IF(CALC_TRANSPORT!$E$113="","–",CALC_TRANSPORT!$E$113) | H17: =IF(CALC_TRANSPORT!$F$113="","–",CALC_TRANSPORT!$F$113) | I17: =IF(CALC_TRANSPORT!$H$113="","–",CALC_TRANSPORT!$H$113) | J17: =IF(CALC_TRANSPORT!$K$113="","–",CALC_TRANSPORT!$K$113) | K17: =IF(CALC_TRANSPORT!$L$113="","–",CALC_TRANSPORT!$L$113) | L17: =IF(CALC_TRANSPORT!$M$113="","–",CALC_TRANSPORT!$M$113) | M17: =IF(CALC_TRANSPORT!$N$113="","–",CALC_TRANSPORT!$N$113) | N17: =IF(CALC_TRANSPORT!$P$113="","–",CALC_TRANSPORT!$P$113) | O17: =CALC_TRANSPORT!$Q$113
B18: =CALC_TRANSPORT!$A$114 | D18: =IF(CALC_TRANSPORT!$B$114="","–",CALC_TRANSPORT!$B$114) | E18: =IF(CALC_TRANSPORT!$C$114="","–",CALC_TRANSPORT!$C$114) | F18: =IF(CALC_TRANSPORT!$D$114="","–",CALC_TRANSPORT!$D$114) | G18: =IF(CALC_TRANSPORT!$E$114="","–",CALC_TRANSPORT!$E$114) | H18: =IF(CALC_TRANSPORT!$F$114="","–",CALC_TRANSPORT!$F$114) | I18: =IF(CALC_TRANSPORT!$H$114="","–",CALC_TRANSPORT!$H$114) | J18: =IF(CALC_TRANSPORT!$K$114="","–",CALC_TRANSPORT!$K$114) | K18: =IF(CALC_TRANSPORT!$L$114="","–",CALC_TRANSPORT!$L$114) | L18: =IF(CALC_TRANSPORT!$M$114="","–",CALC_TRANSPORT!$M$114) | M18: =IF(CALC_TRANSPORT!$N$114="","–",CALC_TRANSPORT!$N$114) | N18: =IF(CALC_TRANSPORT!$P$114="","–",CALC_TRANSPORT!$P$114) | O18: =CALC_TRANSPORT!$Q$114
B20: Time analysis — selected week against previous week, the N-week average and period-to-date
B21: KPI | D21: Selected week | E21: Previous week | F21: Change | G21: % change | H21: ="Avg last "&CALC_TRANSPORT!$B$11&" wks" | I21: ="vs "&CALC_TRANSPORT!$B$11&"-wk avg" | J21: MTD total | K21: QTD total | L21: YTD total | M21: Wkly avg (month) | N21: Wkly avg (qtr) | O21: Wkly avg (year)
B22: Riders carried | D22: =IF(CALC_TRANSPORT!$B$90="","–",CALC_TRANSPORT!$B$90) | E22: =IF(CALC_TRANSPORT!$C$90="","–",CALC_TRANSPORT!$C$90) | F22: =IF(CALC_TRANSPORT!$D$90="","–",CALC_TRANSPORT!$D$90) | G22: =IF(CALC_TRANSPORT!$E$90="","–",CALC_TRANSPORT!$E$90) | H22: =IF(CALC_TRANSPORT!$F$90="","–",CALC_TRANSPORT!$F$90) | I22: =IF(CALC_TRANSPORT!$G$90="","–",CALC_TRANSPORT!$G$90) | J22: =IF(CALC_TRANSPORT!$H$90="","–",CALC_TRANSPORT!$H$90) | K22: =IF(CALC_TRANSPORT!$I$90="","–",CALC_TRANSPORT!$I$90) | L22: =IF(CALC_TRANSPORT!$J$90="","–",CALC_TRANSPORT!$J$90) | M22: =IF(CALC_TRANSPORT!$K$90="","–",CALC_TRANSPORT!$K$90) | N22: =IF(CALC_TRANSPORT!$L$90="","–",CALC_TRANSPORT!$L$90) | O22: =IF(CALC_TRANSPORT!$M$90="","–",CALC_TRANSPORT!$M$90)
B23: Buses that ran | D23: =IF(CALC_TRANSPORT!$B$91="","–",CALC_TRANSPORT!$B$91) | E23: =IF(CALC_TRANSPORT!$C$91="","–",CALC_TRANSPORT!$C$91) | F23: =IF(CALC_TRANSPORT!$D$91="","–",CALC_TRANSPORT!$D$91) | G23: =IF(CALC_TRANSPORT!$E$91="","–",CALC_TRANSPORT!$E$91) | H23: =IF(CALC_TRANSPORT!$F$91="","–",CALC_TRANSPORT!$F$91) | I23: =IF(CALC_TRANSPORT!$G$91="","–",CALC_TRANSPORT!$G$91) | J23: =IF(CALC_TRANSPORT!$H$91="","–",CALC_TRANSPORT!$H$91) | K23: =IF(CALC_TRANSPORT!$I$91="","–",CALC_TRANSPORT!$I$91) | L23: =IF(CALC_TRANSPORT!$J$91="","–",CALC_TRANSPORT!$J$91) | M23: =IF(CALC_TRANSPORT!$K$91="","–",CALC_TRANSPORT!$K$91) | N23: =IF(CALC_TRANSPORT!$L$91="","–",CALC_TRANSPORT!$L$91) | O23: =IF(CALC_TRANSPORT!$M$91="","–",CALC_TRANSPORT!$M$91)
B24: Buses listed in reports | D24: =IF(CALC_TRANSPORT!$B$92="","–",CALC_TRANSPORT!$B$92) | E24: =IF(CALC_TRANSPORT!$C$92="","–",CALC_TRANSPORT!$C$92) | F24: =IF(CALC_TRANSPORT!$D$92="","–",CALC_TRANSPORT!$D$92) | G24: =IF(CALC_TRANSPORT!$E$92="","–",CALC_TRANSPORT!$E$92) | H24: =IF(CALC_TRANSPORT!$F$92="","–",CALC_TRANSPORT!$F$92) | I24: =IF(CALC_TRANSPORT!$G$92="","–",CALC_TRANSPORT!$G$92) | J24: =IF(CALC_TRANSPORT!$H$92="","–",CALC_TRANSPORT!$H$92) | K24: =IF(CALC_TRANSPORT!$I$92="","–",CALC_TRANSPORT!$I$92) | L24: =IF(CALC_TRANSPORT!$J$92="","–",CALC_TRANSPORT!$J$92) | M24: =IF(CALC_TRANSPORT!$K$92="","–",CALC_TRANSPORT!$K$92) | N24: =IF(CALC_TRANSPORT!$L$92="","–",CALC_TRANSPORT!$L$92) | O24: =IF(CALC_TRANSPORT!$M$92="","–",CALC_TRANSPORT!$M$92)
B25: % buses that ran | D25: =IF(CALC_TRANSPORT!$B$93="","–",CALC_TRANSPORT!$B$93) | E25: =IF(CALC_TRANSPORT!$C$93="","–",CALC_TRANSPORT!$C$93) | F25: =IF(CALC_TRANSPORT!$D$93="","–",CALC_TRANSPORT!$D$93*100) | G25: =IF(CALC_TRANSPORT!$E$93="","–",CALC_TRANSPORT!$E$93) | H25: =IF(CALC_TRANSPORT!$F$93="","–",CALC_TRANSPORT!$F$93) | I25: =IF(CALC_TRANSPORT!$G$93="","–",CALC_TRANSPORT!$G$93) | J25: =IF(CALC_TRANSPORT!$H$93="","–",CALC_TRANSPORT!$H$93) | K25: =IF(CALC_TRANSPORT!$I$93="","–",CALC_TRANSPORT!$I$93) | L25: =IF(CALC_TRANSPORT!$J$93="","–",CALC_TRANSPORT!$J$93) | M25: =IF(CALC_TRANSPORT!$K$93="","–",CALC_TRANSPORT!$K$93) | N25: =IF(CALC_TRANSPORT!$L$93="","–",CALC_TRANSPORT!$L$93) | O25: =IF(CALC_TRANSPORT!$M$93="","–",CALC_TRANSPORT!$M$93)
B26: Seats offered | D26: =IF(CALC_TRANSPORT!$B$94="","–",CALC_TRANSPORT!$B$94) | E26: =IF(CALC_TRANSPORT!$C$94="","–",CALC_TRANSPORT!$C$94) | F26: =IF(CALC_TRANSPORT!$D$94="","–",CALC_TRANSPORT!$D$94) | G26: =IF(CALC_TRANSPORT!$E$94="","–",CALC_TRANSPORT!$E$94) | H26: =IF(CALC_TRANSPORT!$F$94="","–",CALC_TRANSPORT!$F$94) | I26: =IF(CALC_TRANSPORT!$G$94="","–",CALC_TRANSPORT!$G$94) | J26: =IF(CALC_TRANSPORT!$H$94="","–",CALC_TRANSPORT!$H$94) | K26: =IF(CALC_TRANSPORT!$I$94="","–",CALC_TRANSPORT!$I$94) | L26: =IF(CALC_TRANSPORT!$J$94="","–",CALC_TRANSPORT!$J$94) | M26: =IF(CALC_TRANSPORT!$K$94="","–",CALC_TRANSPORT!$K$94) | N26: =IF(CALC_TRANSPORT!$L$94="","–",CALC_TRANSPORT!$L$94) | O26: =IF(CALC_TRANSPORT!$M$94="","–",CALC_TRANSPORT!$M$94)
B27: Seat utilisation % | D27: =IF(CALC_TRANSPORT!$B$95="","–",CALC_TRANSPORT!$B$95) | E27: =IF(CALC_TRANSPORT!$C$95="","–",CALC_TRANSPORT!$C$95) | F27: =IF(CALC_TRANSPORT!$D$95="","–",CALC_TRANSPORT!$D$95*100) | G27: =IF(CALC_TRANSPORT!$E$95="","–",CALC_TRANSPORT!$E$95) | H27: =IF(CALC_TRANSPORT!$F$95="","–",CALC_TRANSPORT!$F$95) | I27: =IF(CALC_TRANSPORT!$G$95="","–",CALC_TRANSPORT!$G$95) | J27: =IF(CALC_TRANSPORT!$H$95="","–",CALC_TRANSPORT!$H$95) | K27: =IF(CALC_TRANSPORT!$I$95="","–",CALC_TRANSPORT!$I$95) | L27: =IF(CALC_TRANSPORT!$J$95="","–",CALC_TRANSPORT!$J$95) | M27: =IF(CALC_TRANSPORT!$K$95="","–",CALC_TRANSPORT!$K$95) | N27: =IF(CALC_TRANSPORT!$L$95="","–",CALC_TRANSPORT!$L$95) | O27: =IF(CALC_TRANSPORT!$M$95="","–",CALC_TRANSPORT!$M$95)
B28: Total spend | D28: =IF(CALC_TRANSPORT!$B$96="","–",CALC_TRANSPORT!$B$96) | E28: =IF(CALC_TRANSPORT!$C$96="","–",CALC_TRANSPORT!$C$96) | F28: =IF(CALC_TRANSPORT!$D$96="","–",CALC_TRANSPORT!$D$96) | G28: =IF(CALC_TRANSPORT!$E$96="","–",CALC_TRANSPORT!$E$96) | H28: =IF(CALC_TRANSPORT!$F$96="","–",CALC_TRANSPORT!$F$96) | I28: =IF(CALC_TRANSPORT!$G$96="","–",CALC_TRANSPORT!$G$96) | J28: =IF(CALC_TRANSPORT!$H$96="","–",CALC_TRANSPORT!$H$96) | K28: =IF(CALC_TRANSPORT!$I$96="","–",CALC_TRANSPORT!$I$96) | L28: =IF(CALC_TRANSPORT!$J$96="","–",CALC_TRANSPORT!$J$96) | M28: =IF(CALC_TRANSPORT!$K$96="","–",CALC_TRANSPORT!$K$96) | N28: =IF(CALC_TRANSPORT!$L$96="","–",CALC_TRANSPORT!$L$96) | O28: =IF(CALC_TRANSPORT!$M$96="","–",CALC_TRANSPORT!$M$96)
B29: Central spend (FT hire + coaster fuel) | D29: =IF(CALC_TRANSPORT!$B$97="","–",CALC_TRANSPORT!$B$97) | E29: =IF(CALC_TRANSPORT!$C$97="","–",CALC_TRANSPORT!$C$97) | F29: =IF(CALC_TRANSPORT!$D$97="","–",CALC_TRANSPORT!$D$97) | G29: =IF(CALC_TRANSPORT!$E$97="","–",CALC_TRANSPORT!$E$97) | H29: =IF(CALC_TRANSPORT!$F$97="","–",CALC_TRANSPORT!$F$97) | I29: =IF(CALC_TRANSPORT!$G$97="","–",CALC_TRANSPORT!$G$97) | J29: =IF(CALC_TRANSPORT!$H$97="","–",CALC_TRANSPORT!$H$97) | K29: =IF(CALC_TRANSPORT!$I$97="","–",CALC_TRANSPORT!$I$97) | L29: =IF(CALC_TRANSPORT!$J$97="","–",CALC_TRANSPORT!$J$97) | M29: =IF(CALC_TRANSPORT!$K$97="","–",CALC_TRANSPORT!$K$97) | N29: =IF(CALC_TRANSPORT!$L$97="","–",CALC_TRANSPORT!$L$97) | O29: =IF(CALC_TRANSPORT!$M$97="","–",CALC_TRANSPORT!$M$97)
B30: Member-paid (WSF Procured) | D30: =IF(CALC_TRANSPORT!$B$98="","–",CALC_TRANSPORT!$B$98) | E30: =IF(CALC_TRANSPORT!$C$98="","–",CALC_TRANSPORT!$C$98) | F30: =IF(CALC_TRANSPORT!$D$98="","–",CALC_TRANSPORT!$D$98) | G30: =IF(CALC_TRANSPORT!$E$98="","–",CALC_TRANSPORT!$E$98) | H30: =IF(CALC_TRANSPORT!$F$98="","–",CALC_TRANSPORT!$F$98) | I30: =IF(CALC_TRANSPORT!$G$98="","–",CALC_TRANSPORT!$G$98) | J30: =IF(CALC_TRANSPORT!$H$98="","–",CALC_TRANSPORT!$H$98) | K30: =IF(CALC_TRANSPORT!$I$98="","–",CALC_TRANSPORT!$I$98) | L30: =IF(CALC_TRANSPORT!$J$98="","–",CALC_TRANSPORT!$J$98) | M30: =IF(CALC_TRANSPORT!$K$98="","–",CALC_TRANSPORT!$K$98) | N30: =IF(CALC_TRANSPORT!$L$98="","–",CALC_TRANSPORT!$L$98) | O30: =IF(CALC_TRANSPORT!$M$98="","–",CALC_TRANSPORT!$M$98)
B31: Coaster fuel paid (hubs) | D31: =IF(CALC_TRANSPORT!$B$99="","–",CALC_TRANSPORT!$B$99) | E31: =IF(CALC_TRANSPORT!$C$99="","–",CALC_TRANSPORT!$C$99) | F31: =IF(CALC_TRANSPORT!$D$99="","–",CALC_TRANSPORT!$D$99) | G31: =IF(CALC_TRANSPORT!$E$99="","–",CALC_TRANSPORT!$E$99) | H31: =IF(CALC_TRANSPORT!$F$99="","–",CALC_TRANSPORT!$F$99) | I31: =IF(CALC_TRANSPORT!$G$99="","–",CALC_TRANSPORT!$G$99) | J31: =IF(CALC_TRANSPORT!$H$99="","–",CALC_TRANSPORT!$H$99) | K31: =IF(CALC_TRANSPORT!$I$99="","–",CALC_TRANSPORT!$I$99) | L31: =IF(CALC_TRANSPORT!$J$99="","–",CALC_TRANSPORT!$J$99) | M31: =IF(CALC_TRANSPORT!$K$99="","–",CALC_TRANSPORT!$K$99) | N31: =IF(CALC_TRANSPORT!$L$99="","–",CALC_TRANSPORT!$L$99) | O31: =IF(CALC_TRANSPORT!$M$99="","–",CALC_TRANSPORT!$M$99)
B32: Cost per rider | D32: =IF(CALC_TRANSPORT!$B$100="","–",CALC_TRANSPORT!$B$100) | E32: =IF(CALC_TRANSPORT!$C$100="","–",CALC_TRANSPORT!$C$100) | F32: =IF(CALC_TRANSPORT!$D$100="","–",CALC_TRANSPORT!$D$100) | G32: =IF(CALC_TRANSPORT!$E$100="","–",CALC_TRANSPORT!$E$100) | H32: =IF(CALC_TRANSPORT!$F$100="","–",CALC_TRANSPORT!$F$100) | I32: =IF(CALC_TRANSPORT!$G$100="","–",CALC_TRANSPORT!$G$100) | J32: =IF(CALC_TRANSPORT!$H$100="","–",CALC_TRANSPORT!$H$100) | K32: =IF(CALC_TRANSPORT!$I$100="","–",CALC_TRANSPORT!$I$100) | L32: =IF(CALC_TRANSPORT!$J$100="","–",CALC_TRANSPORT!$J$100) | M32: =IF(CALC_TRANSPORT!$K$100="","–",CALC_TRANSPORT!$K$100) | N32: =IF(CALC_TRANSPORT!$L$100="","–",CALC_TRANSPORT!$L$100) | O32: =IF(CALC_TRANSPORT!$M$100="","–",CALC_TRANSPORT!$M$100)
B33: Cost per bus that ran | D33: =IF(CALC_TRANSPORT!$B$101="","–",CALC_TRANSPORT!$B$101) | E33: =IF(CALC_TRANSPORT!$C$101="","–",CALC_TRANSPORT!$C$101) | F33: =IF(CALC_TRANSPORT!$D$101="","–",CALC_TRANSPORT!$D$101) | G33: =IF(CALC_TRANSPORT!$E$101="","–",CALC_TRANSPORT!$E$101) | H33: =IF(CALC_TRANSPORT!$F$101="","–",CALC_TRANSPORT!$F$101) | I33: =IF(CALC_TRANSPORT!$G$101="","–",CALC_TRANSPORT!$G$101) | J33: =IF(CALC_TRANSPORT!$H$101="","–",CALC_TRANSPORT!$H$101) | K33: =IF(CALC_TRANSPORT!$I$101="","–",CALC_TRANSPORT!$I$101) | L33: =IF(CALC_TRANSPORT!$J$101="","–",CALC_TRANSPORT!$J$101) | M33: =IF(CALC_TRANSPORT!$K$101="","–",CALC_TRANSPORT!$K$101) | N33: =IF(CALC_TRANSPORT!$L$101="","–",CALC_TRANSPORT!$L$101) | O33: =IF(CALC_TRANSPORT!$M$101="","–",CALC_TRANSPORT!$M$101)
B34: Cost per seat offered | D34: =IF(CALC_TRANSPORT!$B$102="","–",CALC_TRANSPORT!$B$102) | E34: =IF(CALC_TRANSPORT!$C$102="","–",CALC_TRANSPORT!$C$102) | F34: =IF(CALC_TRANSPORT!$D$102="","–",CALC_TRANSPORT!$D$102) | G34: =IF(CALC_TRANSPORT!$E$102="","–",CALC_TRANSPORT!$E$102) | H34: =IF(CALC_TRANSPORT!$F$102="","–",CALC_TRANSPORT!$F$102) | I34: =IF(CALC_TRANSPORT!$G$102="","–",CALC_TRANSPORT!$G$102) | J34: =IF(CALC_TRANSPORT!$H$102="","–",CALC_TRANSPORT!$H$102) | K34: =IF(CALC_TRANSPORT!$I$102="","–",CALC_TRANSPORT!$I$102) | L34: =IF(CALC_TRANSPORT!$J$102="","–",CALC_TRANSPORT!$J$102) | M34: =IF(CALC_TRANSPORT!$K$102="","–",CALC_TRANSPORT!$K$102) | N34: =IF(CALC_TRANSPORT!$L$102="","–",CALC_TRANSPORT!$L$102) | O34: =IF(CALC_TRANSPORT!$M$102="","–",CALC_TRANSPORT!$M$102)
B35: FT spend vs FT budget | D35: =IF(CALC_TRANSPORT!$B$103="","–",CALC_TRANSPORT!$B$103) | E35: =IF(CALC_TRANSPORT!$C$103="","–",CALC_TRANSPORT!$C$103) | F35: =IF(CALC_TRANSPORT!$D$103="","–",CALC_TRANSPORT!$D$103*100) | G35: =IF(CALC_TRANSPORT!$E$103="","–",CALC_TRANSPORT!$E$103) | H35: =IF(CALC_TRANSPORT!$F$103="","–",CALC_TRANSPORT!$F$103) | I35: =IF(CALC_TRANSPORT!$G$103="","–",CALC_TRANSPORT!$G$103) | J35: =IF(CALC_TRANSPORT!$H$103="","–",CALC_TRANSPORT!$H$103) | K35: =IF(CALC_TRANSPORT!$I$103="","–",CALC_TRANSPORT!$I$103) | L35: =IF(CALC_TRANSPORT!$J$103="","–",CALC_TRANSPORT!$J$103) | M35: =IF(CALC_TRANSPORT!$K$103="","–",CALC_TRANSPORT!$K$103) | N35: =IF(CALC_TRANSPORT!$L$103="","–",CALC_TRANSPORT!$L$103) | O35: =IF(CALC_TRANSPORT!$M$103="","–",CALC_TRANSPORT!$M$103)
B36: Breakdowns | D36: =IF(CALC_TRANSPORT!$B$104="","–",CALC_TRANSPORT!$B$104) | E36: =IF(CALC_TRANSPORT!$C$104="","–",CALC_TRANSPORT!$C$104) | F36: =IF(CALC_TRANSPORT!$D$104="","–",CALC_TRANSPORT!$D$104) | G36: =IF(CALC_TRANSPORT!$E$104="","–",CALC_TRANSPORT!$E$104) | H36: =IF(CALC_TRANSPORT!$F$104="","–",CALC_TRANSPORT!$F$104) | I36: =IF(CALC_TRANSPORT!$G$104="","–",CALC_TRANSPORT!$G$104) | J36: =IF(CALC_TRANSPORT!$H$104="","–",CALC_TRANSPORT!$H$104) | K36: =IF(CALC_TRANSPORT!$I$104="","–",CALC_TRANSPORT!$I$104) | L36: =IF(CALC_TRANSPORT!$J$104="","–",CALC_TRANSPORT!$J$104) | M36: =IF(CALC_TRANSPORT!$K$104="","–",CALC_TRANSPORT!$K$104) | N36: =IF(CALC_TRANSPORT!$L$104="","–",CALC_TRANSPORT!$L$104) | O36: =IF(CALC_TRANSPORT!$M$104="","–",CALC_TRANSPORT!$M$104)
B37: Averages use only weeks that have data. MTD/QTD/YTD run to the selected week; ratio rows show the ratio of the period's totals.
B39: Trends — last 13 weeks
B56: Optimisation — selected week, by Area | O56: Thresholds (UtilLow, UtilHigh, UtilLowWeeks) are on SETTINGS
B57: Demand exceeds seats (fullest) | D57: Lowest utilisation | F57: Highest cost per rider | H57: FT spend over budget | J57: Most riders | L57: Plain-language flags
B58: =IF(CALC_TRANSPORT!$B$3="Zone",IF(0=0,"n/a at Zone scope",""),IF(CALC_TRANSPORT!$BD$3="",IF(0=0,"–",""),1&". "&CALC_TRANSPORT!$BD$3)) | C58: =IF(OR(CALC_TRANSPORT!$B$3="Zone",CALC_TRANSPORT!$BD$3=""),"",CALC_TRANSPORT!$BE$3) | D58: =IF(CALC_TRANSPORT!$B$3="Zone",IF(0=0,"n/a at Zone scope",""),IF(CALC_TRANSPORT!$BF$3="",IF(0=0,"–",""),1&". "&CALC_TRANSPORT!$BF$3)) | E58: =IF(OR(CALC_TRANSPORT!$B$3="Zone",CALC_TRANSPORT!$BF$3=""),"",CALC_TRANSPORT!$BG$3) | F58: =IF(CALC_TRANSPORT!$B$3="Zone",IF(0=0,"n/a at Zone scope",""),IF(CALC_TRANSPORT!$BH$3="",IF(0=0,"–",""),1&". "&CALC_TRANSPORT!$BH$3)) | G58: =IF(OR(CALC_TRANSPORT!$B$3="Zone",CALC_TRANSPORT!$BH$3=""),"",CALC_TRANSPORT!$BI$3) | H58: =IF(CALC_TRANSPORT!$B$3="Zone",IF(0=0,"n/a at Zone scope",""),IF(CALC_TRANSPORT!$BJ$3="",IF(0=0,"–",""),1&". "&CALC_TRANSPORT!$BJ$3)) | I58: =IF(OR(CALC_TRANSPORT!$B$3="Zone",CALC_TRANSPORT!$BJ$3=""),"",CALC_TRANSPORT!$BK$3) | J58: =IF(CALC_TRANSPORT!$B$3="Zone",IF(0=0,"n/a at Zone scope",""),IF(CALC_TRANSPORT!$BL$3="",IF(0=0,"–",""),1&". "&CALC_TRANSPORT!$BL$3)) | K58: =IF(OR(CALC_TRANSPORT!$B$3="Zone",CALC_TRANSPORT!$BL$3=""),"",CALC_TRANSPORT!$BM$3) | L58: =IF(CALC_TRANSPORT!$B$3="Zone",IF(0=0,"n/a at Zone scope",""),IF(CALC_TRANSPORT!$BN$3="",IF(0=0,"No flags this week",""),"• "&CALC_TRANSPORT!$BN$3))
B59: =IF(CALC_TRANSPORT!$B$3="Zone",IF(1=0,"n/a at Zone scope",""),IF(CALC_TRANSPORT!$BD$4="",IF(1=0,"–",""),2&". "&CALC_TRANSPORT!$BD$4)) | C59: =IF(OR(CALC_TRANSPORT!$B$3="Zone",CALC_TRANSPORT!$BD$4=""),"",CALC_TRANSPORT!$BE$4) | D59: =IF(CALC_TRANSPORT!$B$3="Zone",IF(1=0,"n/a at Zone scope",""),IF(CALC_TRANSPORT!$BF$4="",IF(1=0,"–",""),2&". "&CALC_TRANSPORT!$BF$4)) | E59: =IF(OR(CALC_TRANSPORT!$B$3="Zone",CALC_TRANSPORT!$BF$4=""),"",CALC_TRANSPORT!$BG$4) | F59: =IF(CALC_TRANSPORT!$B$3="Zone",IF(1=0,"n/a at Zone scope",""),IF(CALC_TRANSPORT!$BH$4="",IF(1=0,"–",""),2&". "&CALC_TRANSPORT!$BH$4)) | G59: =IF(OR(CALC_TRANSPORT!$B$3="Zone",CALC_TRANSPORT!$BH$4=""),"",CALC_TRANSPORT!$BI$4) | H59: =IF(CALC_TRANSPORT!$B$3="Zone",IF(1=0,"n/a at Zone scope",""),IF(CALC_TRANSPORT!$BJ$4="",IF(1=0,"–",""),2&". "&CALC_TRANSPORT!$BJ$4)) | I59: =IF(OR(CALC_TRANSPORT!$B$3="Zone",CALC_TRANSPORT!$BJ$4=""),"",CALC_TRANSPORT!$BK$4) | J59: =IF(CALC_TRANSPORT!$B$3="Zone",IF(1=0,"n/a at Zone scope",""),IF(CALC_TRANSPORT!$BL$4="",IF(1=0,"–",""),2&". "&CALC_TRANSPORT!$BL$4)) | K59: =IF(OR(CALC_TRANSPORT!$B$3="Zone",CALC_TRANSPORT!$BL$4=""),"",CALC_TRANSPORT!$BM$4) | L59: =IF(CALC_TRANSPORT!$B$3="Zone",IF(1=0,"n/a at Zone scope",""),IF(CALC_TRANSPORT!$BN$4="",IF(1=0,"No flags this week",""),"• "&CALC_TRANSPORT!$BN$4))
B60: =IF(CALC_TRANSPORT!$B$3="Zone",IF(2=0,"n/a at Zone scope",""),IF(CALC_TRANSPORT!$BD$5="",IF(2=0,"–",""),3&". "&CALC_TRANSPORT!$BD$5)) | C60: =IF(OR(CALC_TRANSPORT!$B$3="Zone",CALC_TRANSPORT!$BD$5=""),"",CALC_TRANSPORT!$BE$5) | D60: =IF(CALC_TRANSPORT!$B$3="Zone",IF(2=0,"n/a at Zone scope",""),IF(CALC_TRANSPORT!$BF$5="",IF(2=0,"–",""),3&". "&CALC_TRANSPORT!$BF$5)) | E60: =IF(OR(CALC_TRANSPORT!$B$3="Zone",CALC_TRANSPORT!$BF$5=""),"",CALC_TRANSPORT!$BG$5) | F60: =IF(CALC_TRANSPORT!$B$3="Zone",IF(2=0,"n/a at Zone scope",""),IF(CALC_TRANSPORT!$BH$5="",IF(2=0,"–",""),3&". "&CALC_TRANSPORT!$BH$5)) | G60: =IF(OR(CALC_TRANSPORT!$B$3="Zone",CALC_TRANSPORT!$BH$5=""),"",CALC_TRANSPORT!$BI$5) | H60: =IF(CALC_TRANSPORT!$B$3="Zone",IF(2=0,"n/a at Zone scope",""),IF(CALC_TRANSPORT!$BJ$5="",IF(2=0,"–",""),3&". "&CALC_TRANSPORT!$BJ$5)) | I60: =IF(OR(CALC_TRANSPORT!$B$3="Zone",CALC_TRANSPORT!$BJ$5=""),"",CALC_TRANSPORT!$BK$5) | J60: =IF(CALC_TRANSPORT!$B$3="Zone",IF(2=0,"n/a at Zone scope",""),IF(CALC_TRANSPORT!$BL$5="",IF(2=0,"–",""),3&". "&CALC_TRANSPORT!$BL$5)) | K60: =IF(OR(CALC_TRANSPORT!$B$3="Zone",CALC_TRANSPORT!$BL$5=""),"",CALC_TRANSPORT!$BM$5) | L60: =IF(CALC_TRANSPORT!$B$3="Zone",IF(2=0,"n/a at Zone scope",""),IF(CALC_TRANSPORT!$BN$5="",IF(2=0,"No flags this week",""),"• "&CALC_TRANSPORT!$BN$5))
B61: =IF(CALC_TRANSPORT!$B$3="Zone",IF(3=0,"n/a at Zone scope",""),IF(CALC_TRANSPORT!$BD$6="",IF(3=0,"–",""),4&". "&CALC_TRANSPORT!$BD$6)) | C61: =IF(OR(CALC_TRANSPORT!$B$3="Zone",CALC_TRANSPORT!$BD$6=""),"",CALC_TRANSPORT!$BE$6) | D61: =IF(CALC_TRANSPORT!$B$3="Zone",IF(3=0,"n/a at Zone scope",""),IF(CALC_TRANSPORT!$BF$6="",IF(3=0,"–",""),4&". "&CALC_TRANSPORT!$BF$6)) | E61: =IF(OR(CALC_TRANSPORT!$B$3="Zone",CALC_TRANSPORT!$BF$6=""),"",CALC_TRANSPORT!$BG$6) | F61: =IF(CALC_TRANSPORT!$B$3="Zone",IF(3=0,"n/a at Zone scope",""),IF(CALC_TRANSPORT!$BH$6="",IF(3=0,"–",""),4&". "&CALC_TRANSPORT!$BH$6)) | G61: =IF(OR(CALC_TRANSPORT!$B$3="Zone",CALC_TRANSPORT!$BH$6=""),"",CALC_TRANSPORT!$BI$6) | H61: =IF(CALC_TRANSPORT!$B$3="Zone",IF(3=0,"n/a at Zone scope",""),IF(CALC_TRANSPORT!$BJ$6="",IF(3=0,"–",""),4&". "&CALC_TRANSPORT!$BJ$6)) | I61: =IF(OR(CALC_TRANSPORT!$B$3="Zone",CALC_TRANSPORT!$BJ$6=""),"",CALC_TRANSPORT!$BK$6) | J61: =IF(CALC_TRANSPORT!$B$3="Zone",IF(3=0,"n/a at Zone scope",""),IF(CALC_TRANSPORT!$BL$6="",IF(3=0,"–",""),4&". "&CALC_TRANSPORT!$BL$6)) | K61: =IF(OR(CALC_TRANSPORT!$B$3="Zone",CALC_TRANSPORT!$BL$6=""),"",CALC_TRANSPORT!$BM$6) | L61: =IF(CALC_TRANSPORT!$B$3="Zone",IF(3=0,"n/a at Zone scope",""),IF(CALC_TRANSPORT!$BN$6="",IF(3=0,"No flags this week",""),"• "&CALC_TRANSPORT!$BN$6))
B62: =IF(CALC_TRANSPORT!$B$3="Zone",IF(4=0,"n/a at Zone scope",""),IF(CALC_TRANSPORT!$BD$7="",IF(4=0,"–",""),5&". "&CALC_TRANSPORT!$BD$7)) | C62: =IF(OR(CALC_TRANSPORT!$B$3="Zone",CALC_TRANSPORT!$BD$7=""),"",CALC_TRANSPORT!$BE$7) | D62: =IF(CALC_TRANSPORT!$B$3="Zone",IF(4=0,"n/a at Zone scope",""),IF(CALC_TRANSPORT!$BF$7="",IF(4=0,"–",""),5&". "&CALC_TRANSPORT!$BF$7)) | E62: =IF(OR(CALC_TRANSPORT!$B$3="Zone",CALC_TRANSPORT!$BF$7=""),"",CALC_TRANSPORT!$BG$7) | F62: =IF(CALC_TRANSPORT!$B$3="Zone",IF(4=0,"n/a at Zone scope",""),IF(CALC_TRANSPORT!$BH$7="",IF(4=0,"–",""),5&". "&CALC_TRANSPORT!$BH$7)) | G62: =IF(OR(CALC_TRANSPORT!$B$3="Zone",CALC_TRANSPORT!$BH$7=""),"",CALC_TRANSPORT!$BI$7) | H62: =IF(CALC_TRANSPORT!$B$3="Zone",IF(4=0,"n/a at Zone scope",""),IF(CALC_TRANSPORT!$BJ$7="",IF(4=0,"–",""),5&". "&CALC_TRANSPORT!$BJ$7)) | I62: =IF(OR(CALC_TRANSPORT!$B$3="Zone",CALC_TRANSPORT!$BJ$7=""),"",CALC_TRANSPORT!$BK$7) | J62: =IF(CALC_TRANSPORT!$B$3="Zone",IF(4=0,"n/a at Zone scope",""),IF(CALC_TRANSPORT!$BL$7="",IF(4=0,"–",""),5&". "&CALC_TRANSPORT!$BL$7)) | K62: =IF(OR(CALC_TRANSPORT!$B$3="Zone",CALC_TRANSPORT!$BL$7=""),"",CALC_TRANSPORT!$BM$7) | L62: =IF(CALC_TRANSPORT!$B$3="Zone",IF(4=0,"n/a at Zone scope",""),IF(CALC_TRANSPORT!$BN$7="",IF(4=0,"No flags this week",""),"• "&CALC_TRANSPORT!$BN$7))
B63: =IF(CALC_TRANSPORT!$B$3="Zone",IF(5=0,"n/a at Zone scope",""),IF(CALC_TRANSPORT!$BD$8="",IF(5=0,"–",""),6&". "&CALC_TRANSPORT!$BD$8)) | C63: =IF(OR(CALC_TRANSPORT!$B$3="Zone",CALC_TRANSPORT!$BD$8=""),"",CALC_TRANSPORT!$BE$8) | D63: =IF(CALC_TRANSPORT!$B$3="Zone",IF(5=0,"n/a at Zone scope",""),IF(CALC_TRANSPORT!$BF$8="",IF(5=0,"–",""),6&". "&CALC_TRANSPORT!$BF$8)) | E63: =IF(OR(CALC_TRANSPORT!$B$3="Zone",CALC_TRANSPORT!$BF$8=""),"",CALC_TRANSPORT!$BG$8) | F63: =IF(CALC_TRANSPORT!$B$3="Zone",IF(5=0,"n/a at Zone scope",""),IF(CALC_TRANSPORT!$BH$8="",IF(5=0,"–",""),6&". "&CALC_TRANSPORT!$BH$8)) | G63: =IF(OR(CALC_TRANSPORT!$B$3="Zone",CALC_TRANSPORT!$BH$8=""),"",CALC_TRANSPORT!$BI$8) | H63: =IF(CALC_TRANSPORT!$B$3="Zone",IF(5=0,"n/a at Zone scope",""),IF(CALC_TRANSPORT!$BJ$8="",IF(5=0,"–",""),6&". "&CALC_TRANSPORT!$BJ$8)) | I63: =IF(OR(CALC_TRANSPORT!$B$3="Zone",CALC_TRANSPORT!$BJ$8=""),"",CALC_TRANSPORT!$BK$8) | J63: =IF(CALC_TRANSPORT!$B$3="Zone",IF(5=0,"n/a at Zone scope",""),IF(CALC_TRANSPORT!$BL$8="",IF(5=0,"–",""),6&". "&CALC_TRANSPORT!$BL$8)) | K63: =IF(OR(CALC_TRANSPORT!$B$3="Zone",CALC_TRANSPORT!$BL$8=""),"",CALC_TRANSPORT!$BM$8) | L63: =IF(CALC_TRANSPORT!$B$3="Zone",IF(5=0,"n/a at Zone scope",""),IF(CALC_TRANSPORT!$BN$8="",IF(5=0,"No flags this week",""),"• "&CALC_TRANSPORT!$BN$8))
B64: =IF(CALC_TRANSPORT!$B$3="Zone",IF(6=0,"n/a at Zone scope",""),IF(CALC_TRANSPORT!$BD$9="",IF(6=0,"–",""),7&". "&CALC_TRANSPORT!$BD$9)) | C64: =IF(OR(CALC_TRANSPORT!$B$3="Zone",CALC_TRANSPORT!$BD$9=""),"",CALC_TRANSPORT!$BE$9) | D64: =IF(CALC_TRANSPORT!$B$3="Zone",IF(6=0,"n/a at Zone scope",""),IF(CALC_TRANSPORT!$BF$9="",IF(6=0,"–",""),7&". "&CALC_TRANSPORT!$BF$9)) | E64: =IF(OR(CALC_TRANSPORT!$B$3="Zone",CALC_TRANSPORT!$BF$9=""),"",CALC_TRANSPORT!$BG$9) | F64: =IF(CALC_TRANSPORT!$B$3="Zone",IF(6=0,"n/a at Zone scope",""),IF(CALC_TRANSPORT!$BH$9="",IF(6=0,"–",""),7&". "&CALC_TRANSPORT!$BH$9)) | G64: =IF(OR(CALC_TRANSPORT!$B$3="Zone",CALC_TRANSPORT!$BH$9=""),"",CALC_TRANSPORT!$BI$9) | H64: =IF(CALC_TRANSPORT!$B$3="Zone",IF(6=0,"n/a at Zone scope",""),IF(CALC_TRANSPORT!$BJ$9="",IF(6=0,"–",""),7&". "&CALC_TRANSPORT!$BJ$9)) | I64: =IF(OR(CALC_TRANSPORT!$B$3="Zone",CALC_TRANSPORT!$BJ$9=""),"",CALC_TRANSPORT!$BK$9) | J64: =IF(CALC_TRANSPORT!$B$3="Zone",IF(6=0,"n/a at Zone scope",""),IF(CALC_TRANSPORT!$BL$9="",IF(6=0,"–",""),7&". "&CALC_TRANSPORT!$BL$9)) | K64: =IF(OR(CALC_TRANSPORT!$B$3="Zone",CALC_TRANSPORT!$BL$9=""),"",CALC_TRANSPORT!$BM$9) | L64: =IF(CALC_TRANSPORT!$B$3="Zone",IF(6=0,"n/a at Zone scope",""),IF(CALC_TRANSPORT!$BN$9="",IF(6=0,"No flags this week",""),"• "&CALC_TRANSPORT!$BN$9))
B65: =IF(CALC_TRANSPORT!$B$3="Zone",IF(7=0,"n/a at Zone scope",""),IF(CALC_TRANSPORT!$BD$10="",IF(7=0,"–",""),8&". "&CALC_TRANSPORT!$BD$10)) | C65: =IF(OR(CALC_TRANSPORT!$B$3="Zone",CALC_TRANSPORT!$BD$10=""),"",CALC_TRANSPORT!$BE$10) | D65: =IF(CALC_TRANSPORT!$B$3="Zone",IF(7=0,"n/a at Zone scope",""),IF(CALC_TRANSPORT!$BF$10="",IF(7=0,"–",""),8&". "&CALC_TRANSPORT!$BF$10)) | E65: =IF(OR(CALC_TRANSPORT!$B$3="Zone",CALC_TRANSPORT!$BF$10=""),"",CALC_TRANSPORT!$BG$10) | F65: =IF(CALC_TRANSPORT!$B$3="Zone",IF(7=0,"n/a at Zone scope",""),IF(CALC_TRANSPORT!$BH$10="",IF(7=0,"–",""),8&". "&CALC_TRANSPORT!$BH$10)) | G65: =IF(OR(CALC_TRANSPORT!$B$3="Zone",CALC_TRANSPORT!$BH$10=""),"",CALC_TRANSPORT!$BI$10) | H65: =IF(CALC_TRANSPORT!$B$3="Zone",IF(7=0,"n/a at Zone scope",""),IF(CALC_TRANSPORT!$BJ$10="",IF(7=0,"–",""),8&". "&CALC_TRANSPORT!$BJ$10)) | I65: =IF(OR(CALC_TRANSPORT!$B$3="Zone",CALC_TRANSPORT!$BJ$10=""),"",CALC_TRANSPORT!$BK$10) | J65: =IF(CALC_TRANSPORT!$B$3="Zone",IF(7=0,"n/a at Zone scope",""),IF(CALC_TRANSPORT!$BL$10="",IF(7=0,"–",""),8&". "&CALC_TRANSPORT!$BL$10)) | K65: =IF(OR(CALC_TRANSPORT!$B$3="Zone",CALC_TRANSPORT!$BL$10=""),"",CALC_TRANSPORT!$BM$10) | L65: =IF(CALC_TRANSPORT!$B$3="Zone",IF(7=0,"n/a at Zone scope",""),IF(CALC_TRANSPORT!$BN$10="",IF(7=0,"No flags this week",""),"• "&CALC_TRANSPORT!$BN$10))
B66: =IF(CALC_TRANSPORT!$B$3="Zone",IF(8=0,"n/a at Zone scope",""),IF(CALC_TRANSPORT!$BD$11="",IF(8=0,"–",""),9&". "&CALC_TRANSPORT!$BD$11)) | C66: =IF(OR(CALC_TRANSPORT!$B$3="Zone",CALC_TRANSPORT!$BD$11=""),"",CALC_TRANSPORT!$BE$11) | D66: =IF(CALC_TRANSPORT!$B$3="Zone",IF(8=0,"n/a at Zone scope",""),IF(CALC_TRANSPORT!$BF$11="",IF(8=0,"–",""),9&". "&CALC_TRANSPORT!$BF$11)) | E66: =IF(OR(CALC_TRANSPORT!$B$3="Zone",CALC_TRANSPORT!$BF$11=""),"",CALC_TRANSPORT!$BG$11) | F66: =IF(CALC_TRANSPORT!$B$3="Zone",IF(8=0,"n/a at Zone scope",""),IF(CALC_TRANSPORT!$BH$11="",IF(8=0,"–",""),9&". "&CALC_TRANSPORT!$BH$11)) | G66: =IF(OR(CALC_TRANSPORT!$B$3="Zone",CALC_TRANSPORT!$BH$11=""),"",CALC_TRANSPORT!$BI$11) | H66: =IF(CALC_TRANSPORT!$B$3="Zone",IF(8=0,"n/a at Zone scope",""),IF(CALC_TRANSPORT!$BJ$11="",IF(8=0,"–",""),9&". "&CALC_TRANSPORT!$BJ$11)) | I66: =IF(OR(CALC_TRANSPORT!$B$3="Zone",CALC_TRANSPORT!$BJ$11=""),"",CALC_TRANSPORT!$BK$11) | J66: =IF(CALC_TRANSPORT!$B$3="Zone",IF(8=0,"n/a at Zone scope",""),IF(CALC_TRANSPORT!$BL$11="",IF(8=0,"–",""),9&". "&CALC_TRANSPORT!$BL$11)) | K66: =IF(OR(CALC_TRANSPORT!$B$3="Zone",CALC_TRANSPORT!$BL$11=""),"",CALC_TRANSPORT!$BM$11) | L66: =IF(CALC_TRANSPORT!$B$3="Zone",IF(8=0,"n/a at Zone scope",""),IF(CALC_TRANSPORT!$BN$11="",IF(8=0,"No flags this week",""),"• "&CALC_TRANSPORT!$BN$11))
B67: =IF(CALC_TRANSPORT!$B$3="Zone",IF(9=0,"n/a at Zone scope",""),IF(CALC_TRANSPORT!$BD$12="",IF(9=0,"–",""),10&". "&CALC_TRANSPORT!$BD$12)) | C67: =IF(OR(CALC_TRANSPORT!$B$3="Zone",CALC_TRANSPORT!$BD$12=""),"",CALC_TRANSPORT!$BE$12) | D67: =IF(CALC_TRANSPORT!$B$3="Zone",IF(9=0,"n/a at Zone scope",""),IF(CALC_TRANSPORT!$BF$12="",IF(9=0,"–",""),10&". "&CALC_TRANSPORT!$BF$12)) | E67: =IF(OR(CALC_TRANSPORT!$B$3="Zone",CALC_TRANSPORT!$BF$12=""),"",CALC_TRANSPORT!$BG$12) | F67: =IF(CALC_TRANSPORT!$B$3="Zone",IF(9=0,"n/a at Zone scope",""),IF(CALC_TRANSPORT!$BH$12="",IF(9=0,"–",""),10&". "&CALC_TRANSPORT!$BH$12)) | G67: =IF(OR(CALC_TRANSPORT!$B$3="Zone",CALC_TRANSPORT!$BH$12=""),"",CALC_TRANSPORT!$BI$12) | H67: =IF(CALC_TRANSPORT!$B$3="Zone",IF(9=0,"n/a at Zone scope",""),IF(CALC_TRANSPORT!$BJ$12="",IF(9=0,"–",""),10&". "&CALC_TRANSPORT!$BJ$12)) | I67: =IF(OR(CALC_TRANSPORT!$B$3="Zone",CALC_TRANSPORT!$BJ$12=""),"",CALC_TRANSPORT!$BK$12) | J67: =IF(CALC_TRANSPORT!$B$3="Zone",IF(9=0,"n/a at Zone scope",""),IF(CALC_TRANSPORT!$BL$12="",IF(9=0,"–",""),10&". "&CALC_TRANSPORT!$BL$12)) | K67: =IF(OR(CALC_TRANSPORT!$B$3="Zone",CALC_TRANSPORT!$BL$12=""),"",CALC_TRANSPORT!$BM$12) | L67: =IF(CALC_TRANSPORT!$B$3="Zone",IF(9=0,"n/a at Zone scope",""),IF(CALC_TRANSPORT!$BN$12="",IF(9=0,"No flags this week",""),"• "&CALC_TRANSPORT!$BN$12))
B70: Operational notes — breakdowns, extra passengers and requests for more buses
B71: =IF(CALC_TRANSPORT!$BO$1=0,"None reported for the selected week in this scope.",TEXT(CALC_TRANSPORT!$BO$1,"#,##0")&" note(s)"&IF(CALC_TRANSPORT!$BO$1>40," — showing the first 40.","."))
B72: Area | D72: Category | F72: Location / bus | J72: Note | L72: Details
B73: =CALC_TRANSPORT!$BP$3 | D73: =CALC_TRANSPORT!$BQ$3 | F73: =CALC_TRANSPORT!$BR$3 | J73: =CALC_TRANSPORT!$BS$3 | L73: =CALC_TRANSPORT!$BT$3
B74: =CALC_TRANSPORT!$BP$4 | D74: =CALC_TRANSPORT!$BQ$4 | F74: =CALC_TRANSPORT!$BR$4 | J74: =CALC_TRANSPORT!$BS$4 | L74: =CALC_TRANSPORT!$BT$4
B75: =CALC_TRANSPORT!$BP$5 | D75: =CALC_TRANSPORT!$BQ$5 | F75: =CALC_TRANSPORT!$BR$5 | J75: =CALC_TRANSPORT!$BS$5 | L75: =CALC_TRANSPORT!$BT$5
B76: =CALC_TRANSPORT!$BP$6 | D76: =CALC_TRANSPORT!$BQ$6 | F76: =CALC_TRANSPORT!$BR$6 | J76: =CALC_TRANSPORT!$BS$6 | L76: =CALC_TRANSPORT!$BT$6
B77: =CALC_TRANSPORT!$BP$7 | D77: =CALC_TRANSPORT!$BQ$7 | F77: =CALC_TRANSPORT!$BR$7 | J77: =CALC_TRANSPORT!$BS$7 | L77: =CALC_TRANSPORT!$BT$7
B78: =CALC_TRANSPORT!$BP$8 | D78: =CALC_TRANSPORT!$BQ$8 | F78: =CALC_TRANSPORT!$BR$8 | J78: =CALC_TRANSPORT!$BS$8 | L78: =CALC_TRANSPORT!$BT$8
B79: =CALC_TRANSPORT!$BP$9 | D79: =CALC_TRANSPORT!$BQ$9 | F79: =CALC_TRANSPORT!$BR$9 | J79: =CALC_TRANSPORT!$BS$9 | L79: =CALC_TRANSPORT!$BT$9
B80: =CALC_TRANSPORT!$BP$10 | D80: =CALC_TRANSPORT!$BQ$10 | F80: =CALC_TRANSPORT!$BR$10 | J80: =CALC_TRANSPORT!$BS$10 | L80: =CALC_TRANSPORT!$BT$10
B81: =CALC_TRANSPORT!$BP$11 | D81: =CALC_TRANSPORT!$BQ$11 | F81: =CALC_TRANSPORT!$BR$11 | J81: =CALC_TRANSPORT!$BS$11 | L81: =CALC_TRANSPORT!$BT$11
B82: =CALC_TRANSPORT!$BP$12 | D82: =CALC_TRANSPORT!$BQ$12 | F82: =CALC_TRANSPORT!$BR$12 | J82: =CALC_TRANSPORT!$BS$12 | L82: =CALC_TRANSPORT!$BT$12
B83: =CALC_TRANSPORT!$BP$13 | D83: =CALC_TRANSPORT!$BQ$13 | F83: =CALC_TRANSPORT!$BR$13 | J83: =CALC_TRANSPORT!$BS$13 | L83: =CALC_TRANSPORT!$BT$13
B84: =CALC_TRANSPORT!$BP$14 | D84: =CALC_TRANSPORT!$BQ$14 | F84: =CALC_TRANSPORT!$BR$14 | J84: =CALC_TRANSPORT!$BS$14 | L84: =CALC_TRANSPORT!$BT$14
B85: =CALC_TRANSPORT!$BP$15 | D85: =CALC_TRANSPORT!$BQ$15 | F85: =CALC_TRANSPORT!$BR$15 | J85: =CALC_TRANSPORT!$BS$15 | L85: =CALC_TRANSPORT!$BT$15
B86: =CALC_TRANSPORT!$BP$16 | D86: =CALC_TRANSPORT!$BQ$16 | F86: =CALC_TRANSPORT!$BR$16 | J86: =CALC_TRANSPORT!$BS$16 | L86: =CALC_TRANSPORT!$BT$16
B87: =CALC_TRANSPORT!$BP$17 | D87: =CALC_TRANSPORT!$BQ$17 | F87: =CALC_TRANSPORT!$BR$17 | J87: =CALC_TRANSPORT!$BS$17 | L87: =CALC_TRANSPORT!$BT$17
B88: =CALC_TRANSPORT!$BP$18 | D88: =CALC_TRANSPORT!$BQ$18 | F88: =CALC_TRANSPORT!$BR$18 | J88: =CALC_TRANSPORT!$BS$18 | L88: =CALC_TRANSPORT!$BT$18
B89: =CALC_TRANSPORT!$BP$19 | D89: =CALC_TRANSPORT!$BQ$19 | F89: =CALC_TRANSPORT!$BR$19 | J89: =CALC_TRANSPORT!$BS$19 | L89: =CALC_TRANSPORT!$BT$19
B90: =CALC_TRANSPORT!$BP$20 | D90: =CALC_TRANSPORT!$BQ$20 | F90: =CALC_TRANSPORT!$BR$20 | J90: =CALC_TRANSPORT!$BS$20 | L90: =CALC_TRANSPORT!$BT$20
B91: =CALC_TRANSPORT!$BP$21 | D91: =CALC_TRANSPORT!$BQ$21 | F91: =CALC_TRANSPORT!$BR$21 | J91: =CALC_TRANSPORT!$BS$21 | L91: =CALC_TRANSPORT!$BT$21
B92: =CALC_TRANSPORT!$BP$22 | D92: =CALC_TRANSPORT!$BQ$22 | F92: =CALC_TRANSPORT!$BR$22 | J92: =CALC_TRANSPORT!$BS$22 | L92: =CALC_TRANSPORT!$BT$22
B93: =CALC_TRANSPORT!$BP$23 | D93: =CALC_TRANSPORT!$BQ$23 | F93: =CALC_TRANSPORT!$BR$23 | J93: =CALC_TRANSPORT!$BS$23 | L93: =CALC_TRANSPORT!$BT$23
B94: =CALC_TRANSPORT!$BP$24 | D94: =CALC_TRANSPORT!$BQ$24 | F94: =CALC_TRANSPORT!$BR$24 | J94: =CALC_TRANSPORT!$BS$24 | L94: =CALC_TRANSPORT!$BT$24
B95: =CALC_TRANSPORT!$BP$25 | D95: =CALC_TRANSPORT!$BQ$25 | F95: =CALC_TRANSPORT!$BR$25 | J95: =CALC_TRANSPORT!$BS$25 | L95: =CALC_TRANSPORT!$BT$25
B96: =CALC_TRANSPORT!$BP$26 | D96: =CALC_TRANSPORT!$BQ$26 | F96: =CALC_TRANSPORT!$BR$26 | J96: =CALC_TRANSPORT!$BS$26 | L96: =CALC_TRANSPORT!$BT$26
B97: =CALC_TRANSPORT!$BP$27 | D97: =CALC_TRANSPORT!$BQ$27 | F97: =CALC_TRANSPORT!$BR$27 | J97: =CALC_TRANSPORT!$BS$27 | L97: =CALC_TRANSPORT!$BT$27
B98: =CALC_TRANSPORT!$BP$28 | D98: =CALC_TRANSPORT!$BQ$28 | F98: =CALC_TRANSPORT!$BR$28 | J98: =CALC_TRANSPORT!$BS$28 | L98: =CALC_TRANSPORT!$BT$28
B99: =CALC_TRANSPORT!$BP$29 | D99: =CALC_TRANSPORT!$BQ$29 | F99: =CALC_TRANSPORT!$BR$29 | J99: =CALC_TRANSPORT!$BS$29 | L99: =CALC_TRANSPORT!$BT$29
B100: =CALC_TRANSPORT!$BP$30 | D100: =CALC_TRANSPORT!$BQ$30 | F100: =CALC_TRANSPORT!$BR$30 | J100: =CALC_TRANSPORT!$BS$30 | L100: =CALC_TRANSPORT!$BT$30
B101: =CALC_TRANSPORT!$BP$31 | D101: =CALC_TRANSPORT!$BQ$31 | F101: =CALC_TRANSPORT!$BR$31 | J101: =CALC_TRANSPORT!$BS$31 | L101: =CALC_TRANSPORT!$BT$31
B102: =CALC_TRANSPORT!$BP$32 | D102: =CALC_TRANSPORT!$BQ$32 | F102: =CALC_TRANSPORT!$BR$32 | J102: =CALC_TRANSPORT!$BS$32 | L102: =CALC_TRANSPORT!$BT$32
B103: =CALC_TRANSPORT!$BP$33 | D103: =CALC_TRANSPORT!$BQ$33 | F103: =CALC_TRANSPORT!$BR$33 | J103: =CALC_TRANSPORT!$BS$33 | L103: =CALC_TRANSPORT!$BT$33
B104: =CALC_TRANSPORT!$BP$34 | D104: =CALC_TRANSPORT!$BQ$34 | F104: =CALC_TRANSPORT!$BR$34 | J104: =CALC_TRANSPORT!$BS$34 | L104: =CALC_TRANSPORT!$BT$34
B105: =CALC_TRANSPORT!$BP$35 | D105: =CALC_TRANSPORT!$BQ$35 | F105: =CALC_TRANSPORT!$BR$35 | J105: =CALC_TRANSPORT!$BS$35 | L105: =CALC_TRANSPORT!$BT$35
B106: =CALC_TRANSPORT!$BP$36 | D106: =CALC_TRANSPORT!$BQ$36 | F106: =CALC_TRANSPORT!$BR$36 | J106: =CALC_TRANSPORT!$BS$36 | L106: =CALC_TRANSPORT!$BT$36
B107: =CALC_TRANSPORT!$BP$37 | D107: =CALC_TRANSPORT!$BQ$37 | F107: =CALC_TRANSPORT!$BR$37 | J107: =CALC_TRANSPORT!$BS$37 | L107: =CALC_TRANSPORT!$BT$37
B108: =CALC_TRANSPORT!$BP$38 | D108: =CALC_TRANSPORT!$BQ$38 | F108: =CALC_TRANSPORT!$BR$38 | J108: =CALC_TRANSPORT!$BS$38 | L108: =CALC_TRANSPORT!$BT$38
B109: =CALC_TRANSPORT!$BP$39 | D109: =CALC_TRANSPORT!$BQ$39 | F109: =CALC_TRANSPORT!$BR$39 | J109: =CALC_TRANSPORT!$BS$39 | L109: =CALC_TRANSPORT!$BT$39
B110: =CALC_TRANSPORT!$BP$40 | D110: =CALC_TRANSPORT!$BQ$40 | F110: =CALC_TRANSPORT!$BR$40 | J110: =CALC_TRANSPORT!$BS$40 | L110: =CALC_TRANSPORT!$BT$40
B111: =CALC_TRANSPORT!$BP$41 | D111: =CALC_TRANSPORT!$BQ$41 | F111: =CALC_TRANSPORT!$BR$41 | J111: =CALC_TRANSPORT!$BS$41 | L111: =CALC_TRANSPORT!$BT$41
B112: =CALC_TRANSPORT!$BP$42 | D112: =CALC_TRANSPORT!$BQ$42 | F112: =CALC_TRANSPORT!$BR$42 | J112: =CALC_TRANSPORT!$BS$42 | L112: =CALC_TRANSPORT!$BT$42

Sheet AREA SCORECARD
B1: AREA SCORECARD | N1: ⌂ HOME
B2: One Area across every stream, with rank among all Areas
B4: Stage 2: this dashboard is built after the WSF DASHBOARD is reviewed, using the same control strip, KPI cards, time analysis, rankings and non-reporting layout. Its data is already loaded in the DATA_* sheet.

Sheet ZONE SCORECARD
B1: ZONE SCORECARD | N1: ⌂ HOME
B2: One Zone across every stream
B4: Stage 2: this dashboard is built after the WSF DASHBOARD is reviewed, using the same control strip, KPI cards, time analysis, rankings and non-reporting layout. Its data is already loaded in the DATA_* sheet.

Sheet DATA QUALITY
B1: DATA QUALITY | I1: ⌂ HOME
B2: Rejected rows, mismatched totals, duplicates, unknown Areas/Zones/Cells and missing weeks. Fix the source file and drop it in the inbox again; a re-sent file replaces the old rows.
B4: Issues by type
B5: Stream | C5: Severity | D5: Issue | E5: Rows
B6: – | C6: – | D6: No issues logged | E6: 0
B8: Stream coverage
B9: Stream | C9: First week | D9: Latest week | E9: Weeks loaded | F9: Rows in workbook
B10: WSF | E10: 0 | F10: 0
B11: MIDWEEK | E11: 0 | F11: 0
B12: CHOP | E12: 0 | F12: 0
B13: COMMUNITY | E13: 0 | F13: 0
B14: TRANSPORT | E14: 0 | F14: 0
B15: TRANSPORT_COSTS | E15: 0 | F15: 0
B16: TRANSPORT_BUDGET | E16: 0 | F16: 0
B18: Missing weeks (no rows at all between a stream's first and latest week)
B19: Stream | C19: Week ending
B20: None — every stream has data for every week in its range.
B23: Issue log (newest first)
B24: Stream | C24: Severity | D24: Issue | E24: Source file | F24: Row | G24: Week ending | H24: Detail | I24: Logged on
B25: No issues logged.

Sheet DATA_WSF
A1: Week_Ending | B1: Report_Date | C1: Area | D1: Zone | E1: Cells_Total | F1: Cells_Reported | G1: Cells_Not_Reported | H1: Male | I1: Female | J1: Adult_Total | K1: Children | L1: Grand_Total | M1: Source_File | N1: Loaded_On
A2: =IF(B2="","",B2+MOD(WeekEndDay-WEEKDAY(B2,2),7)) | G2: =IF(E2="","",E2-F2) | J2: =IF(H2="","",H2+I2) | L2: =IF(H2="","",J2+K2)

Sheet WSF_CELLS_CURRENT
A1: Week_Ending | B1: Report_Date | C1: Area | D1: Zone | E1: Cell | F1: Reported | G1: Male | H1: Female | I1: Adult_Total | J1: Children | K1: Grand_Total | L1: Source_File | M1: Loaded_On | N1: List_Helper
A2: =IF(B2="","",B2+MOD(WeekEndDay-WEEKDAY(B2,2),7)) | I2: =IF(G2="","",G2+H2) | K2: =IF(G2="","",I2+J2) | N2: =IF(AND(F2="N",A2=CALC_WSF!$B$10,OR(CALC_WSF!$B$6="*",C2=CALC_WSF!$B$6),OR(CALC_WSF!$B$7="*",D2=CALC_WSF!$B$7)),ROW(),"")

Sheet DATA_MIDWEEK
A1: Week_Ending | B1: Report_Date | C1: Area | D1: Zone | E1: Male | F1: Female | G1: Adult_Total | H1: Children | I1: Grand_Total | J1: Source_File | K1: Loaded_On
A2: =IF(B2="","",B2+MOD(WeekEndDay-WEEKDAY(B2,2),7)) | G2: =IF(E2="","",E2+F2) | I2: =IF(E2="","",G2+H2)

Sheet DATA_CHOP
A1: Week_Ending | B1: Report_Date | C1: Area | D1: Zone | E1: Male | F1: Female | G1: Adult_Total | H1: Children | I1: Grand_Total | J1: Source_File | K1: Loaded_On
A2: =IF(B2="","",B2+MOD(WeekEndDay-WEEKDAY(B2,2),7)) | G2: =IF(E2="","",E2+F2) | I2: =IF(E2="","",G2+H2)

Sheet DATA_COMMUNITY
A1: Week_Ending | B1: Report_Date | C1: Church | D1: Service_Type | E1: Male | F1: Female | G1: Adult_Total | H1: Children | I1: Grand_Total | J1: Source_File | K1: Loaded_On
A2: =IF(B2="","",B2+MOD(WeekEndDay-WEEKDAY(B2,2),7)) | G2: =IF(E2="","",E2+F2) | I2: =IF(E2="","",G2+H2)

Sheet DATA_TRANSPORT
A1: Week_Ending | B1: Report_Date | C1: Category | D1: Vehicle_Type | E1: Area | F1: Zone_Code | G1: Location | H1: Vehicle_ID | I1: Buses | J1: Capacity | K1: Trips | L1: Seats_Offered | M1: Male | N1: Female | O1: Adult_Total | P1: Children | Q1: Grand_Total | R1: Riders_With_Seats | S1: Cost | T1: Paid_By | U1: Status | V1: Service | W1: Remarks_Category | X1: Remarks | Y1: In_Church | Z1: Source_File | AA1: Loaded_On | AB1: Zone_Key | AC1: Note_Helper
A2: =IF(B2="","",B2+MOD(WeekEndDay-WEEKDAY(B2,2),7)) | L2: =IF(OR(J2="",J2=0),"",IF(U2="Ran",J2*MAX(1,K2),0)) | O2: =IF(M2="","",M2+N2) | Q2: =IF(M2="","",O2+P2) | R2: =IF(L2="","",Q2) | AB2: =IF(F2="","-",F2) | AC2: =IF(AND(A2=CALC_TRANSPORT!$B$10,OR(CALC_TRANSPORT!$B$6="*",E2=CALC_TRANSPORT!$B$6),OR(CALC_TRANSPORT!$B$7="*",F2=CALC_TRANSPORT!$B$7),OR(U2="Breakdown",W2="Extra passengers",ISNUMBER(SEARCH("more bus",X2)))),ROW(),"")

Sheet DATA_TRANSPORT_COSTS
A1: Week_Ending | B1: Report_Date | C1: Category | D1: Area | E1: Vehicle_ID | F1: Cost_Type | G1: Hub_Status | H1: Trips | I1: Litres | J1: Unit_Price | K1: Amount | L1: Payable | M1: Paid_Amount | N1: Paid_By | O1: Source_File | P1: Loaded_On
A2: =IF(B2="","",B2+MOD(WeekEndDay-WEEKDAY(B2,2),7)) | M2: =IF(L2="Y",K2,0)

Sheet DATA_TRANSPORT_BUDGET
A1: Week_Ending | B1: Report_Date | C1: Area_No | D1: Area | E1: Buses_Allocated | F1: Cost_Per_Bus | G1: Expected_Spend | H1: Payable_This_Week | I1: Source_File | J1: Loaded_On
A2: =IF(B2="","",B2+MOD(WeekEndDay-WEEKDAY(B2,2),7)) | G2: =IF(D2="","",E2*F2)

Sheet MASTER_AREAS
A1: Area_ID | B1: Area_Name | C1: Active | D1: Area_No | E1: Aliases
A2: A01 | B2: CANAANLAND 2 | C2: Y | D2: 1 | E2: CANAANLAND 2 (IGE DARAMOLA);CANAAN LAND 2
A3: A02 | B3: IYESI 1 | C3: Y | D3: 2 | E3: IYESI;IYESI1
A4: A03 | B4: OBASANJO | C4: Y | D4: 3
A5: A04 | B5: OJU ORE | C5: Y | D5: 4 | E5: OJUORE
A6: A05 | B6: CAPERNAUM | C6: Y | D6: 5
A7: A06 | B7: NAZARETH | C7: Y | D7: 6 | E7: NAZARATH
A8: A07 | B8: GOWON ESTATE | C8: Y | D8: 7
A9: A08 | B9: BARUWA | C9: Y | D9: 8
A10: A09 | B10: ABORU | C10: Y | D10: 9
A11: A10 | B11: IYANA ISASHI | C11: Y | D11: 10 | E11: IYANA ISHASHI
A12: A11 | B12: WILKY | C12: Y | D12: 11
A13: A12 | B13: PEDRO | C13: Y | D13: 12 | E13: PETRO
A14: A13 | B14: IJAIYE | C14: Y | D14: 13
A15: A14 | B15: OGBA | C15: Y | D15: 14
A16: A15 | B16: YABA | C16: Y | D16: 15
A17: A16 | B17: MUSHIN | C17: Y | D17: 16
A18: A17 | B18: AMUWO | C18: Y | D18: 17 | E18: AMUWO ODOFIN
A19: A18 | B19: AYOBO | C19: Y | D19: 18
A20: A19 | B20: OLAYEMI | C20: Y | D20: 19
A21: A20 | B21: CANDOS | C21: Y | D21: 20
A22: A21 | B22: MAJIYAGBE | C22: Y | D22: 21 | E22: MAJIYAIGBE
A23: A22 | B23: LAFENWA | C23: Y | D23: 22
A24: A23 | B24: PERFECT PEACE | C24: Y | D24: 23
A25: A24 | B25: ANTHONY | C25: Y | D25: 24
A26: A25 | B26: AKUTE | C26: Y | D26: 25
A27: A26 | B27: DENRO | C27: Y | D27: 26
A28: A27 | B28: OLODI APAPA | C28: Y | D28: 27 | E28: 0L0DI APAPA
A29: A28 | B29: PARKLANE APAPA | C29: Y | D29: 28 | E29: PARKLANE, APAPA;APAPA PARKLANE
A30: A29 | B30: ALAGBADO AKINDE | C30: Y | D30: 29
A31: A30 | B31: AIT | C31: Y | D31: 30 | E31: ALT
A32: A31 | B32: AGEGE | C32: Y | D32: 31
A33: A32 | B33: FAGBA | C33: Y | D33: 32
A34: A33 | B34: ATAN 1 | C34: Y | D34: 33 | E34: ATAN;ATAN1
A35: A34 | B35: ADELANS 1 | C35: Y | D35: 34 | E35: ADELANS;ADELANS1
A36: A35 | B36: LUSADA | C36: Y | D36: 35
A37: A36 | B37: IJEGUN IKOTUN | C37: Y | D37: 36
A38: A37 | B38: IGANDO | C38: Y | D38: 37
A39: A38 | B39: IYANA ODO | C39: Y | D39: 38 | E39: IYANA- ODO
A40: A39 | B40: ARIDA | C40: Y | D40: 39
A41: A40 | B41: SHASHA | C41: Y | D41: 40
A42: A41 | B42: EGBEDA | C42: Y | D42: 41
A43: A42 | B43: OREGUN IKEJA | C43: Y | D43: 42 | E43: OREGUN-IKEJA;IKEJA
A44: A43 | B44: CEMENT | C44: Y | D44: 43
A45: A44 | B45: OJODU BERGER 1 | C45: Y | D45: 44
A46: A45 | B46: IFAKO | C46: Y | D46: 45
A47: A46 | B47: ISHERI OPIC | C47: Y | D47: 46 | E47: ISHERI-OPIC
A48: A47 | B48: OJODU BERGER 2 | C48: Y | D48: 47
A49: A48 | B49: IKOSI KETU | C49: Y | D49: 48 | E49: IKOSI-KETU
A50: A49 | B50: MAGODO GRA | C50: Y | D50: 49 | E50: MAGODO
A51: A50 | B51: OKOKOMAIKO | C51: Y | D51: 50
A52: A51 | B52: AGBARA | C52: Y | D52: 51
A53: A52 | B53: IDORAWA EDU | C53: Y | D53: 52 | E53: IDORAWA;IDOWARA EDU
A54: A53 | B54: IJURI | C54: Y | D54: 53
A55: A54 | B55: BADAGRY | C55: Y | D55: 54
A56: A55 | B56: IBIYE | C56: Y | D56: 55
A57: A56 | B57: OKOTA | C57: Y | D57: 56
A58: A57 | B58: OSHODI | C58: Y | D58: 57
A59: A58 | B59: FESTAC | C59: Y | D59: 58
A60: A59 | B60: IJU ISHAGA | C60: Y | D60: 59 | E60: IJU - ISHAGA;IJU-ISHAGA
A61: A60 | B61: EMDEO | C61: Y | D61: 60
A62: A61 | B62: AGBADO | C62: Y | D62: 61
A63: A62 | B63: BODE WILLIAMS | C63: Y | D63: 62
A64: A63 | B64: LEKKI | C64: Y | D64: 63
A65: A64 | B65: VGC | C65: Y | D65: 64
A66: A65 | B66: AJAH | C66: Y | D66: 65
A67: A66 | B67: BADORE | C67: Y | D67: 66
A68: A67 | B68: SURULERE | C68: Y | D68: 67
A69: A68 | B69: LAWANSON | C69: Y | D69: 68
A70: A69 | B70: MASHA | C70: Y | D70: 69
A71: A70 | B71: ILAJE | C71: Y | D71: 70
A72: A71 | B72: OWODE | C72: Y | D72: 71
A73: A72 | B73: SANGO OTA | C73: Y | D73: 72 | E73: SANGO-OTA
A74: A73 | B74: ABEBI OTA | C74: Y | D74: 73 | E74: ABEBI - OTA
A75: A74 | B75: IGBALA | C75: Y | D75: 74
A76: A75 | B76: ILOGBO OTA | C76: Y | D76: 75 | E76: ILOGBO, OTA;ILOGBO
A77: A76 | B77: IJOKO | C77: Y | D77: 76 | E77: IJOKO (76)
A78: A77 | B78: WHITEHOUSE | C78: Y | D78: 77 | E78: WHITEHOUSE (77)
A79: A78 | B79: IYESI 2 | C79: Y | D79: 78
A80: A79 | B80: HIGH COURT | C80: Y | D80: 79 | E80: HIGH COURT (79)
A81: A80 | B81: ATAN 2 | C81: Y | D81: 80
A82: A81 | B82: ADELANS 2 | C82: Y | D82: 81
A83: A82 | B83: AMJE | C83: Y | D83: 82
A84: A83 | B84: IKOLA COMMAND | C84: Y | D84: 83 | E84: IKOLA/COMMAND
A85: A84 | B85: EJIGBO | C85: Y | D85: 84
A86: A85 | B86: IJEDODO | C86: Y | D86: 85
A87: A86 | B87: LSDPC | C87: Y | D87: 86
A88: A87 | B88: ILOGBO OKOKO | C88: Y | D88: 87 | E88: ILOGBO,OKOKO;ILOGBO-OKOKO
A89: A88 | B89: GBAGADA | C89: Y | D89: 88
A90: A89 | B90: ILUPEJU | C90: Y | D90: 89 | E90: ILLUPEJU
A91: A90 | B91: SATELLITE TOWN | C91: Y | D91: 90 | E91: SATELITE;SATELLITE
A92: A91 | B92: IKOYI | C92: Y | D92: 91
A93: A92 | B93: ETI-OSA | C93: Y | D93: 92 | E93: ETI -OSA;ETI OSA

Sheet MASTER_ZONES
A1: Zone_ID | B1: Zone_Name | C1: Area_Name | D1: Has_CHOP | E1: Active
A2: LFC0101 | B2: LFC0101 | C2: CANAANLAND 2 | E2: Y
A3: LFC0102 | B3: LFC0102 | C3: CANAANLAND 2 | E3: Y
A4: LFC0103 | B4: LFC0103 | C4: CANAANLAND 2 | E4: Y
A5: LFC0104 | B5: LFC0104 | C5: CANAANLAND 2 | E5: Y
A6: LFC0105 | B6: LFC0105 | C6: CANAANLAND 2 | E6: Y
A7: LFC0106 | B7: LFC0106 | C7: CANAANLAND 2 | E7: Y
A8: LFC0107 | B8: LFC0107 | C8: CANAANLAND 2 | E8: Y
A9: LFC0108 | B9: LFC0108 | C9: CANAANLAND 2 | E9: Y
A10: LFC0109 | B10: LFC0109 | C10: CANAANLAND 2 | E10: Y
A11: LFC0110 | B11: LFC0110 | C11: CANAANLAND 2 | E11: Y
A12: LFC0111 | B12: LFC0111 | C12: CANAANLAND 2 | E12: Y
A13: LFC0112 | B13: LFC0112 | C13: CANAANLAND 2 | E13: Y
... A1165: LFC9215 | B1165: LFC9215 | C1165: ETI-OSA | E1165: Y

Sheet MASTER_CELLS
A1: Cell | B1: Zone_Name | C1: Area_Name | D1: Operational

Sheet MASTER_COMMUNITY
A1: Church_ID | B1: Church_Name | C1: Location | D1: Active

Sheet MASTER_FLEET
A1: Vehicle_ID | B1: Category | C1: Capacity | D1: Owner | E1: Status | F1: Area_Name | G1: Zone_Name | H1: Hired_By_Type

Sheet CALENDAR
A1: Week_Ending | B1: Week_No | C1: Month | D1: Month_Name | E1: Quarter | F1: Year | G1: Year_Month
A2: =DATE(2024,1,1)+MOD(WeekEndDay-WEEKDAY(DATE(2024,1,1),2),7) | B2: =INT((A2-DATE(YEAR(A2),1,1))/7)+1 | C2: =MONTH(A2) | D2: =TEXT(A2,"mmm") | E2: =ROUNDUP(C2/3,0) | F2: =YEAR(A2) | G2: =F2&"-"&TEXT(C2,"00")
A3: =A2+7 | B3: =INT((A3-DATE(YEAR(A3),1,1))/7)+1 | C3: =MONTH(A3) | D3: =TEXT(A3,"mmm") | E3: =ROUNDUP(C3/3,0) | F3: =YEAR(A3) | G3: =F3&"-"&TEXT(C3,"00")
A4: =A3+7 | B4: =INT((A4-DATE(YEAR(A4),1,1))/7)+1 | C4: =MONTH(A4) | D4: =TEXT(A4,"mmm") | E4: =ROUNDUP(C4/3,0) | F4: =YEAR(A4) | G4: =F4&"-"&TEXT(C4,"00")
A5: =A4+7 | B5: =INT((A5-DATE(YEAR(A5),1,1))/7)+1 | C5: =MONTH(A5) | D5: =TEXT(A5,"mmm") | E5: =ROUNDUP(C5/3,0) | F5: =YEAR(A5) | G5: =F5&"-"&TEXT(C5,"00")
A6: =A5+7 | B6: =INT((A6-DATE(YEAR(A6),1,1))/7)+1 | C6: =MONTH(A6) | D6: =TEXT(A6,"mmm") | E6: =ROUNDUP(C6/3,0) | F6: =YEAR(A6) | G6: =F6&"-"&TEXT(C6,"00")
A7: =A6+7 | B7: =INT((A7-DATE(YEAR(A7),1,1))/7)+1 | C7: =MONTH(A7) | D7: =TEXT(A7,"mmm") | E7: =ROUNDUP(C7/3,0) | F7: =YEAR(A7) | G7: =F7&"-"&TEXT(C7,"00")
A8: =A7+7 | B8: =INT((A8-DATE(YEAR(A8),1,1))/7)+1 | C8: =MONTH(A8) | D8: =TEXT(A8,"mmm") | E8: =ROUNDUP(C8/3,0) | F8: =YEAR(A8) | G8: =F8&"-"&TEXT(C8,"00")
A9: =A8+7 | B9: =INT((A9-DATE(YEAR(A9),1,1))/7)+1 | C9: =MONTH(A9) | D9: =TEXT(A9,"mmm") | E9: =ROUNDUP(C9/3,0) | F9: =YEAR(A9) | G9: =F9&"-"&TEXT(C9,"00")
A10: =A9+7 | B10: =INT((A10-DATE(YEAR(A10),1,1))/7)+1 | C10: =MONTH(A10) | D10: =TEXT(A10,"mmm") | E10: =ROUNDUP(C10/3,0) | F10: =YEAR(A10) | G10: =F10&"-"&TEXT(C10,"00")
A11: =A10+7 | B11: =INT((A11-DATE(YEAR(A11),1,1))/7)+1 | C11: =MONTH(A11) | D11: =TEXT(A11,"mmm") | E11: =ROUNDUP(C11/3,0) | F11: =YEAR(A11) | G11: =F11&"-"&TEXT(C11,"00")
A12: =A11+7 | B12: =INT((A12-DATE(YEAR(A12),1,1))/7)+1 | C12: =MONTH(A12) | D12: =TEXT(A12,"mmm") | E12: =ROUNDUP(C12/3,0) | F12: =YEAR(A12) | G12: =F12&"-"&TEXT(C12,"00")
A13: =A12+7 | B13: =INT((A13-DATE(YEAR(A13),1,1))/7)+1 | C13: =MONTH(A13) | D13: =TEXT(A13,"mmm") | E13: =ROUNDUP(C13/3,0) | F13: =YEAR(A13) | G13: =F13&"-"&TEXT(C13,"00")
A14: =A13+7 | B14: =INT((A14-DATE(YEAR(A14),1,1))/7)+1 | C14: =MONTH(A14) | D14: =TEXT(A14,"mmm") | E14: =ROUNDUP(C14/3,0) | F14: =YEAR(A14) | G14: =F14&"-"&TEXT(C14,"00")
... A372: =A371+7 | B372: =INT((A372-DATE(YEAR(A372),1,1))/7)+1 | C372: =MONTH(A372) | D372: =TEXT(A372,"mmm") | E372: =ROUNDUP(C372/3,0) | F372: =YEAR(A372) | G372: =F372&"-"&TEXT(C372,"00")

Sheet SETTINGS
A1: SETTINGS
A2: Edit the blue values. They are kept when ingest.py rebuilds the workbook.
A3: Setting | B3: Value | C3: What it does
A4: WeekEndDay | B4: 7 | C4: Day the reporting week ends: 1=Mon ... 6=Sat, 7=Sun. Change it in settings.yaml, then run ingest.py so stored data and the workbook stay in step.
A5: DefaultWindow | B5: 4 | C5: Comparison window used when a dashboard's window box is empty (1, 2, 4, 8, 13, 26 or 52).
A6: RAG_Green | B6: 0.9 | C6: Reporting / utilisation at or above this is green.
A7: RAG_Amber | B7: 0.75 | C7: At or above this (but below green) is amber; below it is red.
A8: UtilLow | B8: 0.5 | C8: Transport: buses/routes under this utilisation are flagged (X in the spec).
A9: UtilHigh | B9: 1 | C9: Transport: utilisation above this means demand exceeds capacity.
A10: UtilLowWeeks | B10: 4 | C10: Transport: consecutive weeks under UtilLow before a plain-language flag is raised.
A11: Cap_FT | B11: 22 | C11: Seats per trip, FT Procured (LT) buses.
A12: Cap_Coaster | B12: 30 | C12: Seats per trip, church-owned Coasters (assumed 30; confirm).
A13: Cap_Electric | B13: 70 | C13: Riders per trip, electric buses.
A14: Cap_Big | B14: 70 | C14: Riders per trip, big buses.
A15: CurrencySymbol | B15: ₦ | C15: Currency shown on finance figures (NGN).
A18: Stream colours (used on every sheet)
A19: MASTER | B19: #1B2A41
A20: WSF | B20: #1F5FA8
A21: MIDWEEK | B21: #0F7C74
A22: CHOP | B22: #6A3FA0
A23: COMMUNITY | B23: #B5446E
A24: TRANSPORT | B24: #D9731A
A25: QUALITY | B25: #5B6770

Sheet CALC_LISTS
A1: Latest | B1: WSF latest | C1: Latest | D1: TRANSPORT latest
A2: =IF($B$2=0,"",IF($B$2-0>=$B$4,$B$2-0,"")) | B2: =MAX(DATA_WSF!$A:$A) | C2: =IF($D$2=0,"",IF($D$2-0>=$D$4,$D$2-0,"")) | D2: =MAX(DATA_TRANSPORT!$A:$A)
A3: =IF($B$2=0,"",IF($B$2-7>=$B$4,$B$2-7,"")) | B3: WSF earliest | C3: =IF($D$2=0,"",IF($D$2-7>=$D$4,$D$2-7,"")) | D3: TRANSPORT earliest
A4: =IF($B$2=0,"",IF($B$2-14>=$B$4,$B$2-14,"")) | B4: =MIN(DATA_WSF!$A:$A) | C4: =IF($D$2=0,"",IF($D$2-14>=$D$4,$D$2-14,"")) | D4: =MIN(DATA_TRANSPORT!$A:$A)
A5: =IF($B$2=0,"",IF($B$2-21>=$B$4,$B$2-21,"")) | B5: WSF weeks listed | C5: =IF($D$2=0,"",IF($D$2-21>=$D$4,$D$2-21,"")) | D5: TRANSPORT weeks listed
A6: =IF($B$2=0,"",IF($B$2-28>=$B$4,$B$2-28,"")) | B6: =COUNT(A2:A105) | C6: =IF($D$2=0,"",IF($D$2-28>=$D$4,$D$2-28,"")) | D6: =COUNT(C2:C105)
A7: =IF($B$2=0,"",IF($B$2-35>=$B$4,$B$2-35,"")) | C7: =IF($D$2=0,"",IF($D$2-35>=$D$4,$D$2-35,""))
A8: =IF($B$2=0,"",IF($B$2-42>=$B$4,$B$2-42,"")) | C8: =IF($D$2=0,"",IF($D$2-42>=$D$4,$D$2-42,""))
A9: =IF($B$2=0,"",IF($B$2-49>=$B$4,$B$2-49,"")) | C9: =IF($D$2=0,"",IF($D$2-49>=$D$4,$D$2-49,""))
A10: =IF($B$2=0,"",IF($B$2-56>=$B$4,$B$2-56,"")) | C10: =IF($D$2=0,"",IF($D$2-56>=$D$4,$D$2-56,""))
A11: =IF($B$2=0,"",IF($B$2-63>=$B$4,$B$2-63,"")) | C11: =IF($D$2=0,"",IF($D$2-63>=$D$4,$D$2-63,""))
A12: =IF($B$2=0,"",IF($B$2-70>=$B$4,$B$2-70,"")) | C12: =IF($D$2=0,"",IF($D$2-70>=$D$4,$D$2-70,""))
A13: =IF($B$2=0,"",IF($B$2-77>=$B$4,$B$2-77,"")) | C13: =IF($D$2=0,"",IF($D$2-77>=$D$4,$D$2-77,""))
A14: =IF($B$2=0,"",IF($B$2-84>=$B$4,$B$2-84,"")) | C14: =IF($D$2=0,"",IF($D$2-84>=$D$4,$D$2-84,""))
A15: =IF($B$2=0,"",IF($B$2-91>=$B$4,$B$2-91,"")) | C15: =IF($D$2=0,"",IF($D$2-91>=$D$4,$D$2-91,""))
A16: =IF($B$2=0,"",IF($B$2-98>=$B$4,$B$2-98,"")) | C16: =IF($D$2=0,"",IF($D$2-98>=$D$4,$D$2-98,""))
A17: =IF($B$2=0,"",IF($B$2-105>=$B$4,$B$2-105,"")) | C17: =IF($D$2=0,"",IF($D$2-105>=$D$4,$D$2-105,""))
A18: =IF($B$2=0,"",IF($B$2-112>=$B$4,$B$2-112,"")) | C18: =IF($D$2=0,"",IF($D$2-112>=$D$4,$D$2-112,""))
A19: =IF($B$2=0,"",IF($B$2-119>=$B$4,$B$2-119,"")) | C19: =IF($D$2=0,"",IF($D$2-119>=$D$4,$D$2-119,""))
A20: =IF($B$2=0,"",IF($B$2-126>=$B$4,$B$2-126,"")) | C20: =IF($D$2=0,"",IF($D$2-126>=$D$4,$D$2-126,""))
A21: =IF($B$2=0,"",IF($B$2-133>=$B$4,$B$2-133,"")) | C21: =IF($D$2=0,"",IF($D$2-133>=$D$4,$D$2-133,""))
A22: =IF($B$2=0,"",IF($B$2-140>=$B$4,$B$2-140,"")) | C22: =IF($D$2=0,"",IF($D$2-140>=$D$4,$D$2-140,""))
A23: =IF($B$2=0,"",IF($B$2-147>=$B$4,$B$2-147,"")) | C23: =IF($D$2=0,"",IF($D$2-147>=$D$4,$D$2-147,""))
A24: =IF($B$2=0,"",IF($B$2-154>=$B$4,$B$2-154,"")) | C24: =IF($D$2=0,"",IF($D$2-154>=$D$4,$D$2-154,""))
A25: =IF($B$2=0,"",IF($B$2-161>=$B$4,$B$2-161,"")) | C25: =IF($D$2=0,"",IF($D$2-161>=$D$4,$D$2-161,""))
A26: =IF($B$2=0,"",IF($B$2-168>=$B$4,$B$2-168,"")) | C26: =IF($D$2=0,"",IF($D$2-168>=$D$4,$D$2-168,""))
A27: =IF($B$2=0,"",IF($B$2-175>=$B$4,$B$2-175,"")) | C27: =IF($D$2=0,"",IF($D$2-175>=$D$4,$D$2-175,""))
A28: =IF($B$2=0,"",IF($B$2-182>=$B$4,$B$2-182,"")) | C28: =IF($D$2=0,"",IF($D$2-182>=$D$4,$D$2-182,""))
A29: =IF($B$2=0,"",IF($B$2-189>=$B$4,$B$2-189,"")) | C29: =IF($D$2=0,"",IF($D$2-189>=$D$4,$D$2-189,""))
A30: =IF($B$2=0,"",IF($B$2-196>=$B$4,$B$2-196,"")) | C30: =IF($D$2=0,"",IF($D$2-196>=$D$4,$D$2-196,""))
A31: =IF($B$2=0,"",IF($B$2-203>=$B$4,$B$2-203,"")) | C31: =IF($D$2=0,"",IF($D$2-203>=$D$4,$D$2-203,""))
A32: =IF($B$2=0,"",IF($B$2-210>=$B$4,$B$2-210,"")) | C32: =IF($D$2=0,"",IF($D$2-210>=$D$4,$D$2-210,""))
A33: =IF($B$2=0,"",IF($B$2-217>=$B$4,$B$2-217,"")) | C33: =IF($D$2=0,"",IF($D$2-217>=$D$4,$D$2-217,""))
A34: =IF($B$2=0,"",IF($B$2-224>=$B$4,$B$2-224,"")) | C34: =IF($D$2=0,"",IF($D$2-224>=$D$4,$D$2-224,""))
A35: =IF($B$2=0,"",IF($B$2-231>=$B$4,$B$2-231,"")) | C35: =IF($D$2=0,"",IF($D$2-231>=$D$4,$D$2-231,""))
A36: =IF($B$2=0,"",IF($B$2-238>=$B$4,$B$2-238,"")) | C36: =IF($D$2=0,"",IF($D$2-238>=$D$4,$D$2-238,""))
A37: =IF($B$2=0,"",IF($B$2-245>=$B$4,$B$2-245,"")) | C37: =IF($D$2=0,"",IF($D$2-245>=$D$4,$D$2-245,""))
A38: =IF($B$2=0,"",IF($B$2-252>=$B$4,$B$2-252,"")) | C38: =IF($D$2=0,"",IF($D$2-252>=$D$4,$D$2-252,""))
A39: =IF($B$2=0,"",IF($B$2-259>=$B$4,$B$2-259,"")) | C39: =IF($D$2=0,"",IF($D$2-259>=$D$4,$D$2-259,""))
A40: =IF($B$2=0,"",IF($B$2-266>=$B$4,$B$2-266,"")) | C40: =IF($D$2=0,"",IF($D$2-266>=$D$4,$D$2-266,""))
A41: =IF($B$2=0,"",IF($B$2-273>=$B$4,$B$2-273,"")) | C41: =IF($D$2=0,"",IF($D$2-273>=$D$4,$D$2-273,""))
A42: =IF($B$2=0,"",IF($B$2-280>=$B$4,$B$2-280,"")) | C42: =IF($D$2=0,"",IF($D$2-280>=$D$4,$D$2-280,""))
A43: =IF($B$2=0,"",IF($B$2-287>=$B$4,$B$2-287,"")) | C43: =IF($D$2=0,"",IF($D$2-287>=$D$4,$D$2-287,""))
A44: =IF($B$2=0,"",IF($B$2-294>=$B$4,$B$2-294,"")) | C44: =IF($D$2=0,"",IF($D$2-294>=$D$4,$D$2-294,""))
A45: =IF($B$2=0,"",IF($B$2-301>=$B$4,$B$2-301,"")) | C45: =IF($D$2=0,"",IF($D$2-301>=$D$4,$D$2-301,""))
A46: =IF($B$2=0,"",IF($B$2-308>=$B$4,$B$2-308,"")) | C46: =IF($D$2=0,"",IF($D$2-308>=$D$4,$D$2-308,""))
A47: =IF($B$2=0,"",IF($B$2-315>=$B$4,$B$2-315,"")) | C47: =IF($D$2=0,"",IF($D$2-315>=$D$4,$D$2-315,""))
A48: =IF($B$2=0,"",IF($B$2-322>=$B$4,$B$2-322,"")) | C48: =IF($D$2=0,"",IF($D$2-322>=$D$4,$D$2-322,""))
A49: =IF($B$2=0,"",IF($B$2-329>=$B$4,$B$2-329,"")) | C49: =IF($D$2=0,"",IF($D$2-329>=$D$4,$D$2-329,""))
A50: =IF($B$2=0,"",IF($B$2-336>=$B$4,$B$2-336,"")) | C50: =IF($D$2=0,"",IF($D$2-336>=$D$4,$D$2-336,""))
A51: =IF($B$2=0,"",IF($B$2-343>=$B$4,$B$2-343,"")) | C51: =IF($D$2=0,"",IF($D$2-343>=$D$4,$D$2-343,""))
A52: =IF($B$2=0,"",IF($B$2-350>=$B$4,$B$2-350,"")) | C52: =IF($D$2=0,"",IF($D$2-350>=$D$4,$D$2-350,""))
A53: =IF($B$2=0,"",IF($B$2-357>=$B$4,$B$2-357,"")) | C53: =IF($D$2=0,"",IF($D$2-357>=$D$4,$D$2-357,""))
A54: =IF($B$2=0,"",IF($B$2-364>=$B$4,$B$2-364,"")) | C54: =IF($D$2=0,"",IF($D$2-364>=$D$4,$D$2-364,""))
A55: =IF($B$2=0,"",IF($B$2-371>=$B$4,$B$2-371,"")) | C55: =IF($D$2=0,"",IF($D$2-371>=$D$4,$D$2-371,""))
A56: =IF($B$2=0,"",IF($B$2-378>=$B$4,$B$2-378,"")) | C56: =IF($D$2=0,"",IF($D$2-378>=$D$4,$D$2-378,""))
A57: =IF($B$2=0,"",IF($B$2-385>=$B$4,$B$2-385,"")) | C57: =IF($D$2=0,"",IF($D$2-385>=$D$4,$D$2-385,""))
A58: =IF($B$2=0,"",IF($B$2-392>=$B$4,$B$2-392,"")) | C58: =IF($D$2=0,"",IF($D$2-392>=$D$4,$D$2-392,""))
A59: =IF($B$2=0,"",IF($B$2-399>=$B$4,$B$2-399,"")) | C59: =IF($D$2=0,"",IF($D$2-399>=$D$4,$D$2-399,""))
A60: =IF($B$2=0,"",IF($B$2-406>=$B$4,$B$2-406,"")) | C60: =IF($D$2=0,"",IF($D$2-406>=$D$4,$D$2-406,""))
A61: =IF($B$2=0,"",IF($B$2-413>=$B$4,$B$2-413,"")) | C61: =IF($D$2=0,"",IF($D$2-413>=$D$4,$D$2-413,""))
A62: =IF($B$2=0,"",IF($B$2-420>=$B$4,$B$2-420,"")) | C62: =IF($D$2=0,"",IF($D$2-420>=$D$4,$D$2-420,""))
A63: =IF($B$2=0,"",IF($B$2-427>=$B$4,$B$2-427,"")) | C63: =IF($D$2=0,"",IF($D$2-427>=$D$4,$D$2-427,""))
A64: =IF($B$2=0,"",IF($B$2-434>=$B$4,$B$2-434,"")) | C64: =IF($D$2=0,"",IF($D$2-434>=$D$4,$D$2-434,""))
A65: =IF($B$2=0,"",IF($B$2-441>=$B$4,$B$2-441,"")) | C65: =IF($D$2=0,"",IF($D$2-441>=$D$4,$D$2-441,""))
A66: =IF($B$2=0,"",IF($B$2-448>=$B$4,$B$2-448,"")) | C66: =IF($D$2=0,"",IF($D$2-448>=$D$4,$D$2-448,""))
A67: =IF($B$2=0,"",IF($B$2-455>=$B$4,$B$2-455,"")) | C67: =IF($D$2=0,"",IF($D$2-455>=$D$4,$D$2-455,""))
A68: =IF($B$2=0,"",IF($B$2-462>=$B$4,$B$2-462,"")) | C68: =IF($D$2=0,"",IF($D$2-462>=$D$4,$D$2-462,""))
A69: =IF($B$2=0,"",IF($B$2-469>=$B$4,$B$2-469,"")) | C69: =IF($D$2=0,"",IF($D$2-469>=$D$4,$D$2-469,""))
A70: =IF($B$2=0,"",IF($B$2-476>=$B$4,$B$2-476,"")) | C70: =IF($D$2=0,"",IF($D$2-476>=$D$4,$D$2-476,""))
A71: =IF($B$2=0,"",IF($B$2-483>=$B$4,$B$2-483,"")) | C71: =IF($D$2=0,"",IF($D$2-483>=$D$4,$D$2-483,""))
A72: =IF($B$2=0,"",IF($B$2-490>=$B$4,$B$2-490,"")) | C72: =IF($D$2=0,"",IF($D$2-490>=$D$4,$D$2-490,""))
A73: =IF($B$2=0,"",IF($B$2-497>=$B$4,$B$2-497,"")) | C73: =IF($D$2=0,"",IF($D$2-497>=$D$4,$D$2-497,""))
A74: =IF($B$2=0,"",IF($B$2-504>=$B$4,$B$2-504,"")) | C74: =IF($D$2=0,"",IF($D$2-504>=$D$4,$D$2-504,""))
A75: =IF($B$2=0,"",IF($B$2-511>=$B$4,$B$2-511,"")) | C75: =IF($D$2=0,"",IF($D$2-511>=$D$4,$D$2-511,""))
A76: =IF($B$2=0,"",IF($B$2-518>=$B$4,$B$2-518,"")) | C76: =IF($D$2=0,"",IF($D$2-518>=$D$4,$D$2-518,""))
A77: =IF($B$2=0,"",IF($B$2-525>=$B$4,$B$2-525,"")) | C77: =IF($D$2=0,"",IF($D$2-525>=$D$4,$D$2-525,""))
A78: =IF($B$2=0,"",IF($B$2-532>=$B$4,$B$2-532,"")) | C78: =IF($D$2=0,"",IF($D$2-532>=$D$4,$D$2-532,""))
A79: =IF($B$2=0,"",IF($B$2-539>=$B$4,$B$2-539,"")) | C79: =IF($D$2=0,"",IF($D$2-539>=$D$4,$D$2-539,""))
A80: =IF($B$2=0,"",IF($B$2-546>=$B$4,$B$2-546,"")) | C80: =IF($D$2=0,"",IF($D$2-546>=$D$4,$D$2-546,""))
A81: =IF($B$2=0,"",IF($B$2-553>=$B$4,$B$2-553,"")) | C81: =IF($D$2=0,"",IF($D$2-553>=$D$4,$D$2-553,""))
A82: =IF($B$2=0,"",IF($B$2-560>=$B$4,$B$2-560,"")) | C82: =IF($D$2=0,"",IF($D$2-560>=$D$4,$D$2-560,""))
A83: =IF($B$2=0,"",IF($B$2-567>=$B$4,$B$2-567,"")) | C83: =IF($D$2=0,"",IF($D$2-567>=$D$4,$D$2-567,""))
A84: =IF($B$2=0,"",IF($B$2-574>=$B$4,$B$2-574,"")) | C84: =IF($D$2=0,"",IF($D$2-574>=$D$4,$D$2-574,""))
A85: =IF($B$2=0,"",IF($B$2-581>=$B$4,$B$2-581,"")) | C85: =IF($D$2=0,"",IF($D$2-581>=$D$4,$D$2-581,""))
A86: =IF($B$2=0,"",IF($B$2-588>=$B$4,$B$2-588,"")) | C86: =IF($D$2=0,"",IF($D$2-588>=$D$4,$D$2-588,""))
A87: =IF($B$2=0,"",IF($B$2-595>=$B$4,$B$2-595,"")) | C87: =IF($D$2=0,"",IF($D$2-595>=$D$4,$D$2-595,""))
A88: =IF($B$2=0,"",IF($B$2-602>=$B$4,$B$2-602,"")) | C88: =IF($D$2=0,"",IF($D$2-602>=$D$4,$D$2-602,""))
A89: =IF($B$2=0,"",IF($B$2-609>=$B$4,$B$2-609,"")) | C89: =IF($D$2=0,"",IF($D$2-609>=$D$4,$D$2-609,""))
A90: =IF($B$2=0,"",IF($B$2-616>=$B$4,$B$2-616,"")) | C90: =IF($D$2=0,"",IF($D$2-616>=$D$4,$D$2-616,""))
A91: =IF($B$2=0,"",IF($B$2-623>=$B$4,$B$2-623,"")) | C91: =IF($D$2=0,"",IF($D$2-623>=$D$4,$D$2-623,""))
A92: =IF($B$2=0,"",IF($B$2-630>=$B$4,$B$2-630,"")) | C92: =IF($D$2=0,"",IF($D$2-630>=$D$4,$D$2-630,""))
A93: =IF($B$2=0,"",IF($B$2-637>=$B$4,$B$2-637,"")) | C93: =IF($D$2=0,"",IF($D$2-637>=$D$4,$D$2-637,""))
A94: =IF($B$2=0,"",IF($B$2-644>=$B$4,$B$2-644,"")) | C94: =IF($D$2=0,"",IF($D$2-644>=$D$4,$D$2-644,""))
A95: =IF($B$2=0,"",IF($B$2-651>=$B$4,$B$2-651,"")) | C95: =IF($D$2=0,"",IF($D$2-651>=$D$4,$D$2-651,""))
A96: =IF($B$2=0,"",IF($B$2-658>=$B$4,$B$2-658,"")) | C96: =IF($D$2=0,"",IF($D$2-658>=$D$4,$D$2-658,""))
A97: =IF($B$2=0,"",IF($B$2-665>=$B$4,$B$2-665,"")) | C97: =IF($D$2=0,"",IF($D$2-665>=$D$4,$D$2-665,""))
A98: =IF($B$2=0,"",IF($B$2-672>=$B$4,$B$2-672,"")) | C98: =IF($D$2=0,"",IF($D$2-672>=$D$4,$D$2-672,""))
A99: =IF($B$2=0,"",IF($B$2-679>=$B$4,$B$2-679,"")) | C99: =IF($D$2=0,"",IF($D$2-679>=$D$4,$D$2-679,""))
A100: =IF($B$2=0,"",IF($B$2-686>=$B$4,$B$2-686,"")) | C100: =IF($D$2=0,"",IF($D$2-686>=$D$4,$D$2-686,""))
...

Sheet CALC_SEARCH
A1: WSF match row | B1: WSF k-th match | C1: WSF name | D1: WSF matches | F1: TRANSPORT match row | G1: TRANSPORT k-th match | H1: TRANSPORT name | I1: TRANSPORT matches
A2: =IF('WSF DASHBOARD'!$B$4="Area",IF(1<=$D$3,IF(OR('WSF DASHBOARD'!$C$4="",ISNUMBER(SEARCH('WSF DASHBOARD'!$C$4,INDEX(MASTER_AREAS!$B:$B,2)))),1,""),""),IF('WSF DASHBOARD'!$B$4="Zone",IF(1<=$D$4,IF(OR('WSF DASHBOARD'!$C$4="",ISNUMBER(SEARCH('WSF DASHBOARD'!$C$4,INDEX(MASTER_ZONES!$B:$B,2)))),1,""),""),"")) | B2: =IFERROR(SMALL($A$2:$A$1365,1),"") | C2: =IF(B2="","",IF('WSF DASHBOARD'!$B$4="Area",INDEX(MASTER_AREAS!$B:$B,B2+1),INDEX(MASTER_ZONES!$B:$B,B2+1))) | D2: =COUNT(A2:A1365) | F2: =IF('TRANSPORT DASHBOARD'!$B$4="Area",IF(1<=$I$3,IF(OR('TRANSPORT DASHBOARD'!$C$4="",ISNUMBER(SEARCH('TRANSPORT DASHBOARD'!$C$4,INDEX(MASTER_AREAS!$B:$B,2)))),1,""),""),IF('TRANSPORT DASHBOARD'!$B$4="Zone",IF(1<=$I$4,IF(OR('TRANSPORT DASHBOARD'!$C$4="",ISNUMBER(SEARCH('TRANSPORT DASHBOARD'!$C$4,INDEX(MASTER_ZONES!$B:$B,2)))),1,""),""),"")) | G2: =IFERROR(SMALL($F$2:$F$1365,1),"") | H2: =IF(G2="","",IF('TRANSPORT DASHBOARD'!$B$4="Area",INDEX(MASTER_AREAS!$B:$B,G2+1),INDEX(MASTER_ZONES!$B:$B,G2+1))) | I2: =COUNT(F2:F1365)
A3: =IF('WSF DASHBOARD'!$B$4="Area",IF(2<=$D$3,IF(OR('WSF DASHBOARD'!$C$4="",ISNUMBER(SEARCH('WSF DASHBOARD'!$C$4,INDEX(MASTER_AREAS!$B:$B,3)))),2,""),""),IF('WSF DASHBOARD'!$B$4="Zone",IF(2<=$D$4,IF(OR('WSF DASHBOARD'!$C$4="",ISNUMBER(SEARCH('WSF DASHBOARD'!$C$4,INDEX(MASTER_ZONES!$B:$B,3)))),2,""),""),"")) | B3: =IFERROR(SMALL($A$2:$A$1365,2),"") | C3: =IF(B3="","",IF('WSF DASHBOARD'!$B$4="Area",INDEX(MASTER_AREAS!$B:$B,B3+1),INDEX(MASTER_ZONES!$B:$B,B3+1))) | D3: =COUNTA(MASTER_AREAS!$B:$B)-1 | F3: =IF('TRANSPORT DASHBOARD'!$B$4="Area",IF(2<=$I$3,IF(OR('TRANSPORT DASHBOARD'!$C$4="",ISNUMBER(SEARCH('TRANSPORT DASHBOARD'!$C$4,INDEX(MASTER_AREAS!$B:$B,3)))),2,""),""),IF('TRANSPORT DASHBOARD'!$B$4="Zone",IF(2<=$I$4,IF(OR('TRANSPORT DASHBOARD'!$C$4="",ISNUMBER(SEARCH('TRANSPORT DASHBOARD'!$C$4,INDEX(MASTER_ZONES!$B:$B,3)))),2,""),""),"")) | G3: =IFERROR(SMALL($F$2:$F$1365,2),"") | H3: =IF(G3="","",IF('TRANSPORT DASHBOARD'!$B$4="Area",INDEX(MASTER_AREAS!$B:$B,G3+1),INDEX(MASTER_ZONES!$B:$B,G3+1))) | I3: =COUNTA(MASTER_AREAS!$B:$B)-1
A4: =IF('WSF DASHBOARD'!$B$4="Area",IF(3<=$D$3,IF(OR('WSF DASHBOARD'!$C$4="",ISNUMBER(SEARCH('WSF DASHBOARD'!$C$4,INDEX(MASTER_AREAS!$B:$B,4)))),3,""),""),IF('WSF DASHBOARD'!$B$4="Zone",IF(3<=$D$4,IF(OR('WSF DASHBOARD'!$C$4="",ISNUMBER(SEARCH('WSF DASHBOARD'!$C$4,INDEX(MASTER_ZONES!$B:$B,4)))),3,""),""),"")) | B4: =IFERROR(SMALL($A$2:$A$1365,3),"") | C4: =IF(B4="","",IF('WSF DASHBOARD'!$B$4="Area",INDEX(MASTER_AREAS!$B:$B,B4+1),INDEX(MASTER_ZONES!$B:$B,B4+1))) | D4: =COUNTA(MASTER_ZONES!$B:$B)-1 | F4: =IF('TRANSPORT DASHBOARD'!$B$4="Area",IF(3<=$I$3,IF(OR('TRANSPORT DASHBOARD'!$C$4="",ISNUMBER(SEARCH('TRANSPORT DASHBOARD'!$C$4,INDEX(MASTER_AREAS!$B:$B,4)))),3,""),""),IF('TRANSPORT DASHBOARD'!$B$4="Zone",IF(3<=$I$4,IF(OR('TRANSPORT DASHBOARD'!$C$4="",ISNUMBER(SEARCH('TRANSPORT DASHBOARD'!$C$4,INDEX(MASTER_ZONES!$B:$B,4)))),3,""),""),"")) | G4: =IFERROR(SMALL($F$2:$F$1365,3),"") | H4: =IF(G4="","",IF('TRANSPORT DASHBOARD'!$B$4="Area",INDEX(MASTER_AREAS!$B:$B,G4+1),INDEX(MASTER_ZONES!$B:$B,G4+1))) | I4: =COUNTA(MASTER_ZONES!$B:$B)-1
A5: =IF('WSF DASHBOARD'!$B$4="Area",IF(4<=$D$3,IF(OR('WSF DASHBOARD'!$C$4="",ISNUMBER(SEARCH('WSF DASHBOARD'!$C$4,INDEX(MASTER_AREAS!$B:$B,5)))),4,""),""),IF('WSF DASHBOARD'!$B$4="Zone",IF(4<=$D$4,IF(OR('WSF DASHBOARD'!$C$4="",ISNUMBER(SEARCH('WSF DASHBOARD'!$C$4,INDEX(MASTER_ZONES!$B:$B,5)))),4,""),""),"")) | B5: =IFERROR(SMALL($A$2:$A$1365,4),"") | C5: =IF(B5="","",IF('WSF DASHBOARD'!$B$4="Area",INDEX(MASTER_AREAS!$B:$B,B5+1),INDEX(MASTER_ZONES!$B:$B,B5+1))) | F5: =IF('TRANSPORT DASHBOARD'!$B$4="Area",IF(4<=$I$3,IF(OR('TRANSPORT DASHBOARD'!$C$4="",ISNUMBER(SEARCH('TRANSPORT DASHBOARD'!$C$4,INDEX(MASTER_AREAS!$B:$B,5)))),4,""),""),IF('TRANSPORT DASHBOARD'!$B$4="Zone",IF(4<=$I$4,IF(OR('TRANSPORT DASHBOARD'!$C$4="",ISNUMBER(SEARCH('TRANSPORT DASHBOARD'!$C$4,INDEX(MASTER_ZONES!$B:$B,5)))),4,""),""),"")) | G5: =IFERROR(SMALL($F$2:$F$1365,4),"") | H5: =IF(G5="","",IF('TRANSPORT DASHBOARD'!$B$4="Area",INDEX(MASTER_AREAS!$B:$B,G5+1),INDEX(MASTER_ZONES!$B:$B,G5+1)))
A6: =IF('WSF DASHBOARD'!$B$4="Area",IF(5<=$D$3,IF(OR('WSF DASHBOARD'!$C$4="",ISNUMBER(SEARCH('WSF DASHBOARD'!$C$4,INDEX(MASTER_AREAS!$B:$B,6)))),5,""),""),IF('WSF DASHBOARD'!$B$4="Zone",IF(5<=$D$4,IF(OR('WSF DASHBOARD'!$C$4="",ISNUMBER(SEARCH('WSF DASHBOARD'!$C$4,INDEX(MASTER_ZONES!$B:$B,6)))),5,""),""),"")) | B6: =IFERROR(SMALL($A$2:$A$1365,5),"") | C6: =IF(B6="","",IF('WSF DASHBOARD'!$B$4="Area",INDEX(MASTER_AREAS!$B:$B,B6+1),INDEX(MASTER_ZONES!$B:$B,B6+1))) | F6: =IF('TRANSPORT DASHBOARD'!$B$4="Area",IF(5<=$I$3,IF(OR('TRANSPORT DASHBOARD'!$C$4="",ISNUMBER(SEARCH('TRANSPORT DASHBOARD'!$C$4,INDEX(MASTER_AREAS!$B:$B,6)))),5,""),""),IF('TRANSPORT DASHBOARD'!$B$4="Zone",IF(5<=$I$4,IF(OR('TRANSPORT DASHBOARD'!$C$4="",ISNUMBER(SEARCH('TRANSPORT DASHBOARD'!$C$4,INDEX(MASTER_ZONES!$B:$B,6)))),5,""),""),"")) | G6: =IFERROR(SMALL($F$2:$F$1365,5),"") | H6: =IF(G6="","",IF('TRANSPORT DASHBOARD'!$B$4="Area",INDEX(MASTER_AREAS!$B:$B,G6+1),INDEX(MASTER_ZONES!$B:$B,G6+1)))
A7: =IF('WSF DASHBOARD'!$B$4="Area",IF(6<=$D$3,IF(OR('WSF DASHBOARD'!$C$4="",ISNUMBER(SEARCH('WSF DASHBOARD'!$C$4,INDEX(MASTER_AREAS!$B:$B,7)))),6,""),""),IF('WSF DASHBOARD'!$B$4="Zone",IF(6<=$D$4,IF(OR('WSF DASHBOARD'!$C$4="",ISNUMBER(SEARCH('WSF DASHBOARD'!$C$4,INDEX(MASTER_ZONES!$B:$B,7)))),6,""),""),"")) | B7: =IFERROR(SMALL($A$2:$A$1365,6),"") | C7: =IF(B7="","",IF('WSF DASHBOARD'!$B$4="Area",INDEX(MASTER_AREAS!$B:$B,B7+1),INDEX(MASTER_ZONES!$B:$B,B7+1))) | F7: =IF('TRANSPORT DASHBOARD'!$B$4="Area",IF(6<=$I$3,IF(OR('TRANSPORT DASHBOARD'!$C$4="",ISNUMBER(SEARCH('TRANSPORT DASHBOARD'!$C$4,INDEX(MASTER_AREAS!$B:$B,7)))),6,""),""),IF('TRANSPORT DASHBOARD'!$B$4="Zone",IF(6<=$I$4,IF(OR('TRANSPORT DASHBOARD'!$C$4="",ISNUMBER(SEARCH('TRANSPORT DASHBOARD'!$C$4,INDEX(MASTER_ZONES!$B:$B,7)))),6,""),""),"")) | G7: =IFERROR(SMALL($F$2:$F$1365,6),"") | H7: =IF(G7="","",IF('TRANSPORT DASHBOARD'!$B$4="Area",INDEX(MASTER_AREAS!$B:$B,G7+1),INDEX(MASTER_ZONES!$B:$B,G7+1)))
A8: =IF('WSF DASHBOARD'!$B$4="Area",IF(7<=$D$3,IF(OR('WSF DASHBOARD'!$C$4="",ISNUMBER(SEARCH('WSF DASHBOARD'!$C$4,INDEX(MASTER_AREAS!$B:$B,8)))),7,""),""),IF('WSF DASHBOARD'!$B$4="Zone",IF(7<=$D$4,IF(OR('WSF DASHBOARD'!$C$4="",ISNUMBER(SEARCH('WSF DASHBOARD'!$C$4,INDEX(MASTER_ZONES!$B:$B,8)))),7,""),""),"")) | B8: =IFERROR(SMALL($A$2:$A$1365,7),"") | C8: =IF(B8="","",IF('WSF DASHBOARD'!$B$4="Area",INDEX(MASTER_AREAS!$B:$B,B8+1),INDEX(MASTER_ZONES!$B:$B,B8+1))) | F8: =IF('TRANSPORT DASHBOARD'!$B$4="Area",IF(7<=$I$3,IF(OR('TRANSPORT DASHBOARD'!$C$4="",ISNUMBER(SEARCH('TRANSPORT DASHBOARD'!$C$4,INDEX(MASTER_AREAS!$B:$B,8)))),7,""),""),IF('TRANSPORT DASHBOARD'!$B$4="Zone",IF(7<=$I$4,IF(OR('TRANSPORT DASHBOARD'!$C$4="",ISNUMBER(SEARCH('TRANSPORT DASHBOARD'!$C$4,INDEX(MASTER_ZONES!$B:$B,8)))),7,""),""),"")) | G8: =IFERROR(SMALL($F$2:$F$1365,7),"") | H8: =IF(G8="","",IF('TRANSPORT DASHBOARD'!$B$4="Area",INDEX(MASTER_AREAS!$B:$B,G8+1),INDEX(MASTER_ZONES!$B:$B,G8+1)))
A9: =IF('WSF DASHBOARD'!$B$4="Area",IF(8<=$D$3,IF(OR('WSF DASHBOARD'!$C$4="",ISNUMBER(SEARCH('WSF DASHBOARD'!$C$4,INDEX(MASTER_AREAS!$B:$B,9)))),8,""),""),IF('WSF DASHBOARD'!$B$4="Zone",IF(8<=$D$4,IF(OR('WSF DASHBOARD'!$C$4="",ISNUMBER(SEARCH('WSF DASHBOARD'!$C$4,INDEX(MASTER_ZONES!$B:$B,9)))),8,""),""),"")) | B9: =IFERROR(SMALL($A$2:$A$1365,8),"") | C9: =IF(B9="","",IF('WSF DASHBOARD'!$B$4="Area",INDEX(MASTER_AREAS!$B:$B,B9+1),INDEX(MASTER_ZONES!$B:$B,B9+1))) | F9: =IF('TRANSPORT DASHBOARD'!$B$4="Area",IF(8<=$I$3,IF(OR('TRANSPORT DASHBOARD'!$C$4="",ISNUMBER(SEARCH('TRANSPORT DASHBOARD'!$C$4,INDEX(MASTER_AREAS!$B:$B,9)))),8,""),""),IF('TRANSPORT DASHBOARD'!$B$4="Zone",IF(8<=$I$4,IF(OR('TRANSPORT DASHBOARD'!$C$4="",ISNUMBER(SEARCH('TRANSPORT DASHBOARD'!$C$4,INDEX(MASTER_ZONES!$B:$B,9)))),8,""),""),"")) | G9: =IFERROR(SMALL($F$2:$F$1365,8),"") | H9: =IF(G9="","",IF('TRANSPORT DASHBOARD'!$B$4="Area",INDEX(MASTER_AREAS!$B:$B,G9+1),INDEX(MASTER_ZONES!$B:$B,G9+1)))
A10: =IF('WSF DASHBOARD'!$B$4="Area",IF(9<=$D$3,IF(OR('WSF DASHBOARD'!$C$4="",ISNUMBER(SEARCH('WSF DASHBOARD'!$C$4,INDEX(MASTER_AREAS!$B:$B,10)))),9,""),""),IF('WSF DASHBOARD'!$B$4="Zone",IF(9<=$D$4,IF(OR('WSF DASHBOARD'!$C$4="",ISNUMBER(SEARCH('WSF DASHBOARD'!$C$4,INDEX(MASTER_ZONES!$B:$B,10)))),9,""),""),"")) | B10: =IFERROR(SMALL($A$2:$A$1365,9),"") | C10: =IF(B10="","",IF('WSF DASHBOARD'!$B$4="Area",INDEX(MASTER_AREAS!$B:$B,B10+1),INDEX(MASTER_ZONES!$B:$B,B10+1))) | F10: =IF('TRANSPORT DASHBOARD'!$B$4="Area",IF(9<=$I$3,IF(OR('TRANSPORT DASHBOARD'!$C$4="",ISNUMBER(SEARCH('TRANSPORT DASHBOARD'!$C$4,INDEX(MASTER_AREAS!$B:$B,10)))),9,""),""),IF('TRANSPORT DASHBOARD'!$B$4="Zone",IF(9<=$I$4,IF(OR('TRANSPORT DASHBOARD'!$C$4="",ISNUMBER(SEARCH('TRANSPORT DASHBOARD'!$C$4,INDEX(MASTER_ZONES!$B:$B,10)))),9,""),""),"")) | G10: =IFERROR(SMALL($F$2:$F$1365,9),"") | H10: =IF(G10="","",IF('TRANSPORT DASHBOARD'!$B$4="Area",INDEX(MASTER_AREAS!$B:$B,G10+1),INDEX(MASTER_ZONES!$B:$B,G10+1)))
A11: =IF('WSF DASHBOARD'!$B$4="Area",IF(10<=$D$3,IF(OR('WSF DASHBOARD'!$C$4="",ISNUMBER(SEARCH('WSF DASHBOARD'!$C$4,INDEX(MASTER_AREAS!$B:$B,11)))),10,""),""),IF('WSF DASHBOARD'!$B$4="Zone",IF(10<=$D$4,IF(OR('WSF DASHBOARD'!$C$4="",ISNUMBER(SEARCH('WSF DASHBOARD'!$C$4,INDEX(MASTER_ZONES!$B:$B,11)))),10,""),""),"")) | B11: =IFERROR(SMALL($A$2:$A$1365,10),"") | C11: =IF(B11="","",IF('WSF DASHBOARD'!$B$4="Area",INDEX(MASTER_AREAS!$B:$B,B11+1),INDEX(MASTER_ZONES!$B:$B,B11+1))) | F11: =IF('TRANSPORT DASHBOARD'!$B$4="Area",IF(10<=$I$3,IF(OR('TRANSPORT DASHBOARD'!$C$4="",ISNUMBER(SEARCH('TRANSPORT DASHBOARD'!$C$4,INDEX(MASTER_AREAS!$B:$B,11)))),10,""),""),IF('TRANSPORT DASHBOARD'!$B$4="Zone",IF(10<=$I$4,IF(OR('TRANSPORT DASHBOARD'!$C$4="",ISNUMBER(SEARCH('TRANSPORT DASHBOARD'!$C$4,INDEX(MASTER_ZONES!$B:$B,11)))),10,""),""),"")) | G11: =IFERROR(SMALL($F$2:$F$1365,10),"") | H11: =IF(G11="","",IF('TRANSPORT DASHBOARD'!$B$4="Area",INDEX(MASTER_AREAS!$B:$B,G11+1),INDEX(MASTER_ZONES!$B:$B,G11+1)))
A12: =IF('WSF DASHBOARD'!$B$4="Area",IF(11<=$D$3,IF(OR('WSF DASHBOARD'!$C$4="",ISNUMBER(SEARCH('WSF DASHBOARD'!$C$4,INDEX(MASTER_AREAS!$B:$B,12)))),11,""),""),IF('WSF DASHBOARD'!$B$4="Zone",IF(11<=$D$4,IF(OR('WSF DASHBOARD'!$C$4="",ISNUMBER(SEARCH('WSF DASHBOARD'!$C$4,INDEX(MASTER_ZONES!$B:$B,12)))),11,""),""),"")) | B12: =IFERROR(SMALL($A$2:$A$1365,11),"") | C12: =IF(B12="","",IF('WSF DASHBOARD'!$B$4="Area",INDEX(MASTER_AREAS!$B:$B,B12+1),INDEX(MASTER_ZONES!$B:$B,B12+1))) | F12: =IF('TRANSPORT DASHBOARD'!$B$4="Area",IF(11<=$I$3,IF(OR('TRANSPORT DASHBOARD'!$C$4="",ISNUMBER(SEARCH('TRANSPORT DASHBOARD'!$C$4,INDEX(MASTER_AREAS!$B:$B,12)))),11,""),""),IF('TRANSPORT DASHBOARD'!$B$4="Zone",IF(11<=$I$4,IF(OR('TRANSPORT DASHBOARD'!$C$4="",ISNUMBER(SEARCH('TRANSPORT DASHBOARD'!$C$4,INDEX(MASTER_ZONES!$B:$B,12)))),11,""),""),"")) | G12: =IFERROR(SMALL($F$2:$F$1365,11),"") | H12: =IF(G12="","",IF('TRANSPORT DASHBOARD'!$B$4="Area",INDEX(MASTER_AREAS!$B:$B,G12+1),INDEX(MASTER_ZONES!$B:$B,G12+1)))
A13: =IF('WSF DASHBOARD'!$B$4="Area",IF(12<=$D$3,IF(OR('WSF DASHBOARD'!$C$4="",ISNUMBER(SEARCH('WSF DASHBOARD'!$C$4,INDEX(MASTER_AREAS!$B:$B,13)))),12,""),""),IF('WSF DASHBOARD'!$B$4="Zone",IF(12<=$D$4,IF(OR('WSF DASHBOARD'!$C$4="",ISNUMBER(SEARCH('WSF DASHBOARD'!$C$4,INDEX(MASTER_ZONES!$B:$B,13)))),12,""),""),"")) | B13: =IFERROR(SMALL($A$2:$A$1365,12),"") | C13: =IF(B13="","",IF('WSF DASHBOARD'!$B$4="Area",INDEX(MASTER_AREAS!$B:$B,B13+1),INDEX(MASTER_ZONES!$B:$B,B13+1))) | F13: =IF('TRANSPORT DASHBOARD'!$B$4="Area",IF(12<=$I$3,IF(OR('TRANSPORT DASHBOARD'!$C$4="",ISNUMBER(SEARCH('TRANSPORT DASHBOARD'!$C$4,INDEX(MASTER_AREAS!$B:$B,13)))),12,""),""),IF('TRANSPORT DASHBOARD'!$B$4="Zone",IF(12<=$I$4,IF(OR('TRANSPORT DASHBOARD'!$C$4="",ISNUMBER(SEARCH('TRANSPORT DASHBOARD'!$C$4,INDEX(MASTER_ZONES!$B:$B,13)))),12,""),""),"")) | G13: =IFERROR(SMALL($F$2:$F$1365,12),"") | H13: =IF(G13="","",IF('TRANSPORT DASHBOARD'!$B$4="Area",INDEX(MASTER_AREAS!$B:$B,G13+1),INDEX(MASTER_ZONES!$B:$B,G13+1)))
A14: =IF('WSF DASHBOARD'!$B$4="Area",IF(13<=$D$3,IF(OR('WSF DASHBOARD'!$C$4="",ISNUMBER(SEARCH('WSF DASHBOARD'!$C$4,INDEX(MASTER_AREAS!$B:$B,14)))),13,""),""),IF('WSF DASHBOARD'!$B$4="Zone",IF(13<=$D$4,IF(OR('WSF DASHBOARD'!$C$4="",ISNUMBER(SEARCH('WSF DASHBOARD'!$C$4,INDEX(MASTER_ZONES!$B:$B,14)))),13,""),""),"")) | B14: =IFERROR(SMALL($A$2:$A$1365,13),"") | C14: =IF(B14="","",IF('WSF DASHBOARD'!$B$4="Area",INDEX(MASTER_AREAS!$B:$B,B14+1),INDEX(MASTER_ZONES!$B:$B,B14+1))) | F14: =IF('TRANSPORT DASHBOARD'!$B$4="Area",IF(13<=$I$3,IF(OR('TRANSPORT DASHBOARD'!$C$4="",ISNUMBER(SEARCH('TRANSPORT DASHBOARD'!$C$4,INDEX(MASTER_AREAS!$B:$B,14)))),13,""),""),IF('TRANSPORT DASHBOARD'!$B$4="Zone",IF(13<=$I$4,IF(OR('TRANSPORT DASHBOARD'!$C$4="",ISNUMBER(SEARCH('TRANSPORT DASHBOARD'!$C$4,INDEX(MASTER_ZONES!$B:$B,14)))),13,""),""),"")) | G14: =IFERROR(SMALL($F$2:$F$1365,13),"") | H14: =IF(G14="","",IF('TRANSPORT DASHBOARD'!$B$4="Area",INDEX(MASTER_AREAS!$B:$B,G14+1),INDEX(MASTER_ZONES!$B:$B,G14+1)))
A15: =IF('WSF DASHBOARD'!$B$4="Area",IF(14<=$D$3,IF(OR('WSF DASHBOARD'!$C$4="",ISNUMBER(SEARCH('WSF DASHBOARD'!$C$4,INDEX(MASTER_AREAS!$B:$B,15)))),14,""),""),IF('WSF DASHBOARD'!$B$4="Zone",IF(14<=$D$4,IF(OR('WSF DASHBOARD'!$C$4="",ISNUMBER(SEARCH('WSF DASHBOARD'!$C$4,INDEX(MASTER_ZONES!$B:$B,15)))),14,""),""),"")) | B15: =IFERROR(SMALL($A$2:$A$1365,14),"") | C15: =IF(B15="","",IF('WSF DASHBOARD'!$B$4="Area",INDEX(MASTER_AREAS!$B:$B,B15+1),INDEX(MASTER_ZONES!$B:$B,B15+1))) | F15: =IF('TRANSPORT DASHBOARD'!$B$4="Area",IF(14<=$I$3,IF(OR('TRANSPORT DASHBOARD'!$C$4="",ISNUMBER(SEARCH('TRANSPORT DASHBOARD'!$C$4,INDEX(MASTER_AREAS!$B:$B,15)))),14,""),""),IF('TRANSPORT DASHBOARD'!$B$4="Zone",IF(14<=$I$4,IF(OR('TRANSPORT DASHBOARD'!$C$4="",ISNUMBER(SEARCH('TRANSPORT DASHBOARD'!$C$4,INDEX(MASTER_ZONES!$B:$B,15)))),14,""),""),"")) | G15: =IFERROR(SMALL($F$2:$F$1365,14),"") | H15: =IF(G15="","",IF('TRANSPORT DASHBOARD'!$B$4="Area",INDEX(MASTER_AREAS!$B:$B,G15+1),INDEX(MASTER_ZONES!$B:$B,G15+1)))
A16: =IF('WSF DASHBOARD'!$B$4="Area",IF(15<=$D$3,IF(OR('WSF DASHBOARD'!$C$4="",ISNUMBER(SEARCH('WSF DASHBOARD'!$C$4,INDEX(MASTER_AREAS!$B:$B,16)))),15,""),""),IF('WSF DASHBOARD'!$B$4="Zone",IF(15<=$D$4,IF(OR('WSF DASHBOARD'!$C$4="",ISNUMBER(SEARCH('WSF DASHBOARD'!$C$4,INDEX(MASTER_ZONES!$B:$B,16)))),15,""),""),"")) | B16: =IFERROR(SMALL($A$2:$A$1365,15),"") | C16: =IF(B16="","",IF('WSF DASHBOARD'!$B$4="Area",INDEX(MASTER_AREAS!$B:$B,B16+1),INDEX(MASTER_ZONES!$B:$B,B16+1))) | F16: =IF('TRANSPORT DASHBOARD'!$B$4="Area",IF(15<=$I$3,IF(OR('TRANSPORT DASHBOARD'!$C$4="",ISNUMBER(SEARCH('TRANSPORT DASHBOARD'!$C$4,INDEX(MASTER_AREAS!$B:$B,16)))),15,""),""),IF('TRANSPORT DASHBOARD'!$B$4="Zone",IF(15<=$I$4,IF(OR('TRANSPORT DASHBOARD'!$C$4="",ISNUMBER(SEARCH('TRANSPORT DASHBOARD'!$C$4,INDEX(MASTER_ZONES!$B:$B,16)))),15,""),""),"")) | G16: =IFERROR(SMALL($F$2:$F$1365,15),"") | H16: =IF(G16="","",IF('TRANSPORT DASHBOARD'!$B$4="Area",INDEX(MASTER_AREAS!$B:$B,G16+1),INDEX(MASTER_ZONES!$B:$B,G16+1)))
A17: =IF('WSF DASHBOARD'!$B$4="Area",IF(16<=$D$3,IF(OR('WSF DASHBOARD'!$C$4="",ISNUMBER(SEARCH('WSF DASHBOARD'!$C$4,INDEX(MASTER_AREAS!$B:$B,17)))),16,""),""),IF('WSF DASHBOARD'!$B$4="Zone",IF(16<=$D$4,IF(OR('WSF DASHBOARD'!$C$4="",ISNUMBER(SEARCH('WSF DASHBOARD'!$C$4,INDEX(MASTER_ZONES!$B:$B,17)))),16,""),""),"")) | B17: =IFERROR(SMALL($A$2:$A$1365,16),"") | C17: =IF(B17="","",IF('WSF DASHBOARD'!$B$4="Area",INDEX(MASTER_AREAS!$B:$B,B17+1),INDEX(MASTER_ZONES!$B:$B,B17+1))) | F17: =IF('TRANSPORT DASHBOARD'!$B$4="Area",IF(16<=$I$3,IF(OR('TRANSPORT DASHBOARD'!$C$4="",ISNUMBER(SEARCH('TRANSPORT DASHBOARD'!$C$4,INDEX(MASTER_AREAS!$B:$B,17)))),16,""),""),IF('TRANSPORT DASHBOARD'!$B$4="Zone",IF(16<=$I$4,IF(OR('TRANSPORT DASHBOARD'!$C$4="",ISNUMBER(SEARCH('TRANSPORT DASHBOARD'!$C$4,INDEX(MASTER_ZONES!$B:$B,17)))),16,""),""),"")) | G17: =IFERROR(SMALL($F$2:$F$1365,16),"") | H17: =IF(G17="","",IF('TRANSPORT DASHBOARD'!$B$4="Area",INDEX(MASTER_AREAS!$B:$B,G17+1),INDEX(MASTER_ZONES!$B:$B,G17+1)))
A18: =IF('WSF DASHBOARD'!$B$4="Area",IF(17<=$D$3,IF(OR('WSF DASHBOARD'!$C$4="",ISNUMBER(SEARCH('WSF DASHBOARD'!$C$4,INDEX(MASTER_AREAS!$B:$B,18)))),17,""),""),IF('WSF DASHBOARD'!$B$4="Zone",IF(17<=$D$4,IF(OR('WSF DASHBOARD'!$C$4="",ISNUMBER(SEARCH('WSF DASHBOARD'!$C$4,INDEX(MASTER_ZONES!$B:$B,18)))),17,""),""),"")) | B18: =IFERROR(SMALL($A$2:$A$1365,17),"") | C18: =IF(B18="","",IF('WSF DASHBOARD'!$B$4="Area",INDEX(MASTER_AREAS!$B:$B,B18+1),INDEX(MASTER_ZONES!$B:$B,B18+1))) | F18: =IF('TRANSPORT DASHBOARD'!$B$4="Area",IF(17<=$I$3,IF(OR('TRANSPORT DASHBOARD'!$C$4="",ISNUMBER(SEARCH('TRANSPORT DASHBOARD'!$C$4,INDEX(MASTER_AREAS!$B:$B,18)))),17,""),""),IF('TRANSPORT DASHBOARD'!$B$4="Zone",IF(17<=$I$4,IF(OR('TRANSPORT DASHBOARD'!$C$4="",ISNUMBER(SEARCH('TRANSPORT DASHBOARD'!$C$4,INDEX(MASTER_ZONES!$B:$B,18)))),17,""),""),"")) | G18: =IFERROR(SMALL($F$2:$F$1365,17),"") | H18: =IF(G18="","",IF('TRANSPORT DASHBOARD'!$B$4="Area",INDEX(MASTER_AREAS!$B:$B,G18+1),INDEX(MASTER_ZONES!$B:$B,G18+1)))
A19: =IF('WSF DASHBOARD'!$B$4="Area",IF(18<=$D$3,IF(OR('WSF DASHBOARD'!$C$4="",ISNUMBER(SEARCH('WSF DASHBOARD'!$C$4,INDEX(MASTER_AREAS!$B:$B,19)))),18,""),""),IF('WSF DASHBOARD'!$B$4="Zone",IF(18<=$D$4,IF(OR('WSF DASHBOARD'!$C$4="",ISNUMBER(SEARCH('WSF DASHBOARD'!$C$4,INDEX(MASTER_ZONES!$B:$B,19)))),18,""),""),"")) | B19: =IFERROR(SMALL($A$2:$A$1365,18),"") | C19: =IF(B19="","",IF('WSF DASHBOARD'!$B$4="Area",INDEX(MASTER_AREAS!$B:$B,B19+1),INDEX(MASTER_ZONES!$B:$B,B19+1))) | F19: =IF('TRANSPORT DASHBOARD'!$B$4="Area",IF(18<=$I$3,IF(OR('TRANSPORT DASHBOARD'!$C$4="",ISNUMBER(SEARCH('TRANSPORT DASHBOARD'!$C$4,INDEX(MASTER_AREAS!$B:$B,19)))),18,""),""),IF('TRANSPORT DASHBOARD'!$B$4="Zone",IF(18<=$I$4,IF(OR('TRANSPORT DASHBOARD'!$C$4="",ISNUMBER(SEARCH('TRANSPORT DASHBOARD'!$C$4,INDEX(MASTER_ZONES!$B:$B,19)))),18,""),""),"")) | G19: =IFERROR(SMALL($F$2:$F$1365,18),"") | H19: =IF(G19="","",IF('TRANSPORT DASHBOARD'!$B$4="Area",INDEX(MASTER_AREAS!$B:$B,G19+1),INDEX(MASTER_ZONES!$B:$B,G19+1)))
A20: =IF('WSF DASHBOARD'!$B$4="Area",IF(19<=$D$3,IF(OR('WSF DASHBOARD'!$C$4="",ISNUMBER(SEARCH('WSF DASHBOARD'!$C$4,INDEX(MASTER_AREAS!$B:$B,20)))),19,""),""),IF('WSF DASHBOARD'!$B$4="Zone",IF(19<=$D$4,IF(OR('WSF DASHBOARD'!$C$4="",ISNUMBER(SEARCH('WSF DASHBOARD'!$C$4,INDEX(MASTER_ZONES!$B:$B,20)))),19,""),""),"")) | B20: =IFERROR(SMALL($A$2:$A$1365,19),"") | C20: =IF(B20="","",IF('WSF DASHBOARD'!$B$4="Area",INDEX(MASTER_AREAS!$B:$B,B20+1),INDEX(MASTER_ZONES!$B:$B,B20+1))) | F20: =IF('TRANSPORT DASHBOARD'!$B$4="Area",IF(19<=$I$3,IF(OR('TRANSPORT DASHBOARD'!$C$4="",ISNUMBER(SEARCH('TRANSPORT DASHBOARD'!$C$4,INDEX(MASTER_AREAS!$B:$B,20)))),19,""),""),IF('TRANSPORT DASHBOARD'!$B$4="Zone",IF(19<=$I$4,IF(OR('TRANSPORT DASHBOARD'!$C$4="",ISNUMBER(SEARCH('TRANSPORT DASHBOARD'!$C$4,INDEX(MASTER_ZONES!$B:$B,20)))),19,""),""),"")) | G20: =IFERROR(SMALL($F$2:$F$1365,19),"") | H20: =IF(G20="","",IF('TRANSPORT DASHBOARD'!$B$4="Area",INDEX(MASTER_AREAS!$B:$B,G20+1),INDEX(MASTER_ZONES!$B:$B,G20+1)))
A21: =IF('WSF DASHBOARD'!$B$4="Area",IF(20<=$D$3,IF(OR('WSF DASHBOARD'!$C$4="",ISNUMBER(SEARCH('WSF DASHBOARD'!$C$4,INDEX(MASTER_AREAS!$B:$B,21)))),20,""),""),IF('WSF DASHBOARD'!$B$4="Zone",IF(20<=$D$4,IF(OR('WSF DASHBOARD'!$C$4="",ISNUMBER(SEARCH('WSF DASHBOARD'!$C$4,INDEX(MASTER_ZONES!$B:$B,21)))),20,""),""),"")) | B21: =IFERROR(SMALL($A$2:$A$1365,20),"") | C21: =IF(B21="","",IF('WSF DASHBOARD'!$B$4="Area",INDEX(MASTER_AREAS!$B:$B,B21+1),INDEX(MASTER_ZONES!$B:$B,B21+1))) | F21: =IF('TRANSPORT DASHBOARD'!$B$4="Area",IF(20<=$I$3,IF(OR('TRANSPORT DASHBOARD'!$C$4="",ISNUMBER(SEARCH('TRANSPORT DASHBOARD'!$C$4,INDEX(MASTER_AREAS!$B:$B,21)))),20,""),""),IF('TRANSPORT DASHBOARD'!$B$4="Zone",IF(20<=$I$4,IF(OR('TRANSPORT DASHBOARD'!$C$4="",ISNUMBER(SEARCH('TRANSPORT DASHBOARD'!$C$4,INDEX(MASTER_ZONES!$B:$B,21)))),20,""),""),"")) | G21: =IFERROR(SMALL($F$2:$F$1365,20),"") | H21: =IF(G21="","",IF('TRANSPORT DASHBOARD'!$B$4="Area",INDEX(MASTER_AREAS!$B:$B,G21+1),INDEX(MASTER_ZONES!$B:$B,G21+1)))
A22: =IF('WSF DASHBOARD'!$B$4="Area",IF(21<=$D$3,IF(OR('WSF DASHBOARD'!$C$4="",ISNUMBER(SEARCH('WSF DASHBOARD'!$C$4,INDEX(MASTER_AREAS!$B:$B,22)))),21,""),""),IF('WSF DASHBOARD'!$B$4="Zone",IF(21<=$D$4,IF(OR('WSF DASHBOARD'!$C$4="",ISNUMBER(SEARCH('WSF DASHBOARD'!$C$4,INDEX(MASTER_ZONES!$B:$B,22)))),21,""),""),"")) | B22: =IFERROR(SMALL($A$2:$A$1365,21),"") | C22: =IF(B22="","",IF('WSF DASHBOARD'!$B$4="Area",INDEX(MASTER_AREAS!$B:$B,B22+1),INDEX(MASTER_ZONES!$B:$B,B22+1))) | F22: =IF('TRANSPORT DASHBOARD'!$B$4="Area",IF(21<=$I$3,IF(OR('TRANSPORT DASHBOARD'!$C$4="",ISNUMBER(SEARCH('TRANSPORT DASHBOARD'!$C$4,INDEX(MASTER_AREAS!$B:$B,22)))),21,""),""),IF('TRANSPORT DASHBOARD'!$B$4="Zone",IF(21<=$I$4,IF(OR('TRANSPORT DASHBOARD'!$C$4="",ISNUMBER(SEARCH('TRANSPORT DASHBOARD'!$C$4,INDEX(MASTER_ZONES!$B:$B,22)))),21,""),""),"")) | G22: =IFERROR(SMALL($F$2:$F$1365,21),"") | H22: =IF(G22="","",IF('TRANSPORT DASHBOARD'!$B$4="Area",INDEX(MASTER_AREAS!$B:$B,G22+1),INDEX(MASTER_ZONES!$B:$B,G22+1)))
A23: =IF('WSF DASHBOARD'!$B$4="Area",IF(22<=$D$3,IF(OR('WSF DASHBOARD'!$C$4="",ISNUMBER(SEARCH('WSF DASHBOARD'!$C$4,INDEX(MASTER_AREAS!$B:$B,23)))),22,""),""),IF('WSF DASHBOARD'!$B$4="Zone",IF(22<=$D$4,IF(OR('WSF DASHBOARD'!$C$4="",ISNUMBER(SEARCH('WSF DASHBOARD'!$C$4,INDEX(MASTER_ZONES!$B:$B,23)))),22,""),""),"")) | B23: =IFERROR(SMALL($A$2:$A$1365,22),"") | C23: =IF(B23="","",IF('WSF DASHBOARD'!$B$4="Area",INDEX(MASTER_AREAS!$B:$B,B23+1),INDEX(MASTER_ZONES!$B:$B,B23+1))) | F23: =IF('TRANSPORT DASHBOARD'!$B$4="Area",IF(22<=$I$3,IF(OR('TRANSPORT DASHBOARD'!$C$4="",ISNUMBER(SEARCH('TRANSPORT DASHBOARD'!$C$4,INDEX(MASTER_AREAS!$B:$B,23)))),22,""),""),IF('TRANSPORT DASHBOARD'!$B$4="Zone",IF(22<=$I$4,IF(OR('TRANSPORT DASHBOARD'!$C$4="",ISNUMBER(SEARCH('TRANSPORT DASHBOARD'!$C$4,INDEX(MASTER_ZONES!$B:$B,23)))),22,""),""),"")) | G23: =IFERROR(SMALL($F$2:$F$1365,22),"") | H23: =IF(G23="","",IF('TRANSPORT DASHBOARD'!$B$4="Area",INDEX(MASTER_AREAS!$B:$B,G23+1),INDEX(MASTER_ZONES!$B:$B,G23+1)))
A24: =IF('WSF DASHBOARD'!$B$4="Area",IF(23<=$D$3,IF(OR('WSF DASHBOARD'!$C$4="",ISNUMBER(SEARCH('WSF DASHBOARD'!$C$4,INDEX(MASTER_AREAS!$B:$B,24)))),23,""),""),IF('WSF DASHBOARD'!$B$4="Zone",IF(23<=$D$4,IF(OR('WSF DASHBOARD'!$C$4="",ISNUMBER(SEARCH('WSF DASHBOARD'!$C$4,INDEX(MASTER_ZONES!$B:$B,24)))),23,""),""),"")) | B24: =IFERROR(SMALL($A$2:$A$1365,23),"") | C24: =IF(B24="","",IF('WSF DASHBOARD'!$B$4="Area",INDEX(MASTER_AREAS!$B:$B,B24+1),INDEX(MASTER_ZONES!$B:$B,B24+1))) | F24: =IF('TRANSPORT DASHBOARD'!$B$4="Area",IF(23<=$I$3,IF(OR('TRANSPORT DASHBOARD'!$C$4="",ISNUMBER(SEARCH('TRANSPORT DASHBOARD'!$C$4,INDEX(MASTER_AREAS!$B:$B,24)))),23,""),""),IF('TRANSPORT DASHBOARD'!$B$4="Zone",IF(23<=$I$4,IF(OR('TRANSPORT DASHBOARD'!$C$4="",ISNUMBER(SEARCH('TRANSPORT DASHBOARD'!$C$4,INDEX(MASTER_ZONES!$B:$B,24)))),23,""),""),"")) | G24: =IFERROR(SMALL($F$2:$F$1365,23),"") | H24: =IF(G24="","",IF('TRANSPORT DASHBOARD'!$B$4="Area",INDEX(MASTER_AREAS!$B:$B,G24+1),INDEX(MASTER_ZONES!$B:$B,G24+1)))
A25: =IF('WSF DASHBOARD'!$B$4="Area",IF(24<=$D$3,IF(OR('WSF DASHBOARD'!$C$4="",ISNUMBER(SEARCH('WSF DASHBOARD'!$C$4,INDEX(MASTER_AREAS!$B:$B,25)))),24,""),""),IF('WSF DASHBOARD'!$B$4="Zone",IF(24<=$D$4,IF(OR('WSF DASHBOARD'!$C$4="",ISNUMBER(SEARCH('WSF DASHBOARD'!$C$4,INDEX(MASTER_ZONES!$B:$B,25)))),24,""),""),"")) | B25: =IFERROR(SMALL($A$2:$A$1365,24),"") | C25: =IF(B25="","",IF('WSF DASHBOARD'!$B$4="Area",INDEX(MASTER_AREAS!$B:$B,B25+1),INDEX(MASTER_ZONES!$B:$B,B25+1))) | F25: =IF('TRANSPORT DASHBOARD'!$B$4="Area",IF(24<=$I$3,IF(OR('TRANSPORT DASHBOARD'!$C$4="",ISNUMBER(SEARCH('TRANSPORT DASHBOARD'!$C$4,INDEX(MASTER_AREAS!$B:$B,25)))),24,""),""),IF('TRANSPORT DASHBOARD'!$B$4="Zone",IF(24<=$I$4,IF(OR('TRANSPORT DASHBOARD'!$C$4="",ISNUMBER(SEARCH('TRANSPORT DASHBOARD'!$C$4,INDEX(MASTER_ZONES!$B:$B,25)))),24,""),""),"")) | G25: =IFERROR(SMALL($F$2:$F$1365,24),"") | H25: =IF(G25="","",IF('TRANSPORT DASHBOARD'!$B$4="Area",INDEX(MASTER_AREAS!$B:$B,G25+1),INDEX(MASTER_ZONES!$B:$B,G25+1)))
A26: =IF('WSF DASHBOARD'!$B$4="Area",IF(25<=$D$3,IF(OR('WSF DASHBOARD'!$C$4="",ISNUMBER(SEARCH('WSF DASHBOARD'!$C$4,INDEX(MASTER_AREAS!$B:$B,26)))),25,""),""),IF('WSF DASHBOARD'!$B$4="Zone",IF(25<=$D$4,IF(OR('WSF DASHBOARD'!$C$4="",ISNUMBER(SEARCH('WSF DASHBOARD'!$C$4,INDEX(MASTER_ZONES!$B:$B,26)))),25,""),""),"")) | B26: =IFERROR(SMALL($A$2:$A$1365,25),"") | C26: =IF(B26="","",IF('WSF DASHBOARD'!$B$4="Area",INDEX(MASTER_AREAS!$B:$B,B26+1),INDEX(MASTER_ZONES!$B:$B,B26+1))) | F26: =IF('TRANSPORT DASHBOARD'!$B$4="Area",IF(25<=$I$3,IF(OR('TRANSPORT DASHBOARD'!$C$4="",ISNUMBER(SEARCH('TRANSPORT DASHBOARD'!$C$4,INDEX(MASTER_AREAS!$B:$B,26)))),25,""),""),IF('TRANSPORT DASHBOARD'!$B$4="Zone",IF(25<=$I$4,IF(OR('TRANSPORT DASHBOARD'!$C$4="",ISNUMBER(SEARCH('TRANSPORT DASHBOARD'!$C$4,INDEX(MASTER_ZONES!$B:$B,26)))),25,""),""),"")) | G26: =IFERROR(SMALL($F$2:$F$1365,25),"") | H26: =IF(G26="","",IF('TRANSPORT DASHBOARD'!$B$4="Area",INDEX(MASTER_AREAS!$B:$B,G26+1),INDEX(MASTER_ZONES!$B:$B,G26+1)))
A27: =IF('WSF DASHBOARD'!$B$4="Area",IF(26<=$D$3,IF(OR('WSF DASHBOARD'!$C$4="",ISNUMBER(SEARCH('WSF DASHBOARD'!$C$4,INDEX(MASTER_AREAS!$B:$B,27)))),26,""),""),IF('WSF DASHBOARD'!$B$4="Zone",IF(26<=$D$4,IF(OR('WSF DASHBOARD'!$C$4="",ISNUMBER(SEARCH('WSF DASHBOARD'!$C$4,INDEX(MASTER_ZONES!$B:$B,27)))),26,""),""),"")) | B27: =IFERROR(SMALL($A$2:$A$1365,26),"") | C27: =IF(B27="","",IF('WSF DASHBOARD'!$B$4="Area",INDEX(MASTER_AREAS!$B:$B,B27+1),INDEX(MASTER_ZONES!$B:$B,B27+1))) | F27: =IF('TRANSPORT DASHBOARD'!$B$4="Area",IF(26<=$I$3,IF(OR('TRANSPORT DASHBOARD'!$C$4="",ISNUMBER(SEARCH('TRANSPORT DASHBOARD'!$C$4,INDEX(MASTER_AREAS!$B:$B,27)))),26,""),""),IF('TRANSPORT DASHBOARD'!$B$4="Zone",IF(26<=$I$4,IF(OR('TRANSPORT DASHBOARD'!$C$4="",ISNUMBER(SEARCH('TRANSPORT DASHBOARD'!$C$4,INDEX(MASTER_ZONES!$B:$B,27)))),26,""),""),"")) | G27: =IFERROR(SMALL($F$2:$F$1365,26),"") | H27: =IF(G27="","",IF('TRANSPORT DASHBOARD'!$B$4="Area",INDEX(MASTER_AREAS!$B:$B,G27+1),INDEX(MASTER_ZONES!$B:$B,G27+1)))
A28: =IF('WSF DASHBOARD'!$B$4="Area",IF(27<=$D$3,IF(OR('WSF DASHBOARD'!$C$4="",ISNUMBER(SEARCH('WSF DASHBOARD'!$C$4,INDEX(MASTER_AREAS!$B:$B,28)))),27,""),""),IF('WSF DASHBOARD'!$B$4="Zone",IF(27<=$D$4,IF(OR('WSF DASHBOARD'!$C$4="",ISNUMBER(SEARCH('WSF DASHBOARD'!$C$4,INDEX(MASTER_ZONES!$B:$B,28)))),27,""),""),"")) | B28: =IFERROR(SMALL($A$2:$A$1365,27),"") | C28: =IF(B28="","",IF('WSF DASHBOARD'!$B$4="Area",INDEX(MASTER_AREAS!$B:$B,B28+1),INDEX(MASTER_ZONES!$B:$B,B28+1))) | F28: =IF('TRANSPORT DASHBOARD'!$B$4="Area",IF(27<=$I$3,IF(OR('TRANSPORT DASHBOARD'!$C$4="",ISNUMBER(SEARCH('TRANSPORT DASHBOARD'!$C$4,INDEX(MASTER_AREAS!$B:$B,28)))),27,""),""),IF('TRANSPORT DASHBOARD'!$B$4="Zone",IF(27<=$I$4,IF(OR('TRANSPORT DASHBOARD'!$C$4="",ISNUMBER(SEARCH('TRANSPORT DASHBOARD'!$C$4,INDEX(MASTER_ZONES!$B:$B,28)))),27,""),""),"")) | G28: =IFERROR(SMALL($F$2:$F$1365,27),"") | H28: =IF(G28="","",IF('TRANSPORT DASHBOARD'!$B$4="Area",INDEX(MASTER_AREAS!$B:$B,G28+1),INDEX(MASTER_ZONES!$B:$B,G28+1)))
A29: =IF('WSF DASHBOARD'!$B$4="Area",IF(28<=$D$3,IF(OR('WSF DASHBOARD'!$C$4="",ISNUMBER(SEARCH('WSF DASHBOARD'!$C$4,INDEX(MASTER_AREAS!$B:$B,29)))),28,""),""),IF('WSF DASHBOARD'!$B$4="Zone",IF(28<=$D$4,IF(OR('WSF DASHBOARD'!$C$4="",ISNUMBER(SEARCH('WSF DASHBOARD'!$C$4,INDEX(MASTER_ZONES!$B:$B,29)))),28,""),""),"")) | B29: =IFERROR(SMALL($A$2:$A$1365,28),"") | C29: =IF(B29="","",IF('WSF DASHBOARD'!$B$4="Area",INDEX(MASTER_AREAS!$B:$B,B29+1),INDEX(MASTER_ZONES!$B:$B,B29+1))) | F29: =IF('TRANSPORT DASHBOARD'!$B$4="Area",IF(28<=$I$3,IF(OR('TRANSPORT DASHBOARD'!$C$4="",ISNUMBER(SEARCH('TRANSPORT DASHBOARD'!$C$4,INDEX(MASTER_AREAS!$B:$B,29)))),28,""),""),IF('TRANSPORT DASHBOARD'!$B$4="Zone",IF(28<=$I$4,IF(OR('TRANSPORT DASHBOARD'!$C$4="",ISNUMBER(SEARCH('TRANSPORT DASHBOARD'!$C$4,INDEX(MASTER_ZONES!$B:$B,29)))),28,""),""),"")) | G29: =IFERROR(SMALL($F$2:$F$1365,28),"") | H29: =IF(G29="","",IF('TRANSPORT DASHBOARD'!$B$4="Area",INDEX(MASTER_AREAS!$B:$B,G29+1),INDEX(MASTER_ZONES!$B:$B,G29+1)))
A30: =IF('WSF DASHBOARD'!$B$4="Area",IF(29<=$D$3,IF(OR('WSF DASHBOARD'!$C$4="",ISNUMBER(SEARCH('WSF DASHBOARD'!$C$4,INDEX(MASTER_AREAS!$B:$B,30)))),29,""),""),IF('WSF DASHBOARD'!$B$4="Zone",IF(29<=$D$4,IF(OR('WSF DASHBOARD'!$C$4="",ISNUMBER(SEARCH('WSF DASHBOARD'!$C$4,INDEX(MASTER_ZONES!$B:$B,30)))),29,""),""),"")) | B30: =IFERROR(SMALL($A$2:$A$1365,29),"") | C30: =IF(B30="","",IF('WSF DASHBOARD'!$B$4="Area",INDEX(MASTER_AREAS!$B:$B,B30+1),INDEX(MASTER_ZONES!$B:$B,B30+1))) | F30: =IF('TRANSPORT DASHBOARD'!$B$4="Area",IF(29<=$I$3,IF(OR('TRANSPORT DASHBOARD'!$C$4="",ISNUMBER(SEARCH('TRANSPORT DASHBOARD'!$C$4,INDEX(MASTER_AREAS!$B:$B,30)))),29,""),""),IF('TRANSPORT DASHBOARD'!$B$4="Zone",IF(29<=$I$4,IF(OR('TRANSPORT DASHBOARD'!$C$4="",ISNUMBER(SEARCH('TRANSPORT DASHBOARD'!$C$4,INDEX(MASTER_ZONES!$B:$B,30)))),29,""),""),"")) | G30: =IFERROR(SMALL($F$2:$F$1365,29),"") | H30: =IF(G30="","",IF('TRANSPORT DASHBOARD'!$B$4="Area",INDEX(MASTER_AREAS!$B:$B,G30+1),INDEX(MASTER_ZONES!$B:$B,G30+1)))
A31: =IF('WSF DASHBOARD'!$B$4="Area",IF(30<=$D$3,IF(OR('WSF DASHBOARD'!$C$4="",ISNUMBER(SEARCH('WSF DASHBOARD'!$C$4,INDEX(MASTER_AREAS!$B:$B,31)))),30,""),""),IF('WSF DASHBOARD'!$B$4="Zone",IF(30<=$D$4,IF(OR('WSF DASHBOARD'!$C$4="",ISNUMBER(SEARCH('WSF DASHBOARD'!$C$4,INDEX(MASTER_ZONES!$B:$B,31)))),30,""),""),"")) | B31: =IFERROR(SMALL($A$2:$A$1365,30),"") | C31: =IF(B31="","",IF('WSF DASHBOARD'!$B$4="Area",INDEX(MASTER_AREAS!$B:$B,B31+1),INDEX(MASTER_ZONES!$B:$B,B31+1))) | F31: =IF('TRANSPORT DASHBOARD'!$B$4="Area",IF(30<=$I$3,IF(OR('TRANSPORT DASHBOARD'!$C$4="",ISNUMBER(SEARCH('TRANSPORT DASHBOARD'!$C$4,INDEX(MASTER_AREAS!$B:$B,31)))),30,""),""),IF('TRANSPORT DASHBOARD'!$B$4="Zone",IF(30<=$I$4,IF(OR('TRANSPORT DASHBOARD'!$C$4="",ISNUMBER(SEARCH('TRANSPORT DASHBOARD'!$C$4,INDEX(MASTER_ZONES!$B:$B,31)))),30,""),""),"")) | G31: =IFERROR(SMALL($F$2:$F$1365,30),"") | H31: =IF(G31="","",IF('TRANSPORT DASHBOARD'!$B$4="Area",INDEX(MASTER_AREAS!$B:$B,G31+1),INDEX(MASTER_ZONES!$B:$B,G31+1)))
A32: =IF('WSF DASHBOARD'!$B$4="Area",IF(31<=$D$3,IF(OR('WSF DASHBOARD'!$C$4="",ISNUMBER(SEARCH('WSF DASHBOARD'!$C$4,INDEX(MASTER_AREAS!$B:$B,32)))),31,""),""),IF('WSF DASHBOARD'!$B$4="Zone",IF(31<=$D$4,IF(OR('WSF DASHBOARD'!$C$4="",ISNUMBER(SEARCH('WSF DASHBOARD'!$C$4,INDEX(MASTER_ZONES!$B:$B,32)))),31,""),""),"")) | B32: =IFERROR(SMALL($A$2:$A$1365,31),"") | C32: =IF(B32="","",IF('WSF DASHBOARD'!$B$4="Area",INDEX(MASTER_AREAS!$B:$B,B32+1),INDEX(MASTER_ZONES!$B:$B,B32+1))) | F32: =IF('TRANSPORT DASHBOARD'!$B$4="Area",IF(31<=$I$3,IF(OR('TRANSPORT DASHBOARD'!$C$4="",ISNUMBER(SEARCH('TRANSPORT DASHBOARD'!$C$4,INDEX(MASTER_AREAS!$B:$B,32)))),31,""),""),IF('TRANSPORT DASHBOARD'!$B$4="Zone",IF(31<=$I$4,IF(OR('TRANSPORT DASHBOARD'!$C$4="",ISNUMBER(SEARCH('TRANSPORT DASHBOARD'!$C$4,INDEX(MASTER_ZONES!$B:$B,32)))),31,""),""),"")) | G32: =IFERROR(SMALL($F$2:$F$1365,31),"") | H32: =IF(G32="","",IF('TRANSPORT DASHBOARD'!$B$4="Area",INDEX(MASTER_AREAS!$B:$B,G32+1),INDEX(MASTER_ZONES!$B:$B,G32+1)))
A33: =IF('WSF DASHBOARD'!$B$4="Area",IF(32<=$D$3,IF(OR('WSF DASHBOARD'!$C$4="",ISNUMBER(SEARCH('WSF DASHBOARD'!$C$4,INDEX(MASTER_AREAS!$B:$B,33)))),32,""),""),IF('WSF DASHBOARD'!$B$4="Zone",IF(32<=$D$4,IF(OR('WSF DASHBOARD'!$C$4="",ISNUMBER(SEARCH('WSF DASHBOARD'!$C$4,INDEX(MASTER_ZONES!$B:$B,33)))),32,""),""),"")) | B33: =IFERROR(SMALL($A$2:$A$1365,32),"") | C33: =IF(B33="","",IF('WSF DASHBOARD'!$B$4="Area",INDEX(MASTER_AREAS!$B:$B,B33+1),INDEX(MASTER_ZONES!$B:$B,B33+1))) | F33: =IF('TRANSPORT DASHBOARD'!$B$4="Area",IF(32<=$I$3,IF(OR('TRANSPORT DASHBOARD'!$C$4="",ISNUMBER(SEARCH('TRANSPORT DASHBOARD'!$C$4,INDEX(MASTER_AREAS!$B:$B,33)))),32,""),""),IF('TRANSPORT DASHBOARD'!$B$4="Zone",IF(32<=$I$4,IF(OR('TRANSPORT DASHBOARD'!$C$4="",ISNUMBER(SEARCH('TRANSPORT DASHBOARD'!$C$4,INDEX(MASTER_ZONES!$B:$B,33)))),32,""),""),"")) | G33: =IFERROR(SMALL($F$2:$F$1365,32),"") | H33: =IF(G33="","",IF('TRANSPORT DASHBOARD'!$B$4="Area",INDEX(MASTER_AREAS!$B:$B,G33+1),INDEX(MASTER_ZONES!$B:$B,G33+1)))
A34: =IF('WSF DASHBOARD'!$B$4="Area",IF(33<=$D$3,IF(OR('WSF DASHBOARD'!$C$4="",ISNUMBER(SEARCH('WSF DASHBOARD'!$C$4,INDEX(MASTER_AREAS!$B:$B,34)))),33,""),""),IF('WSF DASHBOARD'!$B$4="Zone",IF(33<=$D$4,IF(OR('WSF DASHBOARD'!$C$4="",ISNUMBER(SEARCH('WSF DASHBOARD'!$C$4,INDEX(MASTER_ZONES!$B:$B,34)))),33,""),""),"")) | B34: =IFERROR(SMALL($A$2:$A$1365,33),"") | C34: =IF(B34="","",IF('WSF DASHBOARD'!$B$4="Area",INDEX(MASTER_AREAS!$B:$B,B34+1),INDEX(MASTER_ZONES!$B:$B,B34+1))) | F34: =IF('TRANSPORT DASHBOARD'!$B$4="Area",IF(33<=$I$3,IF(OR('TRANSPORT DASHBOARD'!$C$4="",ISNUMBER(SEARCH('TRANSPORT DASHBOARD'!$C$4,INDEX(MASTER_AREAS!$B:$B,34)))),33,""),""),IF('TRANSPORT DASHBOARD'!$B$4="Zone",IF(33<=$I$4,IF(OR('TRANSPORT DASHBOARD'!$C$4="",ISNUMBER(SEARCH('TRANSPORT DASHBOARD'!$C$4,INDEX(MASTER_ZONES!$B:$B,34)))),33,""),""),"")) | G34: =IFERROR(SMALL($F$2:$F$1365,33),"") | H34: =IF(G34="","",IF('TRANSPORT DASHBOARD'!$B$4="Area",INDEX(MASTER_AREAS!$B:$B,G34+1),INDEX(MASTER_ZONES!$B:$B,G34+1)))
A35: =IF('WSF DASHBOARD'!$B$4="Area",IF(34<=$D$3,IF(OR('WSF DASHBOARD'!$C$4="",ISNUMBER(SEARCH('WSF DASHBOARD'!$C$4,INDEX(MASTER_AREAS!$B:$B,35)))),34,""),""),IF('WSF DASHBOARD'!$B$4="Zone",IF(34<=$D$4,IF(OR('WSF DASHBOARD'!$C$4="",ISNUMBER(SEARCH('WSF DASHBOARD'!$C$4,INDEX(MASTER_ZONES!$B:$B,35)))),34,""),""),"")) | B35: =IFERROR(SMALL($A$2:$A$1365,34),"") | C35: =IF(B35="","",IF('WSF DASHBOARD'!$B$4="Area",INDEX(MASTER_AREAS!$B:$B,B35+1),INDEX(MASTER_ZONES!$B:$B,B35+1))) | F35: =IF('TRANSPORT DASHBOARD'!$B$4="Area",IF(34<=$I$3,IF(OR('TRANSPORT DASHBOARD'!$C$4="",ISNUMBER(SEARCH('TRANSPORT DASHBOARD'!$C$4,INDEX(MASTER_AREAS!$B:$B,35)))),34,""),""),IF('TRANSPORT DASHBOARD'!$B$4="Zone",IF(34<=$I$4,IF(OR('TRANSPORT DASHBOARD'!$C$4="",ISNUMBER(SEARCH('TRANSPORT DASHBOARD'!$C$4,INDEX(MASTER_ZONES!$B:$B,35)))),34,""),""),"")) | G35: =IFERROR(SMALL($F$2:$F$1365,34),"") | H35: =IF(G35="","",IF('TRANSPORT DASHBOARD'!$B$4="Area",INDEX(MASTER_AREAS!$B:$B,G35+1),INDEX(MASTER_ZONES!$B:$B,G35+1)))
A36: =IF('WSF DASHBOARD'!$B$4="Area",IF(35<=$D$3,IF(OR('WSF DASHBOARD'!$C$4="",ISNUMBER(SEARCH('WSF DASHBOARD'!$C$4,INDEX(MASTER_AREAS!$B:$B,36)))),35,""),""),IF('WSF DASHBOARD'!$B$4="Zone",IF(35<=$D$4,IF(OR('WSF DASHBOARD'!$C$4="",ISNUMBER(SEARCH('WSF DASHBOARD'!$C$4,INDEX(MASTER_ZONES!$B:$B,36)))),35,""),""),"")) | B36: =IFERROR(SMALL($A$2:$A$1365,35),"") | C36: =IF(B36="","",IF('WSF DASHBOARD'!$B$4="Area",INDEX(MASTER_AREAS!$B:$B,B36+1),INDEX(MASTER_ZONES!$B:$B,B36+1))) | F36: =IF('TRANSPORT DASHBOARD'!$B$4="Area",IF(35<=$I$3,IF(OR('TRANSPORT DASHBOARD'!$C$4="",ISNUMBER(SEARCH('TRANSPORT DASHBOARD'!$C$4,INDEX(MASTER_AREAS!$B:$B,36)))),35,""),""),IF('TRANSPORT DASHBOARD'!$B$4="Zone",IF(35<=$I$4,IF(OR('TRANSPORT DASHBOARD'!$C$4="",ISNUMBER(SEARCH('TRANSPORT DASHBOARD'!$C$4,INDEX(MASTER_ZONES!$B:$B,36)))),35,""),""),"")) | G36: =IFERROR(SMALL($F$2:$F$1365,35),"") | H36: =IF(G36="","",IF('TRANSPORT DASHBOARD'!$B$4="Area",INDEX(MASTER_AREAS!$B:$B,G36+1),INDEX(MASTER_ZONES!$B:$B,G36+1)))
A37: =IF('WSF DASHBOARD'!$B$4="Area",IF(36<=$D$3,IF(OR('WSF DASHBOARD'!$C$4="",ISNUMBER(SEARCH('WSF DASHBOARD'!$C$4,INDEX(MASTER_AREAS!$B:$B,37)))),36,""),""),IF('WSF DASHBOARD'!$B$4="Zone",IF(36<=$D$4,IF(OR('WSF DASHBOARD'!$C$4="",ISNUMBER(SEARCH('WSF DASHBOARD'!$C$4,INDEX(MASTER_ZONES!$B:$B,37)))),36,""),""),"")) | B37: =IFERROR(SMALL($A$2:$A$1365,36),"") | C37: =IF(B37="","",IF('WSF DASHBOARD'!$B$4="Area",INDEX(MASTER_AREAS!$B:$B,B37+1),INDEX(MASTER_ZONES!$B:$B,B37+1))) | F37: =IF('TRANSPORT DASHBOARD'!$B$4="Area",IF(36<=$I$3,IF(OR('TRANSPORT DASHBOARD'!$C$4="",ISNUMBER(SEARCH('TRANSPORT DASHBOARD'!$C$4,INDEX(MASTER_AREAS!$B:$B,37)))),36,""),""),IF('TRANSPORT DASHBOARD'!$B$4="Zone",IF(36<=$I$4,IF(OR('TRANSPORT DASHBOARD'!$C$4="",ISNUMBER(SEARCH('TRANSPORT DASHBOARD'!$C$4,INDEX(MASTER_ZONES!$B:$B,37)))),36,""),""),"")) | G37: =IFERROR(SMALL($F$2:$F$1365,36),"") | H37: =IF(G37="","",IF('TRANSPORT DASHBOARD'!$B$4="Area",INDEX(MASTER_AREAS!$B:$B,G37+1),INDEX(MASTER_ZONES!$B:$B,G37+1)))
A38: =IF('WSF DASHBOARD'!$B$4="Area",IF(37<=$D$3,IF(OR('WSF DASHBOARD'!$C$4="",ISNUMBER(SEARCH('WSF DASHBOARD'!$C$4,INDEX(MASTER_AREAS!$B:$B,38)))),37,""),""),IF('WSF DASHBOARD'!$B$4="Zone",IF(37<=$D$4,IF(OR('WSF DASHBOARD'!$C$4="",ISNUMBER(SEARCH('WSF DASHBOARD'!$C$4,INDEX(MASTER_ZONES!$B:$B,38)))),37,""),""),"")) | B38: =IFERROR(SMALL($A$2:$A$1365,37),"") | C38: =IF(B38="","",IF('WSF DASHBOARD'!$B$4="Area",INDEX(MASTER_AREAS!$B:$B,B38+1),INDEX(MASTER_ZONES!$B:$B,B38+1))) | F38: =IF('TRANSPORT DASHBOARD'!$B$4="Area",IF(37<=$I$3,IF(OR('TRANSPORT DASHBOARD'!$C$4="",ISNUMBER(SEARCH('TRANSPORT DASHBOARD'!$C$4,INDEX(MASTER_AREAS!$B:$B,38)))),37,""),""),IF('TRANSPORT DASHBOARD'!$B$4="Zone",IF(37<=$I$4,IF(OR('TRANSPORT DASHBOARD'!$C$4="",ISNUMBER(SEARCH('TRANSPORT DASHBOARD'!$C$4,INDEX(MASTER_ZONES!$B:$B,38)))),37,""),""),"")) | G38: =IFERROR(SMALL($F$2:$F$1365,37),"") | H38: =IF(G38="","",IF('TRANSPORT DASHBOARD'!$B$4="Area",INDEX(MASTER_AREAS!$B:$B,G38+1),INDEX(MASTER_ZONES!$B:$B,G38+1)))
A39: =IF('WSF DASHBOARD'!$B$4="Area",IF(38<=$D$3,IF(OR('WSF DASHBOARD'!$C$4="",ISNUMBER(SEARCH('WSF DASHBOARD'!$C$4,INDEX(MASTER_AREAS!$B:$B,39)))),38,""),""),IF('WSF DASHBOARD'!$B$4="Zone",IF(38<=$D$4,IF(OR('WSF DASHBOARD'!$C$4="",ISNUMBER(SEARCH('WSF DASHBOARD'!$C$4,INDEX(MASTER_ZONES!$B:$B,39)))),38,""),""),"")) | B39: =IFERROR(SMALL($A$2:$A$1365,38),"") | C39: =IF(B39="","",IF('WSF DASHBOARD'!$B$4="Area",INDEX(MASTER_AREAS!$B:$B,B39+1),INDEX(MASTER_ZONES!$B:$B,B39+1))) | F39: =IF('TRANSPORT DASHBOARD'!$B$4="Area",IF(38<=$I$3,IF(OR('TRANSPORT DASHBOARD'!$C$4="",ISNUMBER(SEARCH('TRANSPORT DASHBOARD'!$C$4,INDEX(MASTER_AREAS!$B:$B,39)))),38,""),""),IF('TRANSPORT DASHBOARD'!$B$4="Zone",IF(38<=$I$4,IF(OR('TRANSPORT DASHBOARD'!$C$4="",ISNUMBER(SEARCH('TRANSPORT DASHBOARD'!$C$4,INDEX(MASTER_ZONES!$B:$B,39)))),38,""),""),"")) | G39: =IFERROR(SMALL($F$2:$F$1365,38),"") | H39: =IF(G39="","",IF('TRANSPORT DASHBOARD'!$B$4="Area",INDEX(MASTER_AREAS!$B:$B,G39+1),INDEX(MASTER_ZONES!$B:$B,G39+1)))
A40: =IF('WSF DASHBOARD'!$B$4="Area",IF(39<=$D$3,IF(OR('WSF DASHBOARD'!$C$4="",ISNUMBER(SEARCH('WSF DASHBOARD'!$C$4,INDEX(MASTER_AREAS!$B:$B,40)))),39,""),""),IF('WSF DASHBOARD'!$B$4="Zone",IF(39<=$D$4,IF(OR('WSF DASHBOARD'!$C$4="",ISNUMBER(SEARCH('WSF DASHBOARD'!$C$4,INDEX(MASTER_ZONES!$B:$B,40)))),39,""),""),"")) | B40: =IFERROR(SMALL($A$2:$A$1365,39),"") | C40: =IF(B40="","",IF('WSF DASHBOARD'!$B$4="Area",INDEX(MASTER_AREAS!$B:$B,B40+1),INDEX(MASTER_ZONES!$B:$B,B40+1))) | F40: =IF('TRANSPORT DASHBOARD'!$B$4="Area",IF(39<=$I$3,IF(OR('TRANSPORT DASHBOARD'!$C$4="",ISNUMBER(SEARCH('TRANSPORT DASHBOARD'!$C$4,INDEX(MASTER_AREAS!$B:$B,40)))),39,""),""),IF('TRANSPORT DASHBOARD'!$B$4="Zone",IF(39<=$I$4,IF(OR('TRANSPORT DASHBOARD'!$C$4="",ISNUMBER(SEARCH('TRANSPORT DASHBOARD'!$C$4,INDEX(MASTER_ZONES!$B:$B,40)))),39,""),""),"")) | G40: =IFERROR(SMALL($F$2:$F$1365,39),"") | H40: =IF(G40="","",IF('TRANSPORT DASHBOARD'!$B$4="Area",INDEX(MASTER_AREAS!$B:$B,G40+1),INDEX(MASTER_ZONES!$B:$B,G40+1)))
A41: =IF('WSF DASHBOARD'!$B$4="Area",IF(40<=$D$3,IF(OR('WSF DASHBOARD'!$C$4="",ISNUMBER(SEARCH('WSF DASHBOARD'!$C$4,INDEX(MASTER_AREAS!$B:$B,41)))),40,""),""),IF('WSF DASHBOARD'!$B$4="Zone",IF(40<=$D$4,IF(OR('WSF DASHBOARD'!$C$4="",ISNUMBER(SEARCH('WSF DASHBOARD'!$C$4,INDEX(MASTER_ZONES!$B:$B,41)))),40,""),""),"")) | B41: =IFERROR(SMALL($A$2:$A$1365,40),"") | C41: =IF(B41="","",IF('WSF DASHBOARD'!$B$4="Area",INDEX(MASTER_AREAS!$B:$B,B41+1),INDEX(MASTER_ZONES!$B:$B,B41+1))) | F41: =IF('TRANSPORT DASHBOARD'!$B$4="Area",IF(40<=$I$3,IF(OR('TRANSPORT DASHBOARD'!$C$4="",ISNUMBER(SEARCH('TRANSPORT DASHBOARD'!$C$4,INDEX(MASTER_AREAS!$B:$B,41)))),40,""),""),IF('TRANSPORT DASHBOARD'!$B$4="Zone",IF(40<=$I$4,IF(OR('TRANSPORT DASHBOARD'!$C$4="",ISNUMBER(SEARCH('TRANSPORT DASHBOARD'!$C$4,INDEX(MASTER_ZONES!$B:$B,41)))),40,""),""),"")) | G41: =IFERROR(SMALL($F$2:$F$1365,40),"") | H41: =IF(G41="","",IF('TRANSPORT DASHBOARD'!$B$4="Area",INDEX(MASTER_AREAS!$B:$B,G41+1),INDEX(MASTER_ZONES!$B:$B,G41+1)))
A42: =IF('WSF DASHBOARD'!$B$4="Area",IF(41<=$D$3,IF(OR('WSF DASHBOARD'!$C$4="",ISNUMBER(SEARCH('WSF DASHBOARD'!$C$4,INDEX(MASTER_AREAS!$B:$B,42)))),41,""),""),IF('WSF DASHBOARD'!$B$4="Zone",IF(41<=$D$4,IF(OR('WSF DASHBOARD'!$C$4="",ISNUMBER(SEARCH('WSF DASHBOARD'!$C$4,INDEX(MASTER_ZONES!$B:$B,42)))),41,""),""),"")) | B42: =IFERROR(SMALL($A$2:$A$1365,41),"") | C42: =IF(B42="","",IF('WSF DASHBOARD'!$B$4="Area",INDEX(MASTER_AREAS!$B:$B,B42+1),INDEX(MASTER_ZONES!$B:$B,B42+1))) | F42: =IF('TRANSPORT DASHBOARD'!$B$4="Area",IF(41<=$I$3,IF(OR('TRANSPORT DASHBOARD'!$C$4="",ISNUMBER(SEARCH('TRANSPORT DASHBOARD'!$C$4,INDEX(MASTER_AREAS!$B:$B,42)))),41,""),""),IF('TRANSPORT DASHBOARD'!$B$4="Zone",IF(41<=$I$4,IF(OR('TRANSPORT DASHBOARD'!$C$4="",ISNUMBER(SEARCH('TRANSPORT DASHBOARD'!$C$4,INDEX(MASTER_ZONES!$B:$B,42)))),41,""),""),"")) | G42: =IFERROR(SMALL($F$2:$F$1365,41),"") | H42: =IF(G42="","",IF('TRANSPORT DASHBOARD'!$B$4="Area",INDEX(MASTER_AREAS!$B:$B,G42+1),INDEX(MASTER_ZONES!$B:$B,G42+1)))
A43: =IF('WSF DASHBOARD'!$B$4="Area",IF(42<=$D$3,IF(OR('WSF DASHBOARD'!$C$4="",ISNUMBER(SEARCH('WSF DASHBOARD'!$C$4,INDEX(MASTER_AREAS!$B:$B,43)))),42,""),""),IF('WSF DASHBOARD'!$B$4="Zone",IF(42<=$D$4,IF(OR('WSF DASHBOARD'!$C$4="",ISNUMBER(SEARCH('WSF DASHBOARD'!$C$4,INDEX(MASTER_ZONES!$B:$B,43)))),42,""),""),"")) | B43: =IFERROR(SMALL($A$2:$A$1365,42),"") | C43: =IF(B43="","",IF('WSF DASHBOARD'!$B$4="Area",INDEX(MASTER_AREAS!$B:$B,B43+1),INDEX(MASTER_ZONES!$B:$B,B43+1))) | F43: =IF('TRANSPORT DASHBOARD'!$B$4="Area",IF(42<=$I$3,IF(OR('TRANSPORT DASHBOARD'!$C$4="",ISNUMBER(SEARCH('TRANSPORT DASHBOARD'!$C$4,INDEX(MASTER_AREAS!$B:$B,43)))),42,""),""),IF('TRANSPORT DASHBOARD'!$B$4="Zone",IF(42<=$I$4,IF(OR('TRANSPORT DASHBOARD'!$C$4="",ISNUMBER(SEARCH('TRANSPORT DASHBOARD'!$C$4,INDEX(MASTER_ZONES!$B:$B,43)))),42,""),""),"")) | G43: =IFERROR(SMALL($F$2:$F$1365,42),"") | H43: =IF(G43="","",IF('TRANSPORT DASHBOARD'!$B$4="Area",INDEX(MASTER_AREAS!$B:$B,G43+1),INDEX(MASTER_ZONES!$B:$B,G43+1)))
A44: =IF('WSF DASHBOARD'!$B$4="Area",IF(43<=$D$3,IF(OR('WSF DASHBOARD'!$C$4="",ISNUMBER(SEARCH('WSF DASHBOARD'!$C$4,INDEX(MASTER_AREAS!$B:$B,44)))),43,""),""),IF('WSF DASHBOARD'!$B$4="Zone",IF(43<=$D$4,IF(OR('WSF DASHBOARD'!$C$4="",ISNUMBER(SEARCH('WSF DASHBOARD'!$C$4,INDEX(MASTER_ZONES!$B:$B,44)))),43,""),""),"")) | B44: =IFERROR(SMALL($A$2:$A$1365,43),"") | C44: =IF(B44="","",IF('WSF DASHBOARD'!$B$4="Area",INDEX(MASTER_AREAS!$B:$B,B44+1),INDEX(MASTER_ZONES!$B:$B,B44+1))) | F44: =IF('TRANSPORT DASHBOARD'!$B$4="Area",IF(43<=$I$3,IF(OR('TRANSPORT DASHBOARD'!$C$4="",ISNUMBER(SEARCH('TRANSPORT DASHBOARD'!$C$4,INDEX(MASTER_AREAS!$B:$B,44)))),43,""),""),IF('TRANSPORT DASHBOARD'!$B$4="Zone",IF(43<=$I$4,IF(OR('TRANSPORT DASHBOARD'!$C$4="",ISNUMBER(SEARCH('TRANSPORT DASHBOARD'!$C$4,INDEX(MASTER_ZONES!$B:$B,44)))),43,""),""),"")) | G44: =IFERROR(SMALL($F$2:$F$1365,43),"") | H44: =IF(G44="","",IF('TRANSPORT DASHBOARD'!$B$4="Area",INDEX(MASTER_AREAS!$B:$B,G44+1),INDEX(MASTER_ZONES!$B:$B,G44+1)))
A45: =IF('WSF DASHBOARD'!$B$4="Area",IF(44<=$D$3,IF(OR('WSF DASHBOARD'!$C$4="",ISNUMBER(SEARCH('WSF DASHBOARD'!$C$4,INDEX(MASTER_AREAS!$B:$B,45)))),44,""),""),IF('WSF DASHBOARD'!$B$4="Zone",IF(44<=$D$4,IF(OR('WSF DASHBOARD'!$C$4="",ISNUMBER(SEARCH('WSF DASHBOARD'!$C$4,INDEX(MASTER_ZONES!$B:$B,45)))),44,""),""),"")) | B45: =IFERROR(SMALL($A$2:$A$1365,44),"") | C45: =IF(B45="","",IF('WSF DASHBOARD'!$B$4="Area",INDEX(MASTER_AREAS!$B:$B,B45+1),INDEX(MASTER_ZONES!$B:$B,B45+1))) | F45: =IF('TRANSPORT DASHBOARD'!$B$4="Area",IF(44<=$I$3,IF(OR('TRANSPORT DASHBOARD'!$C$4="",ISNUMBER(SEARCH('TRANSPORT DASHBOARD'!$C$4,INDEX(MASTER_AREAS!$B:$B,45)))),44,""),""),IF('TRANSPORT DASHBOARD'!$B$4="Zone",IF(44<=$I$4,IF(OR('TRANSPORT DASHBOARD'!$C$4="",ISNUMBER(SEARCH('TRANSPORT DASHBOARD'!$C$4,INDEX(MASTER_ZONES!$B:$B,45)))),44,""),""),"")) | G45: =IFERROR(SMALL($F$2:$F$1365,44),"") | H45: =IF(G45="","",IF('TRANSPORT DASHBOARD'!$B$4="Area",INDEX(MASTER_AREAS!$B:$B,G45+1),INDEX(MASTER_ZONES!$B:$B,G45+1)))
A46: =IF('WSF DASHBOARD'!$B$4="Area",IF(45<=$D$3,IF(OR('WSF DASHBOARD'!$C$4="",ISNUMBER(SEARCH('WSF DASHBOARD'!$C$4,INDEX(MASTER_AREAS!$B:$B,46)))),45,""),""),IF('WSF DASHBOARD'!$B$4="Zone",IF(45<=$D$4,IF(OR('WSF DASHBOARD'!$C$4="",ISNUMBER(SEARCH('WSF DASHBOARD'!$C$4,INDEX(MASTER_ZONES!$B:$B,46)))),45,""),""),"")) | B46: =IFERROR(SMALL($A$2:$A$1365,45),"") | C46: =IF(B46="","",IF('WSF DASHBOARD'!$B$4="Area",INDEX(MASTER_AREAS!$B:$B,B46+1),INDEX(MASTER_ZONES!$B:$B,B46+1))) | F46: =IF('TRANSPORT DASHBOARD'!$B$4="Area",IF(45<=$I$3,IF(OR('TRANSPORT DASHBOARD'!$C$4="",ISNUMBER(SEARCH('TRANSPORT DASHBOARD'!$C$4,INDEX(MASTER_AREAS!$B:$B,46)))),45,""),""),IF('TRANSPORT DASHBOARD'!$B$4="Zone",IF(45<=$I$4,IF(OR('TRANSPORT DASHBOARD'!$C$4="",ISNUMBER(SEARCH('TRANSPORT DASHBOARD'!$C$4,INDEX(MASTER_ZONES!$B:$B,46)))),45,""),""),"")) | G46: =IFERROR(SMALL($F$2:$F$1365,45),"") | H46: =IF(G46="","",IF('TRANSPORT DASHBOARD'!$B$4="Area",INDEX(MASTER_AREAS!$B:$B,G46+1),INDEX(MASTER_ZONES!$B:$B,G46+1)))
A47: =IF('WSF DASHBOARD'!$B$4="Area",IF(46<=$D$3,IF(OR('WSF DASHBOARD'!$C$4="",ISNUMBER(SEARCH('WSF DASHBOARD'!$C$4,INDEX(MASTER_AREAS!$B:$B,47)))),46,""),""),IF('WSF DASHBOARD'!$B$4="Zone",IF(46<=$D$4,IF(OR('WSF DASHBOARD'!$C$4="",ISNUMBER(SEARCH('WSF DASHBOARD'!$C$4,INDEX(MASTER_ZONES!$B:$B,47)))),46,""),""),"")) | B47: =IFERROR(SMALL($A$2:$A$1365,46),"") | C47: =IF(B47="","",IF('WSF DASHBOARD'!$B$4="Area",INDEX(MASTER_AREAS!$B:$B,B47+1),INDEX(MASTER_ZONES!$B:$B,B47+1))) | F47: =IF('TRANSPORT DASHBOARD'!$B$4="Area",IF(46<=$I$3,IF(OR('TRANSPORT DASHBOARD'!$C$4="",ISNUMBER(SEARCH('TRANSPORT DASHBOARD'!$C$4,INDEX(MASTER_AREAS!$B:$B,47)))),46,""),""),IF('TRANSPORT DASHBOARD'!$B$4="Zone",IF(46<=$I$4,IF(OR('TRANSPORT DASHBOARD'!$C$4="",ISNUMBER(SEARCH('TRANSPORT DASHBOARD'!$C$4,INDEX(MASTER_ZONES!$B:$B,47)))),46,""),""),"")) | G47: =IFERROR(SMALL($F$2:$F$1365,46),"") | H47: =IF(G47="","",IF('TRANSPORT DASHBOARD'!$B$4="Area",INDEX(MASTER_AREAS!$B:$B,G47+1),INDEX(MASTER_ZONES!$B:$B,G47+1)))
A48: =IF('WSF DASHBOARD'!$B$4="Area",IF(47<=$D$3,IF(OR('WSF DASHBOARD'!$C$4="",ISNUMBER(SEARCH('WSF DASHBOARD'!$C$4,INDEX(MASTER_AREAS!$B:$B,48)))),47,""),""),IF('WSF DASHBOARD'!$B$4="Zone",IF(47<=$D$4,IF(OR('WSF DASHBOARD'!$C$4="",ISNUMBER(SEARCH('WSF DASHBOARD'!$C$4,INDEX(MASTER_ZONES!$B:$B,48)))),47,""),""),"")) | B48: =IFERROR(SMALL($A$2:$A$1365,47),"") | C48: =IF(B48="","",IF('WSF DASHBOARD'!$B$4="Area",INDEX(MASTER_AREAS!$B:$B,B48+1),INDEX(MASTER_ZONES!$B:$B,B48+1))) | F48: =IF('TRANSPORT DASHBOARD'!$B$4="Area",IF(47<=$I$3,IF(OR('TRANSPORT DASHBOARD'!$C$4="",ISNUMBER(SEARCH('TRANSPORT DASHBOARD'!$C$4,INDEX(MASTER_AREAS!$B:$B,48)))),47,""),""),IF('TRANSPORT DASHBOARD'!$B$4="Zone",IF(47<=$I$4,IF(OR('TRANSPORT DASHBOARD'!$C$4="",ISNUMBER(SEARCH('TRANSPORT DASHBOARD'!$C$4,INDEX(MASTER_ZONES!$B:$B,48)))),47,""),""),"")) | G48: =IFERROR(SMALL($F$2:$F$1365,47),"") | H48: =IF(G48="","",IF('TRANSPORT DASHBOARD'!$B$4="Area",INDEX(MASTER_AREAS!$B:$B,G48+1),INDEX(MASTER_ZONES!$B:$B,G48+1)))
A49: =IF('WSF DASHBOARD'!$B$4="Area",IF(48<=$D$3,IF(OR('WSF DASHBOARD'!$C$4="",ISNUMBER(SEARCH('WSF DASHBOARD'!$C$4,INDEX(MASTER_AREAS!$B:$B,49)))),48,""),""),IF('WSF DASHBOARD'!$B$4="Zone",IF(48<=$D$4,IF(OR('WSF DASHBOARD'!$C$4="",ISNUMBER(SEARCH('WSF DASHBOARD'!$C$4,INDEX(MASTER_ZONES!$B:$B,49)))),48,""),""),"")) | B49: =IFERROR(SMALL($A$2:$A$1365,48),"") | C49: =IF(B49="","",IF('WSF DASHBOARD'!$B$4="Area",INDEX(MASTER_AREAS!$B:$B,B49+1),INDEX(MASTER_ZONES!$B:$B,B49+1))) | F49: =IF('TRANSPORT DASHBOARD'!$B$4="Area",IF(48<=$I$3,IF(OR('TRANSPORT DASHBOARD'!$C$4="",ISNUMBER(SEARCH('TRANSPORT DASHBOARD'!$C$4,INDEX(MASTER_AREAS!$B:$B,49)))),48,""),""),IF('TRANSPORT DASHBOARD'!$B$4="Zone",IF(48<=$I$4,IF(OR('TRANSPORT DASHBOARD'!$C$4="",ISNUMBER(SEARCH('TRANSPORT DASHBOARD'!$C$4,INDEX(MASTER_ZONES!$B:$B,49)))),48,""),""),"")) | G49: =IFERROR(SMALL($F$2:$F$1365,48),"") | H49: =IF(G49="","",IF('TRANSPORT DASHBOARD'!$B$4="Area",INDEX(MASTER_AREAS!$B:$B,G49+1),INDEX(MASTER_ZONES!$B:$B,G49+1)))
A50: =IF('WSF DASHBOARD'!$B$4="Area",IF(49<=$D$3,IF(OR('WSF DASHBOARD'!$C$4="",ISNUMBER(SEARCH('WSF DASHBOARD'!$C$4,INDEX(MASTER_AREAS!$B:$B,50)))),49,""),""),IF('WSF DASHBOARD'!$B$4="Zone",IF(49<=$D$4,IF(OR('WSF DASHBOARD'!$C$4="",ISNUMBER(SEARCH('WSF DASHBOARD'!$C$4,INDEX(MASTER_ZONES!$B:$B,50)))),49,""),""),"")) | B50: =IFERROR(SMALL($A$2:$A$1365,49),"") | C50: =IF(B50="","",IF('WSF DASHBOARD'!$B$4="Area",INDEX(MASTER_AREAS!$B:$B,B50+1),INDEX(MASTER_ZONES!$B:$B,B50+1))) | F50: =IF('TRANSPORT DASHBOARD'!$B$4="Area",IF(49<=$I$3,IF(OR('TRANSPORT DASHBOARD'!$C$4="",ISNUMBER(SEARCH('TRANSPORT DASHBOARD'!$C$4,INDEX(MASTER_AREAS!$B:$B,50)))),49,""),""),IF('TRANSPORT DASHBOARD'!$B$4="Zone",IF(49<=$I$4,IF(OR('TRANSPORT DASHBOARD'!$C$4="",ISNUMBER(SEARCH('TRANSPORT DASHBOARD'!$C$4,INDEX(MASTER_ZONES!$B:$B,50)))),49,""),""),"")) | G50: =IFERROR(SMALL($F$2:$F$1365,49),"") | H50: =IF(G50="","",IF('TRANSPORT DASHBOARD'!$B$4="Area",INDEX(MASTER_AREAS!$B:$B,G50+1),INDEX(MASTER_ZONES!$B:$B,G50+1)))
A51: =IF('WSF DASHBOARD'!$B$4="Area",IF(50<=$D$3,IF(OR('WSF DASHBOARD'!$C$4="",ISNUMBER(SEARCH('WSF DASHBOARD'!$C$4,INDEX(MASTER_AREAS!$B:$B,51)))),50,""),""),IF('WSF DASHBOARD'!$B$4="Zone",IF(50<=$D$4,IF(OR('WSF DASHBOARD'!$C$4="",ISNUMBER(SEARCH('WSF DASHBOARD'!$C$4,INDEX(MASTER_ZONES!$B:$B,51)))),50,""),""),"")) | B51: =IFERROR(SMALL($A$2:$A$1365,50),"") | C51: =IF(B51="","",IF('WSF DASHBOARD'!$B$4="Area",INDEX(MASTER_AREAS!$B:$B,B51+1),INDEX(MASTER_ZONES!$B:$B,B51+1))) | F51: =IF('TRANSPORT DASHBOARD'!$B$4="Area",IF(50<=$I$3,IF(OR('TRANSPORT DASHBOARD'!$C$4="",ISNUMBER(SEARCH('TRANSPORT DASHBOARD'!$C$4,INDEX(MASTER_AREAS!$B:$B,51)))),50,""),""),IF('TRANSPORT DASHBOARD'!$B$4="Zone",IF(50<=$I$4,IF(OR('TRANSPORT DASHBOARD'!$C$4="",ISNUMBER(SEARCH('TRANSPORT DASHBOARD'!$C$4,INDEX(MASTER_ZONES!$B:$B,51)))),50,""),""),"")) | G51: =IFERROR(SMALL($F$2:$F$1365,50),"") | H51: =IF(G51="","",IF('TRANSPORT DASHBOARD'!$B$4="Area",INDEX(MASTER_AREAS!$B:$B,G51+1),INDEX(MASTER_ZONES!$B:$B,G51+1)))
A52: =IF('WSF DASHBOARD'!$B$4="Area",IF(51<=$D$3,IF(OR('WSF DASHBOARD'!$C$4="",ISNUMBER(SEARCH('WSF DASHBOARD'!$C$4,INDEX(MASTER_AREAS!$B:$B,52)))),51,""),""),IF('WSF DASHBOARD'!$B$4="Zone",IF(51<=$D$4,IF(OR('WSF DASHBOARD'!$C$4="",ISNUMBER(SEARCH('WSF DASHBOARD'!$C$4,INDEX(MASTER_ZONES!$B:$B,52)))),51,""),""),"")) | B52: =IFERROR(SMALL($A$2:$A$1365,51),"") | C52: =IF(B52="","",IF('WSF DASHBOARD'!$B$4="Area",INDEX(MASTER_AREAS!$B:$B,B52+1),INDEX(MASTER_ZONES!$B:$B,B52+1))) | F52: =IF('TRANSPORT DASHBOARD'!$B$4="Area",IF(51<=$I$3,IF(OR('TRANSPORT DASHBOARD'!$C$4="",ISNUMBER(SEARCH('TRANSPORT DASHBOARD'!$C$4,INDEX(MASTER_AREAS!$B:$B,52)))),51,""),""),IF('TRANSPORT DASHBOARD'!$B$4="Zone",IF(51<=$I$4,IF(OR('TRANSPORT DASHBOARD'!$C$4="",ISNUMBER(SEARCH('TRANSPORT DASHBOARD'!$C$4,INDEX(MASTER_ZONES!$B:$B,52)))),51,""),""),"")) | G52: =IFERROR(SMALL($F$2:$F$1365,51),"") | H52: =IF(G52="","",IF('TRANSPORT DASHBOARD'!$B$4="Area",INDEX(MASTER_AREAS!$B:$B,G52+1),INDEX(MASTER_ZONES!$B:$B,G52+1)))
A53: =IF('WSF DASHBOARD'!$B$4="Area",IF(52<=$D$3,IF(OR('WSF DASHBOARD'!$C$4="",ISNUMBER(SEARCH('WSF DASHBOARD'!$C$4,INDEX(MASTER_AREAS!$B:$B,53)))),52,""),""),IF('WSF DASHBOARD'!$B$4="Zone",IF(52<=$D$4,IF(OR('WSF DASHBOARD'!$C$4="",ISNUMBER(SEARCH('WSF DASHBOARD'!$C$4,INDEX(MASTER_ZONES!$B:$B,53)))),52,""),""),"")) | B53: =IFERROR(SMALL($A$2:$A$1365,52),"") | C53: =IF(B53="","",IF('WSF DASHBOARD'!$B$4="Area",INDEX(MASTER_AREAS!$B:$B,B53+1),INDEX(MASTER_ZONES!$B:$B,B53+1))) | F53: =IF('TRANSPORT DASHBOARD'!$B$4="Area",IF(52<=$I$3,IF(OR('TRANSPORT DASHBOARD'!$C$4="",ISNUMBER(SEARCH('TRANSPORT DASHBOARD'!$C$4,INDEX(MASTER_AREAS!$B:$B,53)))),52,""),""),IF('TRANSPORT DASHBOARD'!$B$4="Zone",IF(52<=$I$4,IF(OR('TRANSPORT DASHBOARD'!$C$4="",ISNUMBER(SEARCH('TRANSPORT DASHBOARD'!$C$4,INDEX(MASTER_ZONES!$B:$B,53)))),52,""),""),"")) | G53: =IFERROR(SMALL($F$2:$F$1365,52),"") | H53: =IF(G53="","",IF('TRANSPORT DASHBOARD'!$B$4="Area",INDEX(MASTER_AREAS!$B:$B,G53+1),INDEX(MASTER_ZONES!$B:$B,G53+1)))
A54: =IF('WSF DASHBOARD'!$B$4="Area",IF(53<=$D$3,IF(OR('WSF DASHBOARD'!$C$4="",ISNUMBER(SEARCH('WSF DASHBOARD'!$C$4,INDEX(MASTER_AREAS!$B:$B,54)))),53,""),""),IF('WSF DASHBOARD'!$B$4="Zone",IF(53<=$D$4,IF(OR('WSF DASHBOARD'!$C$4="",ISNUMBER(SEARCH('WSF DASHBOARD'!$C$4,INDEX(MASTER_ZONES!$B:$B,54)))),53,""),""),"")) | B54: =IFERROR(SMALL($A$2:$A$1365,53),"") | C54: =IF(B54="","",IF('WSF DASHBOARD'!$B$4="Area",INDEX(MASTER_AREAS!$B:$B,B54+1),INDEX(MASTER_ZONES!$B:$B,B54+1))) | F54: =IF('TRANSPORT DASHBOARD'!$B$4="Area",IF(53<=$I$3,IF(OR('TRANSPORT DASHBOARD'!$C$4="",ISNUMBER(SEARCH('TRANSPORT DASHBOARD'!$C$4,INDEX(MASTER_AREAS!$B:$B,54)))),53,""),""),IF('TRANSPORT DASHBOARD'!$B$4="Zone",IF(53<=$I$4,IF(OR('TRANSPORT DASHBOARD'!$C$4="",ISNUMBER(SEARCH('TRANSPORT DASHBOARD'!$C$4,INDEX(MASTER_ZONES!$B:$B,54)))),53,""),""),"")) | G54: =IFERROR(SMALL($F$2:$F$1365,53),"") | H54: =IF(G54="","",IF('TRANSPORT DASHBOARD'!$B$4="Area",INDEX(MASTER_AREAS!$B:$B,G54+1),INDEX(MASTER_ZONES!$B:$B,G54+1)))
A55: =IF('WSF DASHBOARD'!$B$4="Area",IF(54<=$D$3,IF(OR('WSF DASHBOARD'!$C$4="",ISNUMBER(SEARCH('WSF DASHBOARD'!$C$4,INDEX(MASTER_AREAS!$B:$B,55)))),54,""),""),IF('WSF DASHBOARD'!$B$4="Zone",IF(54<=$D$4,IF(OR('WSF DASHBOARD'!$C$4="",ISNUMBER(SEARCH('WSF DASHBOARD'!$C$4,INDEX(MASTER_ZONES!$B:$B,55)))),54,""),""),"")) | B55: =IFERROR(SMALL($A$2:$A$1365,54),"") | C55: =IF(B55="","",IF('WSF DASHBOARD'!$B$4="Area",INDEX(MASTER_AREAS!$B:$B,B55+1),INDEX(MASTER_ZONES!$B:$B,B55+1))) | F55: =IF('TRANSPORT DASHBOARD'!$B$4="Area",IF(54<=$I$3,IF(OR('TRANSPORT DASHBOARD'!$C$4="",ISNUMBER(SEARCH('TRANSPORT DASHBOARD'!$C$4,INDEX(MASTER_AREAS!$B:$B,55)))),54,""),""),IF('TRANSPORT DASHBOARD'!$B$4="Zone",IF(54<=$I$4,IF(OR('TRANSPORT DASHBOARD'!$C$4="",ISNUMBER(SEARCH('TRANSPORT DASHBOARD'!$C$4,INDEX(MASTER_ZONES!$B:$B,55)))),54,""),""),"")) | G55: =IFERROR(SMALL($F$2:$F$1365,54),"") | H55: =IF(G55="","",IF('TRANSPORT DASHBOARD'!$B$4="Area",INDEX(MASTER_AREAS!$B:$B,G55+1),INDEX(MASTER_ZONES!$B:$B,G55+1)))
A56: =IF('WSF DASHBOARD'!$B$4="Area",IF(55<=$D$3,IF(OR('WSF DASHBOARD'!$C$4="",ISNUMBER(SEARCH('WSF DASHBOARD'!$C$4,INDEX(MASTER_AREAS!$B:$B,56)))),55,""),""),IF('WSF DASHBOARD'!$B$4="Zone",IF(55<=$D$4,IF(OR('WSF DASHBOARD'!$C$4="",ISNUMBER(SEARCH('WSF DASHBOARD'!$C$4,INDEX(MASTER_ZONES!$B:$B,56)))),55,""),""),"")) | B56: =IFERROR(SMALL($A$2:$A$1365,55),"") | C56: =IF(B56="","",IF('WSF DASHBOARD'!$B$4="Area",INDEX(MASTER_AREAS!$B:$B,B56+1),INDEX(MASTER_ZONES!$B:$B,B56+1))) | F56: =IF('TRANSPORT DASHBOARD'!$B$4="Area",IF(55<=$I$3,IF(OR('TRANSPORT DASHBOARD'!$C$4="",ISNUMBER(SEARCH('TRANSPORT DASHBOARD'!$C$4,INDEX(MASTER_AREAS!$B:$B,56)))),55,""),""),IF('TRANSPORT DASHBOARD'!$B$4="Zone",IF(55<=$I$4,IF(OR('TRANSPORT DASHBOARD'!$C$4="",ISNUMBER(SEARCH('TRANSPORT DASHBOARD'!$C$4,INDEX(MASTER_ZONES!$B:$B,56)))),55,""),""),"")) | G56: =IFERROR(SMALL($F$2:$F$1365,55),"") | H56: =IF(G56="","",IF('TRANSPORT DASHBOARD'!$B$4="Area",INDEX(MASTER_AREAS!$B:$B,G56+1),INDEX(MASTER_ZONES!$B:$B,G56+1)))
A57: =IF('WSF DASHBOARD'!$B$4="Area",IF(56<=$D$3,IF(OR('WSF DASHBOARD'!$C$4="",ISNUMBER(SEARCH('WSF DASHBOARD'!$C$4,INDEX(MASTER_AREAS!$B:$B,57)))),56,""),""),IF('WSF DASHBOARD'!$B$4="Zone",IF(56<=$D$4,IF(OR('WSF DASHBOARD'!$C$4="",ISNUMBER(SEARCH('WSF DASHBOARD'!$C$4,INDEX(MASTER_ZONES!$B:$B,57)))),56,""),""),"")) | B57: =IFERROR(SMALL($A$2:$A$1365,56),"") | C57: =IF(B57="","",IF('WSF DASHBOARD'!$B$4="Area",INDEX(MASTER_AREAS!$B:$B,B57+1),INDEX(MASTER_ZONES!$B:$B,B57+1))) | F57: =IF('TRANSPORT DASHBOARD'!$B$4="Area",IF(56<=$I$3,IF(OR('TRANSPORT DASHBOARD'!$C$4="",ISNUMBER(SEARCH('TRANSPORT DASHBOARD'!$C$4,INDEX(MASTER_AREAS!$B:$B,57)))),56,""),""),IF('TRANSPORT DASHBOARD'!$B$4="Zone",IF(56<=$I$4,IF(OR('TRANSPORT DASHBOARD'!$C$4="",ISNUMBER(SEARCH('TRANSPORT DASHBOARD'!$C$4,INDEX(MASTER_ZONES!$B:$B,57)))),56,""),""),"")) | G57: =IFERROR(SMALL($F$2:$F$1365,56),"") | H57: =IF(G57="","",IF('TRANSPORT DASHBOARD'!$B$4="Area",INDEX(MASTER_AREAS!$B:$B,G57+1),INDEX(MASTER_ZONES!$B:$B,G57+1)))
A58: =IF('WSF DASHBOARD'!$B$4="Area",IF(57<=$D$3,IF(OR('WSF DASHBOARD'!$C$4="",ISNUMBER(SEARCH('WSF DASHBOARD'!$C$4,INDEX(MASTER_AREAS!$B:$B,58)))),57,""),""),IF('WSF DASHBOARD'!$B$4="Zone",IF(57<=$D$4,IF(OR('WSF DASHBOARD'!$C$4="",ISNUMBER(SEARCH('WSF DASHBOARD'!$C$4,INDEX(MASTER_ZONES!$B:$B,58)))),57,""),""),"")) | B58: =IFERROR(SMALL($A$2:$A$1365,57),"") | C58: =IF(B58="","",IF('WSF DASHBOARD'!$B$4="Area",INDEX(MASTER_AREAS!$B:$B,B58+1),INDEX(MASTER_ZONES!$B:$B,B58+1))) | F58: =IF('TRANSPORT DASHBOARD'!$B$4="Area",IF(57<=$I$3,IF(OR('TRANSPORT DASHBOARD'!$C$4="",ISNUMBER(SEARCH('TRANSPORT DASHBOARD'!$C$4,INDEX(MASTER_AREAS!$B:$B,58)))),57,""),""),IF('TRANSPORT DASHBOARD'!$B$4="Zone",IF(57<=$I$4,IF(OR('TRANSPORT DASHBOARD'!$C$4="",ISNUMBER(SEARCH('TRANSPORT DASHBOARD'!$C$4,INDEX(MASTER_ZONES!$B:$B,58)))),57,""),""),"")) | G58: =IFERROR(SMALL($F$2:$F$1365,57),"") | H58: =IF(G58="","",IF('TRANSPORT DASHBOARD'!$B$4="Area",INDEX(MASTER_AREAS!$B:$B,G58+1),INDEX(MASTER_ZONES!$B:$B,G58+1)))
A59: =IF('WSF DASHBOARD'!$B$4="Area",IF(58<=$D$3,IF(OR('WSF DASHBOARD'!$C$4="",ISNUMBER(SEARCH('WSF DASHBOARD'!$C$4,INDEX(MASTER_AREAS!$B:$B,59)))),58,""),""),IF('WSF DASHBOARD'!$B$4="Zone",IF(58<=$D$4,IF(OR('WSF DASHBOARD'!$C$4="",ISNUMBER(SEARCH('WSF DASHBOARD'!$C$4,INDEX(MASTER_ZONES!$B:$B,59)))),58,""),""),"")) | B59: =IFERROR(SMALL($A$2:$A$1365,58),"") | C59: =IF(B59="","",IF('WSF DASHBOARD'!$B$4="Area",INDEX(MASTER_AREAS!$B:$B,B59+1),INDEX(MASTER_ZONES!$B:$B,B59+1))) | F59: =IF('TRANSPORT DASHBOARD'!$B$4="Area",IF(58<=$I$3,IF(OR('TRANSPORT DASHBOARD'!$C$4="",ISNUMBER(SEARCH('TRANSPORT DASHBOARD'!$C$4,INDEX(MASTER_AREAS!$B:$B,59)))),58,""),""),IF('TRANSPORT DASHBOARD'!$B$4="Zone",IF(58<=$I$4,IF(OR('TRANSPORT DASHBOARD'!$C$4="",ISNUMBER(SEARCH('TRANSPORT DASHBOARD'!$C$4,INDEX(MASTER_ZONES!$B:$B,59)))),58,""),""),"")) | G59: =IFERROR(SMALL($F$2:$F$1365,58),"") | H59: =IF(G59="","",IF('TRANSPORT DASHBOARD'!$B$4="Area",INDEX(MASTER_AREAS!$B:$B,G59+1),INDEX(MASTER_ZONES!$B:$B,G59+1)))
A60: =IF('WSF DASHBOARD'!$B$4="Area",IF(59<=$D$3,IF(OR('WSF DASHBOARD'!$C$4="",ISNUMBER(SEARCH('WSF DASHBOARD'!$C$4,INDEX(MASTER_AREAS!$B:$B,60)))),59,""),""),IF('WSF DASHBOARD'!$B$4="Zone",IF(59<=$D$4,IF(OR('WSF DASHBOARD'!$C$4="",ISNUMBER(SEARCH('WSF DASHBOARD'!$C$4,INDEX(MASTER_ZONES!$B:$B,60)))),59,""),""),"")) | B60: =IFERROR(SMALL($A$2:$A$1365,59),"") | C60: =IF(B60="","",IF('WSF DASHBOARD'!$B$4="Area",INDEX(MASTER_AREAS!$B:$B,B60+1),INDEX(MASTER_ZONES!$B:$B,B60+1))) | F60: =IF('TRANSPORT DASHBOARD'!$B$4="Area",IF(59<=$I$3,IF(OR('TRANSPORT DASHBOARD'!$C$4="",ISNUMBER(SEARCH('TRANSPORT DASHBOARD'!$C$4,INDEX(MASTER_AREAS!$B:$B,60)))),59,""),""),IF('TRANSPORT DASHBOARD'!$B$4="Zone",IF(59<=$I$4,IF(OR('TRANSPORT DASHBOARD'!$C$4="",ISNUMBER(SEARCH('TRANSPORT DASHBOARD'!$C$4,INDEX(MASTER_ZONES!$B:$B,60)))),59,""),""),"")) | G60: =IFERROR(SMALL($F$2:$F$1365,59),"") | H60: =IF(G60="","",IF('TRANSPORT DASHBOARD'!$B$4="Area",INDEX(MASTER_AREAS!$B:$B,G60+1),INDEX(MASTER_ZONES!$B:$B,G60+1)))
A61: =IF('WSF DASHBOARD'!$B$4="Area",IF(60<=$D$3,IF(OR('WSF DASHBOARD'!$C$4="",ISNUMBER(SEARCH('WSF DASHBOARD'!$C$4,INDEX(MASTER_AREAS!$B:$B,61)))),60,""),""),IF('WSF DASHBOARD'!$B$4="Zone",IF(60<=$D$4,IF(OR('WSF DASHBOARD'!$C$4="",ISNUMBER(SEARCH('WSF DASHBOARD'!$C$4,INDEX(MASTER_ZONES!$B:$B,61)))),60,""),""),"")) | B61: =IFERROR(SMALL($A$2:$A$1365,60),"") | C61: =IF(B61="","",IF('WSF DASHBOARD'!$B$4="Area",INDEX(MASTER_AREAS!$B:$B,B61+1),INDEX(MASTER_ZONES!$B:$B,B61+1))) | F61: =IF('TRANSPORT DASHBOARD'!$B$4="Area",IF(60<=$I$3,IF(OR('TRANSPORT DASHBOARD'!$C$4="",ISNUMBER(SEARCH('TRANSPORT DASHBOARD'!$C$4,INDEX(MASTER_AREAS!$B:$B,61)))),60,""),""),IF('TRANSPORT DASHBOARD'!$B$4="Zone",IF(60<=$I$4,IF(OR('TRANSPORT DASHBOARD'!$C$4="",ISNUMBER(SEARCH('TRANSPORT DASHBOARD'!$C$4,INDEX(MASTER_ZONES!$B:$B,61)))),60,""),""),"")) | G61: =IFERROR(SMALL($F$2:$F$1365,60),"") | H61: =IF(G61="","",IF('TRANSPORT DASHBOARD'!$B$4="Area",INDEX(MASTER_AREAS!$B:$B,G61+1),INDEX(MASTER_ZONES!$B:$B,G61+1)))
A62: =IF('WSF DASHBOARD'!$B$4="Area",IF(61<=$D$3,IF(OR('WSF DASHBOARD'!$C$4="",ISNUMBER(SEARCH('WSF DASHBOARD'!$C$4,INDEX(MASTER_AREAS!$B:$B,62)))),61,""),""),IF('WSF DASHBOARD'!$B$4="Zone",IF(61<=$D$4,IF(OR('WSF DASHBOARD'!$C$4="",ISNUMBER(SEARCH('WSF DASHBOARD'!$C$4,INDEX(MASTER_ZONES!$B:$B,62)))),61,""),""),"")) | B62: =IFERROR(SMALL($A$2:$A$1365,61),"") | C62: =IF(B62="","",IF('WSF DASHBOARD'!$B$4="Area",INDEX(MASTER_AREAS!$B:$B,B62+1),INDEX(MASTER_ZONES!$B:$B,B62+1))) | F62: =IF('TRANSPORT DASHBOARD'!$B$4="Area",IF(61<=$I$3,IF(OR('TRANSPORT DASHBOARD'!$C$4="",ISNUMBER(SEARCH('TRANSPORT DASHBOARD'!$C$4,INDEX(MASTER_AREAS!$B:$B,62)))),61,""),""),IF('TRANSPORT DASHBOARD'!$B$4="Zone",IF(61<=$I$4,IF(OR('TRANSPORT DASHBOARD'!$C$4="",ISNUMBER(SEARCH('TRANSPORT DASHBOARD'!$C$4,INDEX(MASTER_ZONES!$B:$B,62)))),61,""),""),"")) | G62: =IFERROR(SMALL($F$2:$F$1365,61),"") | H62: =IF(G62="","",IF('TRANSPORT DASHBOARD'!$B$4="Area",INDEX(MASTER_AREAS!$B:$B,G62+1),INDEX(MASTER_ZONES!$B:$B,G62+1)))
A63: =IF('WSF DASHBOARD'!$B$4="Area",IF(62<=$D$3,IF(OR('WSF DASHBOARD'!$C$4="",ISNUMBER(SEARCH('WSF DASHBOARD'!$C$4,INDEX(MASTER_AREAS!$B:$B,63)))),62,""),""),IF('WSF DASHBOARD'!$B$4="Zone",IF(62<=$D$4,IF(OR('WSF DASHBOARD'!$C$4="",ISNUMBER(SEARCH('WSF DASHBOARD'!$C$4,INDEX(MASTER_ZONES!$B:$B,63)))),62,""),""),"")) | B63: =IFERROR(SMALL($A$2:$A$1365,62),"") | C63: =IF(B63="","",IF('WSF DASHBOARD'!$B$4="Area",INDEX(MASTER_AREAS!$B:$B,B63+1),INDEX(MASTER_ZONES!$B:$B,B63+1))) | F63: =IF('TRANSPORT DASHBOARD'!$B$4="Area",IF(62<=$I$3,IF(OR('TRANSPORT DASHBOARD'!$C$4="",ISNUMBER(SEARCH('TRANSPORT DASHBOARD'!$C$4,INDEX(MASTER_AREAS!$B:$B,63)))),62,""),""),IF('TRANSPORT DASHBOARD'!$B$4="Zone",IF(62<=$I$4,IF(OR('TRANSPORT DASHBOARD'!$C$4="",ISNUMBER(SEARCH('TRANSPORT DASHBOARD'!$C$4,INDEX(MASTER_ZONES!$B:$B,63)))),62,""),""),"")) | G63: =IFERROR(SMALL($F$2:$F$1365,62),"") | H63: =IF(G63="","",IF('TRANSPORT DASHBOARD'!$B$4="Area",INDEX(MASTER_AREAS!$B:$B,G63+1),INDEX(MASTER_ZONES!$B:$B,G63+1)))
A64: =IF('WSF DASHBOARD'!$B$4="Area",IF(63<=$D$3,IF(OR('WSF DASHBOARD'!$C$4="",ISNUMBER(SEARCH('WSF DASHBOARD'!$C$4,INDEX(MASTER_AREAS!$B:$B,64)))),63,""),""),IF('WSF DASHBOARD'!$B$4="Zone",IF(63<=$D$4,IF(OR('WSF DASHBOARD'!$C$4="",ISNUMBER(SEARCH('WSF DASHBOARD'!$C$4,INDEX(MASTER_ZONES!$B:$B,64)))),63,""),""),"")) | B64: =IFERROR(SMALL($A$2:$A$1365,63),"") | C64: =IF(B64="","",IF('WSF DASHBOARD'!$B$4="Area",INDEX(MASTER_AREAS!$B:$B,B64+1),INDEX(MASTER_ZONES!$B:$B,B64+1))) | F64: =IF('TRANSPORT DASHBOARD'!$B$4="Area",IF(63<=$I$3,IF(OR('TRANSPORT DASHBOARD'!$C$4="",ISNUMBER(SEARCH('TRANSPORT DASHBOARD'!$C$4,INDEX(MASTER_AREAS!$B:$B,64)))),63,""),""),IF('TRANSPORT DASHBOARD'!$B$4="Zone",IF(63<=$I$4,IF(OR('TRANSPORT DASHBOARD'!$C$4="",ISNUMBER(SEARCH('TRANSPORT DASHBOARD'!$C$4,INDEX(MASTER_ZONES!$B:$B,64)))),63,""),""),"")) | G64: =IFERROR(SMALL($F$2:$F$1365,63),"") | H64: =IF(G64="","",IF('TRANSPORT DASHBOARD'!$B$4="Area",INDEX(MASTER_AREAS!$B:$B,G64+1),INDEX(MASTER_ZONES!$B:$B,G64+1)))
A65: =IF('WSF DASHBOARD'!$B$4="Area",IF(64<=$D$3,IF(OR('WSF DASHBOARD'!$C$4="",ISNUMBER(SEARCH('WSF DASHBOARD'!$C$4,INDEX(MASTER_AREAS!$B:$B,65)))),64,""),""),IF('WSF DASHBOARD'!$B$4="Zone",IF(64<=$D$4,IF(OR('WSF DASHBOARD'!$C$4="",ISNUMBER(SEARCH('WSF DASHBOARD'!$C$4,INDEX(MASTER_ZONES!$B:$B,65)))),64,""),""),"")) | B65: =IFERROR(SMALL($A$2:$A$1365,64),"") | C65: =IF(B65="","",IF('WSF DASHBOARD'!$B$4="Area",INDEX(MASTER_AREAS!$B:$B,B65+1),INDEX(MASTER_ZONES!$B:$B,B65+1))) | F65: =IF('TRANSPORT DASHBOARD'!$B$4="Area",IF(64<=$I$3,IF(OR('TRANSPORT DASHBOARD'!$C$4="",ISNUMBER(SEARCH('TRANSPORT DASHBOARD'!$C$4,INDEX(MASTER_AREAS!$B:$B,65)))),64,""),""),IF('TRANSPORT DASHBOARD'!$B$4="Zone",IF(64<=$I$4,IF(OR('TRANSPORT DASHBOARD'!$C$4="",ISNUMBER(SEARCH('TRANSPORT DASHBOARD'!$C$4,INDEX(MASTER_ZONES!$B:$B,65)))),64,""),""),"")) | G65: =IFERROR(SMALL($F$2:$F$1365,64),"") | H65: =IF(G65="","",IF('TRANSPORT DASHBOARD'!$B$4="Area",INDEX(MASTER_AREAS!$B:$B,G65+1),INDEX(MASTER_ZONES!$B:$B,G65+1)))
A66: =IF('WSF DASHBOARD'!$B$4="Area",IF(65<=$D$3,IF(OR('WSF DASHBOARD'!$C$4="",ISNUMBER(SEARCH('WSF DASHBOARD'!$C$4,INDEX(MASTER_AREAS!$B:$B,66)))),65,""),""),IF('WSF DASHBOARD'!$B$4="Zone",IF(65<=$D$4,IF(OR('WSF DASHBOARD'!$C$4="",ISNUMBER(SEARCH('WSF DASHBOARD'!$C$4,INDEX(MASTER_ZONES!$B:$B,66)))),65,""),""),"")) | B66: =IFERROR(SMALL($A$2:$A$1365,65),"") | C66: =IF(B66="","",IF('WSF DASHBOARD'!$B$4="Area",INDEX(MASTER_AREAS!$B:$B,B66+1),INDEX(MASTER_ZONES!$B:$B,B66+1))) | F66: =IF('TRANSPORT DASHBOARD'!$B$4="Area",IF(65<=$I$3,IF(OR('TRANSPORT DASHBOARD'!$C$4="",ISNUMBER(SEARCH('TRANSPORT DASHBOARD'!$C$4,INDEX(MASTER_AREAS!$B:$B,66)))),65,""),""),IF('TRANSPORT DASHBOARD'!$B$4="Zone",IF(65<=$I$4,IF(OR('TRANSPORT DASHBOARD'!$C$4="",ISNUMBER(SEARCH('TRANSPORT DASHBOARD'!$C$4,INDEX(MASTER_ZONES!$B:$B,66)))),65,""),""),"")) | G66: =IFERROR(SMALL($F$2:$F$1365,65),"") | H66: =IF(G66="","",IF('TRANSPORT DASHBOARD'!$B$4="Area",INDEX(MASTER_AREAS!$B:$B,G66+1),INDEX(MASTER_ZONES!$B:$B,G66+1)))
A67: =IF('WSF DASHBOARD'!$B$4="Area",IF(66<=$D$3,IF(OR('WSF DASHBOARD'!$C$4="",ISNUMBER(SEARCH('WSF DASHBOARD'!$C$4,INDEX(MASTER_AREAS!$B:$B,67)))),66,""),""),IF('WSF DASHBOARD'!$B$4="Zone",IF(66<=$D$4,IF(OR('WSF DASHBOARD'!$C$4="",ISNUMBER(SEARCH('WSF DASHBOARD'!$C$4,INDEX(MASTER_ZONES!$B:$B,67)))),66,""),""),"")) | B67: =IFERROR(SMALL($A$2:$A$1365,66),"") | C67: =IF(B67="","",IF('WSF DASHBOARD'!$B$4="Area",INDEX(MASTER_AREAS!$B:$B,B67+1),INDEX(MASTER_ZONES!$B:$B,B67+1))) | F67: =IF('TRANSPORT DASHBOARD'!$B$4="Area",IF(66<=$I$3,IF(OR('TRANSPORT DASHBOARD'!$C$4="",ISNUMBER(SEARCH('TRANSPORT DASHBOARD'!$C$4,INDEX(MASTER_AREAS!$B:$B,67)))),66,""),""),IF('TRANSPORT DASHBOARD'!$B$4="Zone",IF(66<=$I$4,IF(OR('TRANSPORT DASHBOARD'!$C$4="",ISNUMBER(SEARCH('TRANSPORT DASHBOARD'!$C$4,INDEX(MASTER_ZONES!$B:$B,67)))),66,""),""),"")) | G67: =IFERROR(SMALL($F$2:$F$1365,66),"") | H67: =IF(G67="","",IF('TRANSPORT DASHBOARD'!$B$4="Area",INDEX(MASTER_AREAS!$B:$B,G67+1),INDEX(MASTER_ZONES!$B:$B,G67+1)))
A68: =IF('WSF DASHBOARD'!$B$4="Area",IF(67<=$D$3,IF(OR('WSF DASHBOARD'!$C$4="",ISNUMBER(SEARCH('WSF DASHBOARD'!$C$4,INDEX(MASTER_AREAS!$B:$B,68)))),67,""),""),IF('WSF DASHBOARD'!$B$4="Zone",IF(67<=$D$4,IF(OR('WSF DASHBOARD'!$C$4="",ISNUMBER(SEARCH('WSF DASHBOARD'!$C$4,INDEX(MASTER_ZONES!$B:$B,68)))),67,""),""),"")) | B68: =IFERROR(SMALL($A$2:$A$1365,67),"") | C68: =IF(B68="","",IF('WSF DASHBOARD'!$B$4="Area",INDEX(MASTER_AREAS!$B:$B,B68+1),INDEX(MASTER_ZONES!$B:$B,B68+1))) | F68: =IF('TRANSPORT DASHBOARD'!$B$4="Area",IF(67<=$I$3,IF(OR('TRANSPORT DASHBOARD'!$C$4="",ISNUMBER(SEARCH('TRANSPORT DASHBOARD'!$C$4,INDEX(MASTER_AREAS!$B:$B,68)))),67,""),""),IF('TRANSPORT DASHBOARD'!$B$4="Zone",IF(67<=$I$4,IF(OR('TRANSPORT DASHBOARD'!$C$4="",ISNUMBER(SEARCH('TRANSPORT DASHBOARD'!$C$4,INDEX(MASTER_ZONES!$B:$B,68)))),67,""),""),"")) | G68: =IFERROR(SMALL($F$2:$F$1365,67),"") | H68: =IF(G68="","",IF('TRANSPORT DASHBOARD'!$B$4="Area",INDEX(MASTER_AREAS!$B:$B,G68+1),INDEX(MASTER_ZONES!$B:$B,G68+1)))
A69: =IF('WSF DASHBOARD'!$B$4="Area",IF(68<=$D$3,IF(OR('WSF DASHBOARD'!$C$4="",ISNUMBER(SEARCH('WSF DASHBOARD'!$C$4,INDEX(MASTER_AREAS!$B:$B,69)))),68,""),""),IF('WSF DASHBOARD'!$B$4="Zone",IF(68<=$D$4,IF(OR('WSF DASHBOARD'!$C$4="",ISNUMBER(SEARCH('WSF DASHBOARD'!$C$4,INDEX(MASTER_ZONES!$B:$B,69)))),68,""),""),"")) | B69: =IFERROR(SMALL($A$2:$A$1365,68),"") | C69: =IF(B69="","",IF('WSF DASHBOARD'!$B$4="Area",INDEX(MASTER_AREAS!$B:$B,B69+1),INDEX(MASTER_ZONES!$B:$B,B69+1))) | F69: =IF('TRANSPORT DASHBOARD'!$B$4="Area",IF(68<=$I$3,IF(OR('TRANSPORT DASHBOARD'!$C$4="",ISNUMBER(SEARCH('TRANSPORT DASHBOARD'!$C$4,INDEX(MASTER_AREAS!$B:$B,69)))),68,""),""),IF('TRANSPORT DASHBOARD'!$B$4="Zone",IF(68<=$I$4,IF(OR('TRANSPORT DASHBOARD'!$C$4="",ISNUMBER(SEARCH('TRANSPORT DASHBOARD'!$C$4,INDEX(MASTER_ZONES!$B:$B,69)))),68,""),""),"")) | G69: =IFERROR(SMALL($F$2:$F$1365,68),"") | H69: =IF(G69="","",IF('TRANSPORT DASHBOARD'!$B$4="Area",INDEX(MASTER_AREAS!$B:$B,G69+1),INDEX(MASTER_ZONES!$B:$B,G69+1)))
A70: =IF('WSF DASHBOARD'!$B$4="Area",IF(69<=$D$3,IF(OR('WSF DASHBOARD'!$C$4="",ISNUMBER(SEARCH('WSF DASHBOARD'!$C$4,INDEX(MASTER_AREAS!$B:$B,70)))),69,""),""),IF('WSF DASHBOARD'!$B$4="Zone",IF(69<=$D$4,IF(OR('WSF DASHBOARD'!$C$4="",ISNUMBER(SEARCH('WSF DASHBOARD'!$C$4,INDEX(MASTER_ZONES!$B:$B,70)))),69,""),""),"")) | B70: =IFERROR(SMALL($A$2:$A$1365,69),"") | C70: =IF(B70="","",IF('WSF DASHBOARD'!$B$4="Area",INDEX(MASTER_AREAS!$B:$B,B70+1),INDEX(MASTER_ZONES!$B:$B,B70+1))) | F70: =IF('TRANSPORT DASHBOARD'!$B$4="Area",IF(69<=$I$3,IF(OR('TRANSPORT DASHBOARD'!$C$4="",ISNUMBER(SEARCH('TRANSPORT DASHBOARD'!$C$4,INDEX(MASTER_AREAS!$B:$B,70)))),69,""),""),IF('TRANSPORT DASHBOARD'!$B$4="Zone",IF(69<=$I$4,IF(OR('TRANSPORT DASHBOARD'!$C$4="",ISNUMBER(SEARCH('TRANSPORT DASHBOARD'!$C$4,INDEX(MASTER_ZONES!$B:$B,70)))),69,""),""),"")) | G70: =IFERROR(SMALL($F$2:$F$1365,69),"") | H70: =IF(G70="","",IF('TRANSPORT DASHBOARD'!$B$4="Area",INDEX(MASTER_AREAS!$B:$B,G70+1),INDEX(MASTER_ZONES!$B:$B,G70+1)))
A71: =IF('WSF DASHBOARD'!$B$4="Area",IF(70<=$D$3,IF(OR('WSF DASHBOARD'!$C$4="",ISNUMBER(SEARCH('WSF DASHBOARD'!$C$4,INDEX(MASTER_AREAS!$B:$B,71)))),70,""),""),IF('WSF DASHBOARD'!$B$4="Zone",IF(70<=$D$4,IF(OR('WSF DASHBOARD'!$C$4="",ISNUMBER(SEARCH('WSF DASHBOARD'!$C$4,INDEX(MASTER_ZONES!$B:$B,71)))),70,""),""),"")) | B71: =IFERROR(SMALL($A$2:$A$1365,70),"") | C71: =IF(B71="","",IF('WSF DASHBOARD'!$B$4="Area",INDEX(MASTER_AREAS!$B:$B,B71+1),INDEX(MASTER_ZONES!$B:$B,B71+1))) | F71: =IF('TRANSPORT DASHBOARD'!$B$4="Area",IF(70<=$I$3,IF(OR('TRANSPORT DASHBOARD'!$C$4="",ISNUMBER(SEARCH('TRANSPORT DASHBOARD'!$C$4,INDEX(MASTER_AREAS!$B:$B,71)))),70,""),""),IF('TRANSPORT DASHBOARD'!$B$4="Zone",IF(70<=$I$4,IF(OR('TRANSPORT DASHBOARD'!$C$4="",ISNUMBER(SEARCH('TRANSPORT DASHBOARD'!$C$4,INDEX(MASTER_ZONES!$B:$B,71)))),70,""),""),"")) | G71: =IFERROR(SMALL($F$2:$F$1365,70),"") | H71: =IF(G71="","",IF('TRANSPORT DASHBOARD'!$B$4="Area",INDEX(MASTER_AREAS!$B:$B,G71+1),INDEX(MASTER_ZONES!$B:$B,G71+1)))
A72: =IF('WSF DASHBOARD'!$B$4="Area",IF(71<=$D$3,IF(OR('WSF DASHBOARD'!$C$4="",ISNUMBER(SEARCH('WSF DASHBOARD'!$C$4,INDEX(MASTER_AREAS!$B:$B,72)))),71,""),""),IF('WSF DASHBOARD'!$B$4="Zone",IF(71<=$D$4,IF(OR('WSF DASHBOARD'!$C$4="",ISNUMBER(SEARCH('WSF DASHBOARD'!$C$4,INDEX(MASTER_ZONES!$B:$B,72)))),71,""),""),"")) | B72: =IFERROR(SMALL($A$2:$A$1365,71),"") | C72: =IF(B72="","",IF('WSF DASHBOARD'!$B$4="Area",INDEX(MASTER_AREAS!$B:$B,B72+1),INDEX(MASTER_ZONES!$B:$B,B72+1))) | F72: =IF('TRANSPORT DASHBOARD'!$B$4="Area",IF(71<=$I$3,IF(OR('TRANSPORT DASHBOARD'!$C$4="",ISNUMBER(SEARCH('TRANSPORT DASHBOARD'!$C$4,INDEX(MASTER_AREAS!$B:$B,72)))),71,""),""),IF('TRANSPORT DASHBOARD'!$B$4="Zone",IF(71<=$I$4,IF(OR('TRANSPORT DASHBOARD'!$C$4="",ISNUMBER(SEARCH('TRANSPORT DASHBOARD'!$C$4,INDEX(MASTER_ZONES!$B:$B,72)))),71,""),""),"")) | G72: =IFERROR(SMALL($F$2:$F$1365,71),"") | H72: =IF(G72="","",IF('TRANSPORT DASHBOARD'!$B$4="Area",INDEX(MASTER_AREAS!$B:$B,G72+1),INDEX(MASTER_ZONES!$B:$B,G72+1)))
A73: =IF('WSF DASHBOARD'!$B$4="Area",IF(72<=$D$3,IF(OR('WSF DASHBOARD'!$C$4="",ISNUMBER(SEARCH('WSF DASHBOARD'!$C$4,INDEX(MASTER_AREAS!$B:$B,73)))),72,""),""),IF('WSF DASHBOARD'!$B$4="Zone",IF(72<=$D$4,IF(OR('WSF DASHBOARD'!$C$4="",ISNUMBER(SEARCH('WSF DASHBOARD'!$C$4,INDEX(MASTER_ZONES!$B:$B,73)))),72,""),""),"")) | B73: =IFERROR(SMALL($A$2:$A$1365,72),"") | C73: =IF(B73="","",IF('WSF DASHBOARD'!$B$4="Area",INDEX(MASTER_AREAS!$B:$B,B73+1),INDEX(MASTER_ZONES!$B:$B,B73+1))) | F73: =IF('TRANSPORT DASHBOARD'!$B$4="Area",IF(72<=$I$3,IF(OR('TRANSPORT DASHBOARD'!$C$4="",ISNUMBER(SEARCH('TRANSPORT DASHBOARD'!$C$4,INDEX(MASTER_AREAS!$B:$B,73)))),72,""),""),IF('TRANSPORT DASHBOARD'!$B$4="Zone",IF(72<=$I$4,IF(OR('TRANSPORT DASHBOARD'!$C$4="",ISNUMBER(SEARCH('TRANSPORT DASHBOARD'!$C$4,INDEX(MASTER_ZONES!$B:$B,73)))),72,""),""),"")) | G73: =IFERROR(SMALL($F$2:$F$1365,72),"") | H73: =IF(G73="","",IF('TRANSPORT DASHBOARD'!$B$4="Area",INDEX(MASTER_AREAS!$B:$B,G73+1),INDEX(MASTER_ZONES!$B:$B,G73+1)))
A74: =IF('WSF DASHBOARD'!$B$4="Area",IF(73<=$D$3,IF(OR('WSF DASHBOARD'!$C$4="",ISNUMBER(SEARCH('WSF DASHBOARD'!$C$4,INDEX(MASTER_AREAS!$B:$B,74)))),73,""),""),IF('WSF DASHBOARD'!$B$4="Zone",IF(73<=$D$4,IF(OR('WSF DASHBOARD'!$C$4="",ISNUMBER(SEARCH('WSF DASHBOARD'!$C$4,INDEX(MASTER_ZONES!$B:$B,74)))),73,""),""),"")) | B74: =IFERROR(SMALL($A$2:$A$1365,73),"") | C74: =IF(B74="","",IF('WSF DASHBOARD'!$B$4="Area",INDEX(MASTER_AREAS!$B:$B,B74+1),INDEX(MASTER_ZONES!$B:$B,B74+1))) | F74: =IF('TRANSPORT DASHBOARD'!$B$4="Area",IF(73<=$I$3,IF(OR('TRANSPORT DASHBOARD'!$C$4="",ISNUMBER(SEARCH('TRANSPORT DASHBOARD'!$C$4,INDEX(MASTER_AREAS!$B:$B,74)))),73,""),""),IF('TRANSPORT DASHBOARD'!$B$4="Zone",IF(73<=$I$4,IF(OR('TRANSPORT DASHBOARD'!$C$4="",ISNUMBER(SEARCH('TRANSPORT DASHBOARD'!$C$4,INDEX(MASTER_ZONES!$B:$B,74)))),73,""),""),"")) | G74: =IFERROR(SMALL($F$2:$F$1365,73),"") | H74: =IF(G74="","",IF('TRANSPORT DASHBOARD'!$B$4="Area",INDEX(MASTER_AREAS!$B:$B,G74+1),INDEX(MASTER_ZONES!$B:$B,G74+1)))
A75: =IF('WSF DASHBOARD'!$B$4="Area",IF(74<=$D$3,IF(OR('WSF DASHBOARD'!$C$4="",ISNUMBER(SEARCH('WSF DASHBOARD'!$C$4,INDEX(MASTER_AREAS!$B:$B,75)))),74,""),""),IF('WSF DASHBOARD'!$B$4="Zone",IF(74<=$D$4,IF(OR('WSF DASHBOARD'!$C$4="",ISNUMBER(SEARCH('WSF DASHBOARD'!$C$4,INDEX(MASTER_ZONES!$B:$B,75)))),74,""),""),"")) | B75: =IFERROR(SMALL($A$2:$A$1365,74),"") | C75: =IF(B75="","",IF('WSF DASHBOARD'!$B$4="Area",INDEX(MASTER_AREAS!$B:$B,B75+1),INDEX(MASTER_ZONES!$B:$B,B75+1))) | F75: =IF('TRANSPORT DASHBOARD'!$B$4="Area",IF(74<=$I$3,IF(OR('TRANSPORT DASHBOARD'!$C$4="",ISNUMBER(SEARCH('TRANSPORT DASHBOARD'!$C$4,INDEX(MASTER_AREAS!$B:$B,75)))),74,""),""),IF('TRANSPORT DASHBOARD'!$B$4="Zone",IF(74<=$I$4,IF(OR('TRANSPORT DASHBOARD'!$C$4="",ISNUMBER(SEARCH('TRANSPORT DASHBOARD'!$C$4,INDEX(MASTER_ZONES!$B:$B,75)))),74,""),""),"")) | G75: =IFERROR(SMALL($F$2:$F$1365,74),"") | H75: =IF(G75="","",IF('TRANSPORT DASHBOARD'!$B$4="Area",INDEX(MASTER_AREAS!$B:$B,G75+1),INDEX(MASTER_ZONES!$B:$B,G75+1)))
A76: =IF('WSF DASHBOARD'!$B$4="Area",IF(75<=$D$3,IF(OR('WSF DASHBOARD'!$C$4="",ISNUMBER(SEARCH('WSF DASHBOARD'!$C$4,INDEX(MASTER_AREAS!$B:$B,76)))),75,""),""),IF('WSF DASHBOARD'!$B$4="Zone",IF(75<=$D$4,IF(OR('WSF DASHBOARD'!$C$4="",ISNUMBER(SEARCH('WSF DASHBOARD'!$C$4,INDEX(MASTER_ZONES!$B:$B,76)))),75,""),""),"")) | B76: =IFERROR(SMALL($A$2:$A$1365,75),"") | C76: =IF(B76="","",IF('WSF DASHBOARD'!$B$4="Area",INDEX(MASTER_AREAS!$B:$B,B76+1),INDEX(MASTER_ZONES!$B:$B,B76+1))) | F76: =IF('TRANSPORT DASHBOARD'!$B$4="Area",IF(75<=$I$3,IF(OR('TRANSPORT DASHBOARD'!$C$4="",ISNUMBER(SEARCH('TRANSPORT DASHBOARD'!$C$4,INDEX(MASTER_AREAS!$B:$B,76)))),75,""),""),IF('TRANSPORT DASHBOARD'!$B$4="Zone",IF(75<=$I$4,IF(OR('TRANSPORT DASHBOARD'!$C$4="",ISNUMBER(SEARCH('TRANSPORT DASHBOARD'!$C$4,INDEX(MASTER_ZONES!$B:$B,76)))),75,""),""),"")) | G76: =IFERROR(SMALL($F$2:$F$1365,75),"") | H76: =IF(G76="","",IF('TRANSPORT DASHBOARD'!$B$4="Area",INDEX(MASTER_AREAS!$B:$B,G76+1),INDEX(MASTER_ZONES!$B:$B,G76+1)))
A77: =IF('WSF DASHBOARD'!$B$4="Area",IF(76<=$D$3,IF(OR('WSF DASHBOARD'!$C$4="",ISNUMBER(SEARCH('WSF DASHBOARD'!$C$4,INDEX(MASTER_AREAS!$B:$B,77)))),76,""),""),IF('WSF DASHBOARD'!$B$4="Zone",IF(76<=$D$4,IF(OR('WSF DASHBOARD'!$C$4="",ISNUMBER(SEARCH('WSF DASHBOARD'!$C$4,INDEX(MASTER_ZONES!$B:$B,77)))),76,""),""),"")) | B77: =IFERROR(SMALL($A$2:$A$1365,76),"") | C77: =IF(B77="","",IF('WSF DASHBOARD'!$B$4="Area",INDEX(MASTER_AREAS!$B:$B,B77+1),INDEX(MASTER_ZONES!$B:$B,B77+1))) | F77: =IF('TRANSPORT DASHBOARD'!$B$4="Area",IF(76<=$I$3,IF(OR('TRANSPORT DASHBOARD'!$C$4="",ISNUMBER(SEARCH('TRANSPORT DASHBOARD'!$C$4,INDEX(MASTER_AREAS!$B:$B,77)))),76,""),""),IF('TRANSPORT DASHBOARD'!$B$4="Zone",IF(76<=$I$4,IF(OR('TRANSPORT DASHBOARD'!$C$4="",ISNUMBER(SEARCH('TRANSPORT DASHBOARD'!$C$4,INDEX(MASTER_ZONES!$B:$B,77)))),76,""),""),"")) | G77: =IFERROR(SMALL($F$2:$F$1365,76),"") | H77: =IF(G77="","",IF('TRANSPORT DASHBOARD'!$B$4="Area",INDEX(MASTER_AREAS!$B:$B,G77+1),INDEX(MASTER_ZONES!$B:$B,G77+1)))
A78: =IF('WSF DASHBOARD'!$B$4="Area",IF(77<=$D$3,IF(OR('WSF DASHBOARD'!$C$4="",ISNUMBER(SEARCH('WSF DASHBOARD'!$C$4,INDEX(MASTER_AREAS!$B:$B,78)))),77,""),""),IF('WSF DASHBOARD'!$B$4="Zone",IF(77<=$D$4,IF(OR('WSF DASHBOARD'!$C$4="",ISNUMBER(SEARCH('WSF DASHBOARD'!$C$4,INDEX(MASTER_ZONES!$B:$B,78)))),77,""),""),"")) | B78: =IFERROR(SMALL($A$2:$A$1365,77),"") | C78: =IF(B78="","",IF('WSF DASHBOARD'!$B$4="Area",INDEX(MASTER_AREAS!$B:$B,B78+1),INDEX(MASTER_ZONES!$B:$B,B78+1))) | F78: =IF('TRANSPORT DASHBOARD'!$B$4="Area",IF(77<=$I$3,IF(OR('TRANSPORT DASHBOARD'!$C$4="",ISNUMBER(SEARCH('TRANSPORT DASHBOARD'!$C$4,INDEX(MASTER_AREAS!$B:$B,78)))),77,""),""),IF('TRANSPORT DASHBOARD'!$B$4="Zone",IF(77<=$I$4,IF(OR('TRANSPORT DASHBOARD'!$C$4="",ISNUMBER(SEARCH('TRANSPORT DASHBOARD'!$C$4,INDEX(MASTER_ZONES!$B:$B,78)))),77,""),""),"")) | G78: =IFERROR(SMALL($F$2:$F$1365,77),"") | H78: =IF(G78="","",IF('TRANSPORT DASHBOARD'!$B$4="Area",INDEX(MASTER_AREAS!$B:$B,G78+1),INDEX(MASTER_ZONES!$B:$B,G78+1)))
A79: =IF('WSF DASHBOARD'!$B$4="Area",IF(78<=$D$3,IF(OR('WSF DASHBOARD'!$C$4="",ISNUMBER(SEARCH('WSF DASHBOARD'!$C$4,INDEX(MASTER_AREAS!$B:$B,79)))),78,""),""),IF('WSF DASHBOARD'!$B$4="Zone",IF(78<=$D$4,IF(OR('WSF DASHBOARD'!$C$4="",ISNUMBER(SEARCH('WSF DASHBOARD'!$C$4,INDEX(MASTER_ZONES!$B:$B,79)))),78,""),""),"")) | B79: =IFERROR(SMALL($A$2:$A$1365,78),"") | C79: =IF(B79="","",IF('WSF DASHBOARD'!$B$4="Area",INDEX(MASTER_AREAS!$B:$B,B79+1),INDEX(MASTER_ZONES!$B:$B,B79+1))) | F79: =IF('TRANSPORT DASHBOARD'!$B$4="Area",IF(78<=$I$3,IF(OR('TRANSPORT DASHBOARD'!$C$4="",ISNUMBER(SEARCH('TRANSPORT DASHBOARD'!$C$4,INDEX(MASTER_AREAS!$B:$B,79)))),78,""),""),IF('TRANSPORT DASHBOARD'!$B$4="Zone",IF(78<=$I$4,IF(OR('TRANSPORT DASHBOARD'!$C$4="",ISNUMBER(SEARCH('TRANSPORT DASHBOARD'!$C$4,INDEX(MASTER_ZONES!$B:$B,79)))),78,""),""),"")) | G79: =IFERROR(SMALL($F$2:$F$1365,78),"") | H79: =IF(G79="","",IF('TRANSPORT DASHBOARD'!$B$4="Area",INDEX(MASTER_AREAS!$B:$B,G79+1),INDEX(MASTER_ZONES!$B:$B,G79+1)))
A80: =IF('WSF DASHBOARD'!$B$4="Area",IF(79<=$D$3,IF(OR('WSF DASHBOARD'!$C$4="",ISNUMBER(SEARCH('WSF DASHBOARD'!$C$4,INDEX(MASTER_AREAS!$B:$B,80)))),79,""),""),IF('WSF DASHBOARD'!$B$4="Zone",IF(79<=$D$4,IF(OR('WSF DASHBOARD'!$C$4="",ISNUMBER(SEARCH('WSF DASHBOARD'!$C$4,INDEX(MASTER_ZONES!$B:$B,80)))),79,""),""),"")) | B80: =IFERROR(SMALL($A$2:$A$1365,79),"") | C80: =IF(B80="","",IF('WSF DASHBOARD'!$B$4="Area",INDEX(MASTER_AREAS!$B:$B,B80+1),INDEX(MASTER_ZONES!$B:$B,B80+1))) | F80: =IF('TRANSPORT DASHBOARD'!$B$4="Area",IF(79<=$I$3,IF(OR('TRANSPORT DASHBOARD'!$C$4="",ISNUMBER(SEARCH('TRANSPORT DASHBOARD'!$C$4,INDEX(MASTER_AREAS!$B:$B,80)))),79,""),""),IF('TRANSPORT DASHBOARD'!$B$4="Zone",IF(79<=$I$4,IF(OR('TRANSPORT DASHBOARD'!$C$4="",ISNUMBER(SEARCH('TRANSPORT DASHBOARD'!$C$4,INDEX(MASTER_ZONES!$B:$B,80)))),79,""),""),"")) | G80: =IFERROR(SMALL($F$2:$F$1365,79),"") | H80: =IF(G80="","",IF('TRANSPORT DASHBOARD'!$B$4="Area",INDEX(MASTER_AREAS!$B:$B,G80+1),INDEX(MASTER_ZONES!$B:$B,G80+1)))
A81: =IF('WSF DASHBOARD'!$B$4="Area",IF(80<=$D$3,IF(OR('WSF DASHBOARD'!$C$4="",ISNUMBER(SEARCH('WSF DASHBOARD'!$C$4,INDEX(MASTER_AREAS!$B:$B,81)))),80,""),""),IF('WSF DASHBOARD'!$B$4="Zone",IF(80<=$D$4,IF(OR('WSF DASHBOARD'!$C$4="",ISNUMBER(SEARCH('WSF DASHBOARD'!$C$4,INDEX(MASTER_ZONES!$B:$B,81)))),80,""),""),"")) | B81: =IFERROR(SMALL($A$2:$A$1365,80),"") | C81: =IF(B81="","",IF('WSF DASHBOARD'!$B$4="Area",INDEX(MASTER_AREAS!$B:$B,B81+1),INDEX(MASTER_ZONES!$B:$B,B81+1))) | F81: =IF('TRANSPORT DASHBOARD'!$B$4="Area",IF(80<=$I$3,IF(OR('TRANSPORT DASHBOARD'!$C$4="",ISNUMBER(SEARCH('TRANSPORT DASHBOARD'!$C$4,INDEX(MASTER_AREAS!$B:$B,81)))),80,""),""),IF('TRANSPORT DASHBOARD'!$B$4="Zone",IF(80<=$I$4,IF(OR('TRANSPORT DASHBOARD'!$C$4="",ISNUMBER(SEARCH('TRANSPORT DASHBOARD'!$C$4,INDEX(MASTER_ZONES!$B:$B,81)))),80,""),""),"")) | G81: =IFERROR(SMALL($F$2:$F$1365,80),"") | H81: =IF(G81="","",IF('TRANSPORT DASHBOARD'!$B$4="Area",INDEX(MASTER_AREAS!$B:$B,G81+1),INDEX(MASTER_ZONES!$B:$B,G81+1)))
A82: =IF('WSF DASHBOARD'!$B$4="Area",IF(81<=$D$3,IF(OR('WSF DASHBOARD'!$C$4="",ISNUMBER(SEARCH('WSF DASHBOARD'!$C$4,INDEX(MASTER_AREAS!$B:$B,82)))),81,""),""),IF('WSF DASHBOARD'!$B$4="Zone",IF(81<=$D$4,IF(OR('WSF DASHBOARD'!$C$4="",ISNUMBER(SEARCH('WSF DASHBOARD'!$C$4,INDEX(MASTER_ZONES!$B:$B,82)))),81,""),""),"")) | B82: =IFERROR(SMALL($A$2:$A$1365,81),"") | C82: =IF(B82="","",IF('WSF DASHBOARD'!$B$4="Area",INDEX(MASTER_AREAS!$B:$B,B82+1),INDEX(MASTER_ZONES!$B:$B,B82+1))) | F82: =IF('TRANSPORT DASHBOARD'!$B$4="Area",IF(81<=$I$3,IF(OR('TRANSPORT DASHBOARD'!$C$4="",ISNUMBER(SEARCH('TRANSPORT DASHBOARD'!$C$4,INDEX(MASTER_AREAS!$B:$B,82)))),81,""),""),IF('TRANSPORT DASHBOARD'!$B$4="Zone",IF(81<=$I$4,IF(OR('TRANSPORT DASHBOARD'!$C$4="",ISNUMBER(SEARCH('TRANSPORT DASHBOARD'!$C$4,INDEX(MASTER_ZONES!$B:$B,82)))),81,""),""),"")) | G82: =IFERROR(SMALL($F$2:$F$1365,81),"") | H82: =IF(G82="","",IF('TRANSPORT DASHBOARD'!$B$4="Area",INDEX(MASTER_AREAS!$B:$B,G82+1),INDEX(MASTER_ZONES!$B:$B,G82+1)))
A83: =IF('WSF DASHBOARD'!$B$4="Area",IF(82<=$D$3,IF(OR('WSF DASHBOARD'!$C$4="",ISNUMBER(SEARCH('WSF DASHBOARD'!$C$4,INDEX(MASTER_AREAS!$B:$B,83)))),82,""),""),IF('WSF DASHBOARD'!$B$4="Zone",IF(82<=$D$4,IF(OR('WSF DASHBOARD'!$C$4="",ISNUMBER(SEARCH('WSF DASHBOARD'!$C$4,INDEX(MASTER_ZONES!$B:$B,83)))),82,""),""),"")) | B83: =IFERROR(SMALL($A$2:$A$1365,82),"") | C83: =IF(B83="","",IF('WSF DASHBOARD'!$B$4="Area",INDEX(MASTER_AREAS!$B:$B,B83+1),INDEX(MASTER_ZONES!$B:$B,B83+1))) | F83: =IF('TRANSPORT DASHBOARD'!$B$4="Area",IF(82<=$I$3,IF(OR('TRANSPORT DASHBOARD'!$C$4="",ISNUMBER(SEARCH('TRANSPORT DASHBOARD'!$C$4,INDEX(MASTER_AREAS!$B:$B,83)))),82,""),""),IF('TRANSPORT DASHBOARD'!$B$4="Zone",IF(82<=$I$4,IF(OR('TRANSPORT DASHBOARD'!$C$4="",ISNUMBER(SEARCH('TRANSPORT DASHBOARD'!$C$4,INDEX(MASTER_ZONES!$B:$B,83)))),82,""),""),"")) | G83: =IFERROR(SMALL($F$2:$F$1365,82),"") | H83: =IF(G83="","",IF('TRANSPORT DASHBOARD'!$B$4="Area",INDEX(MASTER_AREAS!$B:$B,G83+1),INDEX(MASTER_ZONES!$B:$B,G83+1)))
A84: =IF('WSF DASHBOARD'!$B$4="Area",IF(83<=$D$3,IF(OR('WSF DASHBOARD'!$C$4="",ISNUMBER(SEARCH('WSF DASHBOARD'!$C$4,INDEX(MASTER_AREAS!$B:$B,84)))),83,""),""),IF('WSF DASHBOARD'!$B$4="Zone",IF(83<=$D$4,IF(OR('WSF DASHBOARD'!$C$4="",ISNUMBER(SEARCH('WSF DASHBOARD'!$C$4,INDEX(MASTER_ZONES!$B:$B,84)))),83,""),""),"")) | B84: =IFERROR(SMALL($A$2:$A$1365,83),"") | C84: =IF(B84="","",IF('WSF DASHBOARD'!$B$4="Area",INDEX(MASTER_AREAS!$B:$B,B84+1),INDEX(MASTER_ZONES!$B:$B,B84+1))) | F84: =IF('TRANSPORT DASHBOARD'!$B$4="Area",IF(83<=$I$3,IF(OR('TRANSPORT DASHBOARD'!$C$4="",ISNUMBER(SEARCH('TRANSPORT DASHBOARD'!$C$4,INDEX(MASTER_AREAS!$B:$B,84)))),83,""),""),IF('TRANSPORT DASHBOARD'!$B$4="Zone",IF(83<=$I$4,IF(OR('TRANSPORT DASHBOARD'!$C$4="",ISNUMBER(SEARCH('TRANSPORT DASHBOARD'!$C$4,INDEX(MASTER_ZONES!$B:$B,84)))),83,""),""),"")) | G84: =IFERROR(SMALL($F$2:$F$1365,83),"") | H84: =IF(G84="","",IF('TRANSPORT DASHBOARD'!$B$4="Area",INDEX(MASTER_AREAS!$B:$B,G84+1),INDEX(MASTER_ZONES!$B:$B,G84+1)))
A85: =IF('WSF DASHBOARD'!$B$4="Area",IF(84<=$D$3,IF(OR('WSF DASHBOARD'!$C$4="",ISNUMBER(SEARCH('WSF DASHBOARD'!$C$4,INDEX(MASTER_AREAS!$B:$B,85)))),84,""),""),IF('WSF DASHBOARD'!$B$4="Zone",IF(84<=$D$4,IF(OR('WSF DASHBOARD'!$C$4="",ISNUMBER(SEARCH('WSF DASHBOARD'!$C$4,INDEX(MASTER_ZONES!$B:$B,85)))),84,""),""),"")) | B85: =IFERROR(SMALL($A$2:$A$1365,84),"") | C85: =IF(B85="","",IF('WSF DASHBOARD'!$B$4="Area",INDEX(MASTER_AREAS!$B:$B,B85+1),INDEX(MASTER_ZONES!$B:$B,B85+1))) | F85: =IF('TRANSPORT DASHBOARD'!$B$4="Area",IF(84<=$I$3,IF(OR('TRANSPORT DASHBOARD'!$C$4="",ISNUMBER(SEARCH('TRANSPORT DASHBOARD'!$C$4,INDEX(MASTER_AREAS!$B:$B,85)))),84,""),""),IF('TRANSPORT DASHBOARD'!$B$4="Zone",IF(84<=$I$4,IF(OR('TRANSPORT DASHBOARD'!$C$4="",ISNUMBER(SEARCH('TRANSPORT DASHBOARD'!$C$4,INDEX(MASTER_ZONES!$B:$B,85)))),84,""),""),"")) | G85: =IFERROR(SMALL($F$2:$F$1365,84),"") | H85: =IF(G85="","",IF('TRANSPORT DASHBOARD'!$B$4="Area",INDEX(MASTER_AREAS!$B:$B,G85+1),INDEX(MASTER_ZONES!$B:$B,G85+1)))
A86: =IF('WSF DASHBOARD'!$B$4="Area",IF(85<=$D$3,IF(OR('WSF DASHBOARD'!$C$4="",ISNUMBER(SEARCH('WSF DASHBOARD'!$C$4,INDEX(MASTER_AREAS!$B:$B,86)))),85,""),""),IF('WSF DASHBOARD'!$B$4="Zone",IF(85<=$D$4,IF(OR('WSF DASHBOARD'!$C$4="",ISNUMBER(SEARCH('WSF DASHBOARD'!$C$4,INDEX(MASTER_ZONES!$B:$B,86)))),85,""),""),"")) | B86: =IFERROR(SMALL($A$2:$A$1365,85),"") | C86: =IF(B86="","",IF('WSF DASHBOARD'!$B$4="Area",INDEX(MASTER_AREAS!$B:$B,B86+1),INDEX(MASTER_ZONES!$B:$B,B86+1))) | F86: =IF('TRANSPORT DASHBOARD'!$B$4="Area",IF(85<=$I$3,IF(OR('TRANSPORT DASHBOARD'!$C$4="",ISNUMBER(SEARCH('TRANSPORT DASHBOARD'!$C$4,INDEX(MASTER_AREAS!$B:$B,86)))),85,""),""),IF('TRANSPORT DASHBOARD'!$B$4="Zone",IF(85<=$I$4,IF(OR('TRANSPORT DASHBOARD'!$C$4="",ISNUMBER(SEARCH('TRANSPORT DASHBOARD'!$C$4,INDEX(MASTER_ZONES!$B:$B,86)))),85,""),""),"")) | G86: =IFERROR(SMALL($F$2:$F$1365,85),"") | H86: =IF(G86="","",IF('TRANSPORT DASHBOARD'!$B$4="Area",INDEX(MASTER_AREAS!$B:$B,G86+1),INDEX(MASTER_ZONES!$B:$B,G86+1)))
A87: =IF('WSF DASHBOARD'!$B$4="Area",IF(86<=$D$3,IF(OR('WSF DASHBOARD'!$C$4="",ISNUMBER(SEARCH('WSF DASHBOARD'!$C$4,INDEX(MASTER_AREAS!$B:$B,87)))),86,""),""),IF('WSF DASHBOARD'!$B$4="Zone",IF(86<=$D$4,IF(OR('WSF DASHBOARD'!$C$4="",ISNUMBER(SEARCH('WSF DASHBOARD'!$C$4,INDEX(MASTER_ZONES!$B:$B,87)))),86,""),""),"")) | B87: =IFERROR(SMALL($A$2:$A$1365,86),"") | C87: =IF(B87="","",IF('WSF DASHBOARD'!$B$4="Area",INDEX(MASTER_AREAS!$B:$B,B87+1),INDEX(MASTER_ZONES!$B:$B,B87+1))) | F87: =IF('TRANSPORT DASHBOARD'!$B$4="Area",IF(86<=$I$3,IF(OR('TRANSPORT DASHBOARD'!$C$4="",ISNUMBER(SEARCH('TRANSPORT DASHBOARD'!$C$4,INDEX(MASTER_AREAS!$B:$B,87)))),86,""),""),IF('TRANSPORT DASHBOARD'!$B$4="Zone",IF(86<=$I$4,IF(OR('TRANSPORT DASHBOARD'!$C$4="",ISNUMBER(SEARCH('TRANSPORT DASHBOARD'!$C$4,INDEX(MASTER_ZONES!$B:$B,87)))),86,""),""),"")) | G87: =IFERROR(SMALL($F$2:$F$1365,86),"") | H87: =IF(G87="","",IF('TRANSPORT DASHBOARD'!$B$4="Area",INDEX(MASTER_AREAS!$B:$B,G87+1),INDEX(MASTER_ZONES!$B:$B,G87+1)))
A88: =IF('WSF DASHBOARD'!$B$4="Area",IF(87<=$D$3,IF(OR('WSF DASHBOARD'!$C$4="",ISNUMBER(SEARCH('WSF DASHBOARD'!$C$4,INDEX(MASTER_AREAS!$B:$B,88)))),87,""),""),IF('WSF DASHBOARD'!$B$4="Zone",IF(87<=$D$4,IF(OR('WSF DASHBOARD'!$C$4="",ISNUMBER(SEARCH('WSF DASHBOARD'!$C$4,INDEX(MASTER_ZONES!$B:$B,88)))),87,""),""),"")) | B88: =IFERROR(SMALL($A$2:$A$1365,87),"") | C88: =IF(B88="","",IF('WSF DASHBOARD'!$B$4="Area",INDEX(MASTER_AREAS!$B:$B,B88+1),INDEX(MASTER_ZONES!$B:$B,B88+1))) | F88: =IF('TRANSPORT DASHBOARD'!$B$4="Area",IF(87<=$I$3,IF(OR('TRANSPORT DASHBOARD'!$C$4="",ISNUMBER(SEARCH('TRANSPORT DASHBOARD'!$C$4,INDEX(MASTER_AREAS!$B:$B,88)))),87,""),""),IF('TRANSPORT DASHBOARD'!$B$4="Zone",IF(87<=$I$4,IF(OR('TRANSPORT DASHBOARD'!$C$4="",ISNUMBER(SEARCH('TRANSPORT DASHBOARD'!$C$4,INDEX(MASTER_ZONES!$B:$B,88)))),87,""),""),"")) | G88: =IFERROR(SMALL($F$2:$F$1365,87),"") | H88: =IF(G88="","",IF('TRANSPORT DASHBOARD'!$B$4="Area",INDEX(MASTER_AREAS!$B:$B,G88+1),INDEX(MASTER_ZONES!$B:$B,G88+1)))
A89: =IF('WSF DASHBOARD'!$B$4="Area",IF(88<=$D$3,IF(OR('WSF DASHBOARD'!$C$4="",ISNUMBER(SEARCH('WSF DASHBOARD'!$C$4,INDEX(MASTER_AREAS!$B:$B,89)))),88,""),""),IF('WSF DASHBOARD'!$B$4="Zone",IF(88<=$D$4,IF(OR('WSF DASHBOARD'!$C$4="",ISNUMBER(SEARCH('WSF DASHBOARD'!$C$4,INDEX(MASTER_ZONES!$B:$B,89)))),88,""),""),"")) | B89: =IFERROR(SMALL($A$2:$A$1365,88),"") | C89: =IF(B89="","",IF('WSF DASHBOARD'!$B$4="Area",INDEX(MASTER_AREAS!$B:$B,B89+1),INDEX(MASTER_ZONES!$B:$B,B89+1))) | F89: =IF('TRANSPORT DASHBOARD'!$B$4="Area",IF(88<=$I$3,IF(OR('TRANSPORT DASHBOARD'!$C$4="",ISNUMBER(SEARCH('TRANSPORT DASHBOARD'!$C$4,INDEX(MASTER_AREAS!$B:$B,89)))),88,""),""),IF('TRANSPORT DASHBOARD'!$B$4="Zone",IF(88<=$I$4,IF(OR('TRANSPORT DASHBOARD'!$C$4="",ISNUMBER(SEARCH('TRANSPORT DASHBOARD'!$C$4,INDEX(MASTER_ZONES!$B:$B,89)))),88,""),""),"")) | G89: =IFERROR(SMALL($F$2:$F$1365,88),"") | H89: =IF(G89="","",IF('TRANSPORT DASHBOARD'!$B$4="Area",INDEX(MASTER_AREAS!$B:$B,G89+1),INDEX(MASTER_ZONES!$B:$B,G89+1)))
A90: =IF('WSF DASHBOARD'!$B$4="Area",IF(89<=$D$3,IF(OR('WSF DASHBOARD'!$C$4="",ISNUMBER(SEARCH('WSF DASHBOARD'!$C$4,INDEX(MASTER_AREAS!$B:$B,90)))),89,""),""),IF('WSF DASHBOARD'!$B$4="Zone",IF(89<=$D$4,IF(OR('WSF DASHBOARD'!$C$4="",ISNUMBER(SEARCH('WSF DASHBOARD'!$C$4,INDEX(MASTER_ZONES!$B:$B,90)))),89,""),""),"")) | B90: =IFERROR(SMALL($A$2:$A$1365,89),"") | C90: =IF(B90="","",IF('WSF DASHBOARD'!$B$4="Area",INDEX(MASTER_AREAS!$B:$B,B90+1),INDEX(MASTER_ZONES!$B:$B,B90+1))) | F90: =IF('TRANSPORT DASHBOARD'!$B$4="Area",IF(89<=$I$3,IF(OR('TRANSPORT DASHBOARD'!$C$4="",ISNUMBER(SEARCH('TRANSPORT DASHBOARD'!$C$4,INDEX(MASTER_AREAS!$B:$B,90)))),89,""),""),IF('TRANSPORT DASHBOARD'!$B$4="Zone",IF(89<=$I$4,IF(OR('TRANSPORT DASHBOARD'!$C$4="",ISNUMBER(SEARCH('TRANSPORT DASHBOARD'!$C$4,INDEX(MASTER_ZONES!$B:$B,90)))),89,""),""),"")) | G90: =IFERROR(SMALL($F$2:$F$1365,89),"") | H90: =IF(G90="","",IF('TRANSPORT DASHBOARD'!$B$4="Area",INDEX(MASTER_AREAS!$B:$B,G90+1),INDEX(MASTER_ZONES!$B:$B,G90+1)))
A91: =IF('WSF DASHBOARD'!$B$4="Area",IF(90<=$D$3,IF(OR('WSF DASHBOARD'!$C$4="",ISNUMBER(SEARCH('WSF DASHBOARD'!$C$4,INDEX(MASTER_AREAS!$B:$B,91)))),90,""),""),IF('WSF DASHBOARD'!$B$4="Zone",IF(90<=$D$4,IF(OR('WSF DASHBOARD'!$C$4="",ISNUMBER(SEARCH('WSF DASHBOARD'!$C$4,INDEX(MASTER_ZONES!$B:$B,91)))),90,""),""),"")) | B91: =IFERROR(SMALL($A$2:$A$1365,90),"") | C91: =IF(B91="","",IF('WSF DASHBOARD'!$B$4="Area",INDEX(MASTER_AREAS!$B:$B,B91+1),INDEX(MASTER_ZONES!$B:$B,B91+1))) | F91: =IF('TRANSPORT DASHBOARD'!$B$4="Area",IF(90<=$I$3,IF(OR('TRANSPORT DASHBOARD'!$C$4="",ISNUMBER(SEARCH('TRANSPORT DASHBOARD'!$C$4,INDEX(MASTER_AREAS!$B:$B,91)))),90,""),""),IF('TRANSPORT DASHBOARD'!$B$4="Zone",IF(90<=$I$4,IF(OR('TRANSPORT DASHBOARD'!$C$4="",ISNUMBER(SEARCH('TRANSPORT DASHBOARD'!$C$4,INDEX(MASTER_ZONES!$B:$B,91)))),90,""),""),"")) | G91: =IFERROR(SMALL($F$2:$F$1365,90),"") | H91: =IF(G91="","",IF('TRANSPORT DASHBOARD'!$B$4="Area",INDEX(MASTER_AREAS!$B:$B,G91+1),INDEX(MASTER_ZONES!$B:$B,G91+1)))
A92: =IF('WSF DASHBOARD'!$B$4="Area",IF(91<=$D$3,IF(OR('WSF DASHBOARD'!$C$4="",ISNUMBER(SEARCH('WSF DASHBOARD'!$C$4,INDEX(MASTER_AREAS!$B:$B,92)))),91,""),""),IF('WSF DASHBOARD'!$B$4="Zone",IF(91<=$D$4,IF(OR('WSF DASHBOARD'!$C$4="",ISNUMBER(SEARCH('WSF DASHBOARD'!$C$4,INDEX(MASTER_ZONES!$B:$B,92)))),91,""),""),"")) | B92: =IFERROR(SMALL($A$2:$A$1365,91),"") | C92: =IF(B92="","",IF('WSF DASHBOARD'!$B$4="Area",INDEX(MASTER_AREAS!$B:$B,B92+1),INDEX(MASTER_ZONES!$B:$B,B92+1))) | F92: =IF('TRANSPORT DASHBOARD'!$B$4="Area",IF(91<=$I$3,IF(OR('TRANSPORT DASHBOARD'!$C$4="",ISNUMBER(SEARCH('TRANSPORT DASHBOARD'!$C$4,INDEX(MASTER_AREAS!$B:$B,92)))),91,""),""),IF('TRANSPORT DASHBOARD'!$B$4="Zone",IF(91<=$I$4,IF(OR('TRANSPORT DASHBOARD'!$C$4="",ISNUMBER(SEARCH('TRANSPORT DASHBOARD'!$C$4,INDEX(MASTER_ZONES!$B:$B,92)))),91,""),""),"")) | G92: =IFERROR(SMALL($F$2:$F$1365,91),"") | H92: =IF(G92="","",IF('TRANSPORT DASHBOARD'!$B$4="Area",INDEX(MASTER_AREAS!$B:$B,G92+1),INDEX(MASTER_ZONES!$B:$B,G92+1)))
A93: =IF('WSF DASHBOARD'!$B$4="Area",IF(92<=$D$3,IF(OR('WSF DASHBOARD'!$C$4="",ISNUMBER(SEARCH('WSF DASHBOARD'!$C$4,INDEX(MASTER_AREAS!$B:$B,93)))),92,""),""),IF('WSF DASHBOARD'!$B$4="Zone",IF(92<=$D$4,IF(OR('WSF DASHBOARD'!$C$4="",ISNUMBER(SEARCH('WSF DASHBOARD'!$C$4,INDEX(MASTER_ZONES!$B:$B,93)))),92,""),""),"")) | B93: =IFERROR(SMALL($A$2:$A$1365,92),"") | C93: =IF(B93="","",IF('WSF DASHBOARD'!$B$4="Area",INDEX(MASTER_AREAS!$B:$B,B93+1),INDEX(MASTER_ZONES!$B:$B,B93+1))) | F93: =IF('TRANSPORT DASHBOARD'!$B$4="Area",IF(92<=$I$3,IF(OR('TRANSPORT DASHBOARD'!$C$4="",ISNUMBER(SEARCH('TRANSPORT DASHBOARD'!$C$4,INDEX(MASTER_AREAS!$B:$B,93)))),92,""),""),IF('TRANSPORT DASHBOARD'!$B$4="Zone",IF(92<=$I$4,IF(OR('TRANSPORT DASHBOARD'!$C$4="",ISNUMBER(SEARCH('TRANSPORT DASHBOARD'!$C$4,INDEX(MASTER_ZONES!$B:$B,93)))),92,""),""),"")) | G93: =IFERROR(SMALL($F$2:$F$1365,92),"") | H93: =IF(G93="","",IF('TRANSPORT DASHBOARD'!$B$4="Area",INDEX(MASTER_AREAS!$B:$B,G93+1),INDEX(MASTER_ZONES!$B:$B,G93+1)))
A94: =IF('WSF DASHBOARD'!$B$4="Area",IF(93<=$D$3,IF(OR('WSF DASHBOARD'!$C$4="",ISNUMBER(SEARCH('WSF DASHBOARD'!$C$4,INDEX(MASTER_AREAS!$B:$B,94)))),93,""),""),IF('WSF DASHBOARD'!$B$4="Zone",IF(93<=$D$4,IF(OR('WSF DASHBOARD'!$C$4="",ISNUMBER(SEARCH('WSF DASHBOARD'!$C$4,INDEX(MASTER_ZONES!$B:$B,94)))),93,""),""),"")) | B94: =IFERROR(SMALL($A$2:$A$1365,93),"") | C94: =IF(B94="","",IF('WSF DASHBOARD'!$B$4="Area",INDEX(MASTER_AREAS!$B:$B,B94+1),INDEX(MASTER_ZONES!$B:$B,B94+1))) | F94: =IF('TRANSPORT DASHBOARD'!$B$4="Area",IF(93<=$I$3,IF(OR('TRANSPORT DASHBOARD'!$C$4="",ISNUMBER(SEARCH('TRANSPORT DASHBOARD'!$C$4,INDEX(MASTER_AREAS!$B:$B,94)))),93,""),""),IF('TRANSPORT DASHBOARD'!$B$4="Zone",IF(93<=$I$4,IF(OR('TRANSPORT DASHBOARD'!$C$4="",ISNUMBER(SEARCH('TRANSPORT DASHBOARD'!$C$4,INDEX(MASTER_ZONES!$B:$B,94)))),93,""),""),"")) | G94: =IFERROR(SMALL($F$2:$F$1365,93),"") | H94: =IF(G94="","",IF('TRANSPORT DASHBOARD'!$B$4="Area",INDEX(MASTER_AREAS!$B:$B,G94+1),INDEX(MASTER_ZONES!$B:$B,G94+1)))
A95: =IF('WSF DASHBOARD'!$B$4="Area",IF(94<=$D$3,IF(OR('WSF DASHBOARD'!$C$4="",ISNUMBER(SEARCH('WSF DASHBOARD'!$C$4,INDEX(MASTER_AREAS!$B:$B,95)))),94,""),""),IF('WSF DASHBOARD'!$B$4="Zone",IF(94<=$D$4,IF(OR('WSF DASHBOARD'!$C$4="",ISNUMBER(SEARCH('WSF DASHBOARD'!$C$4,INDEX(MASTER_ZONES!$B:$B,95)))),94,""),""),"")) | B95: =IFERROR(SMALL($A$2:$A$1365,94),"") | C95: =IF(B95="","",IF('WSF DASHBOARD'!$B$4="Area",INDEX(MASTER_AREAS!$B:$B,B95+1),INDEX(MASTER_ZONES!$B:$B,B95+1))) | F95: =IF('TRANSPORT DASHBOARD'!$B$4="Area",IF(94<=$I$3,IF(OR('TRANSPORT DASHBOARD'!$C$4="",ISNUMBER(SEARCH('TRANSPORT DASHBOARD'!$C$4,INDEX(MASTER_AREAS!$B:$B,95)))),94,""),""),IF('TRANSPORT DASHBOARD'!$B$4="Zone",IF(94<=$I$4,IF(OR('TRANSPORT DASHBOARD'!$C$4="",ISNUMBER(SEARCH('TRANSPORT DASHBOARD'!$C$4,INDEX(MASTER_ZONES!$B:$B,95)))),94,""),""),"")) | G95: =IFERROR(SMALL($F$2:$F$1365,94),"") | H95: =IF(G95="","",IF('TRANSPORT DASHBOARD'!$B$4="Area",INDEX(MASTER_AREAS!$B:$B,G95+1),INDEX(MASTER_ZONES!$B:$B,G95+1)))
A96: =IF('WSF DASHBOARD'!$B$4="Area",IF(95<=$D$3,IF(OR('WSF DASHBOARD'!$C$4="",ISNUMBER(SEARCH('WSF DASHBOARD'!$C$4,INDEX(MASTER_AREAS!$B:$B,96)))),95,""),""),IF('WSF DASHBOARD'!$B$4="Zone",IF(95<=$D$4,IF(OR('WSF DASHBOARD'!$C$4="",ISNUMBER(SEARCH('WSF DASHBOARD'!$C$4,INDEX(MASTER_ZONES!$B:$B,96)))),95,""),""),"")) | B96: =IFERROR(SMALL($A$2:$A$1365,95),"") | C96: =IF(B96="","",IF('WSF DASHBOARD'!$B$4="Area",INDEX(MASTER_AREAS!$B:$B,B96+1),INDEX(MASTER_ZONES!$B:$B,B96+1))) | F96: =IF('TRANSPORT DASHBOARD'!$B$4="Area",IF(95<=$I$3,IF(OR('TRANSPORT DASHBOARD'!$C$4="",ISNUMBER(SEARCH('TRANSPORT DASHBOARD'!$C$4,INDEX(MASTER_AREAS!$B:$B,96)))),95,""),""),IF('TRANSPORT DASHBOARD'!$B$4="Zone",IF(95<=$I$4,IF(OR('TRANSPORT DASHBOARD'!$C$4="",ISNUMBER(SEARCH('TRANSPORT DASHBOARD'!$C$4,INDEX(MASTER_ZONES!$B:$B,96)))),95,""),""),"")) | G96: =IFERROR(SMALL($F$2:$F$1365,95),"") | H96: =IF(G96="","",IF('TRANSPORT DASHBOARD'!$B$4="Area",INDEX(MASTER_AREAS!$B:$B,G96+1),INDEX(MASTER_ZONES!$B:$B,G96+1)))
A97: =IF('WSF DASHBOARD'!$B$4="Area",IF(96<=$D$3,IF(OR('WSF DASHBOARD'!$C$4="",ISNUMBER(SEARCH('WSF DASHBOARD'!$C$4,INDEX(MASTER_AREAS!$B:$B,97)))),96,""),""),IF('WSF DASHBOARD'!$B$4="Zone",IF(96<=$D$4,IF(OR('WSF DASHBOARD'!$C$4="",ISNUMBER(SEARCH('WSF DASHBOARD'!$C$4,INDEX(MASTER_ZONES!$B:$B,97)))),96,""),""),"")) | B97: =IFERROR(SMALL($A$2:$A$1365,96),"") | C97: =IF(B97="","",IF('WSF DASHBOARD'!$B$4="Area",INDEX(MASTER_AREAS!$B:$B,B97+1),INDEX(MASTER_ZONES!$B:$B,B97+1))) | F97: =IF('TRANSPORT DASHBOARD'!$B$4="Area",IF(96<=$I$3,IF(OR('TRANSPORT DASHBOARD'!$C$4="",ISNUMBER(SEARCH('TRANSPORT DASHBOARD'!$C$4,INDEX(MASTER_AREAS!$B:$B,97)))),96,""),""),IF('TRANSPORT DASHBOARD'!$B$4="Zone",IF(96<=$I$4,IF(OR('TRANSPORT DASHBOARD'!$C$4="",ISNUMBER(SEARCH('TRANSPORT DASHBOARD'!$C$4,INDEX(MASTER_ZONES!$B:$B,97)))),96,""),""),"")) | G97: =IFERROR(SMALL($F$2:$F$1365,96),"") | H97: =IF(G97="","",IF('TRANSPORT DASHBOARD'!$B$4="Area",INDEX(MASTER_AREAS!$B:$B,G97+1),INDEX(MASTER_ZONES!$B:$B,G97+1)))
A98: =IF('WSF DASHBOARD'!$B$4="Area",IF(97<=$D$3,IF(OR('WSF DASHBOARD'!$C$4="",ISNUMBER(SEARCH('WSF DASHBOARD'!$C$4,INDEX(MASTER_AREAS!$B:$B,98)))),97,""),""),IF('WSF DASHBOARD'!$B$4="Zone",IF(97<=$D$4,IF(OR('WSF DASHBOARD'!$C$4="",ISNUMBER(SEARCH('WSF DASHBOARD'!$C$4,INDEX(MASTER_ZONES!$B:$B,98)))),97,""),""),"")) | B98: =IFERROR(SMALL($A$2:$A$1365,97),"") | C98: =IF(B98="","",IF('WSF DASHBOARD'!$B$4="Area",INDEX(MASTER_AREAS!$B:$B,B98+1),INDEX(MASTER_ZONES!$B:$B,B98+1))) | F98: =IF('TRANSPORT DASHBOARD'!$B$4="Area",IF(97<=$I$3,IF(OR('TRANSPORT DASHBOARD'!$C$4="",ISNUMBER(SEARCH('TRANSPORT DASHBOARD'!$C$4,INDEX(MASTER_AREAS!$B:$B,98)))),97,""),""),IF('TRANSPORT DASHBOARD'!$B$4="Zone",IF(97<=$I$4,IF(OR('TRANSPORT DASHBOARD'!$C$4="",ISNUMBER(SEARCH('TRANSPORT DASHBOARD'!$C$4,INDEX(MASTER_ZONES!$B:$B,98)))),97,""),""),"")) | G98: =IFERROR(SMALL($F$2:$F$1365,97),"") | H98: =IF(G98="","",IF('TRANSPORT DASHBOARD'!$B$4="Area",INDEX(MASTER_AREAS!$B:$B,G98+1),INDEX(MASTER_ZONES!$B:$B,G98+1)))
A99: =IF('WSF DASHBOARD'!$B$4="Area",IF(98<=$D$3,IF(OR('WSF DASHBOARD'!$C$4="",ISNUMBER(SEARCH('WSF DASHBOARD'!$C$4,INDEX(MASTER_AREAS!$B:$B,99)))),98,""),""),IF('WSF DASHBOARD'!$B$4="Zone",IF(98<=$D$4,IF(OR('WSF DASHBOARD'!$C$4="",ISNUMBER(SEARCH('WSF DASHBOARD'!$C$4,INDEX(MASTER_ZONES!$B:$B,99)))),98,""),""),"")) | B99: =IFERROR(SMALL($A$2:$A$1365,98),"") | C99: =IF(B99="","",IF('WSF DASHBOARD'!$B$4="Area",INDEX(MASTER_AREAS!$B:$B,B99+1),INDEX(MASTER_ZONES!$B:$B,B99+1))) | F99: =IF('TRANSPORT DASHBOARD'!$B$4="Area",IF(98<=$I$3,IF(OR('TRANSPORT DASHBOARD'!$C$4="",ISNUMBER(SEARCH('TRANSPORT DASHBOARD'!$C$4,INDEX(MASTER_AREAS!$B:$B,99)))),98,""),""),IF('TRANSPORT DASHBOARD'!$B$4="Zone",IF(98<=$I$4,IF(OR('TRANSPORT DASHBOARD'!$C$4="",ISNUMBER(SEARCH('TRANSPORT DASHBOARD'!$C$4,INDEX(MASTER_ZONES!$B:$B,99)))),98,""),""),"")) | G99: =IFERROR(SMALL($F$2:$F$1365,98),"") | H99: =IF(G99="","",IF('TRANSPORT DASHBOARD'!$B$4="Area",INDEX(MASTER_AREAS!$B:$B,G99+1),INDEX(MASTER_ZONES!$B:$B,G99+1)))
A100: =IF('WSF DASHBOARD'!$B$4="Area",IF(99<=$D$3,IF(OR('WSF DASHBOARD'!$C$4="",ISNUMBER(SEARCH('WSF DASHBOARD'!$C$4,INDEX(MASTER_AREAS!$B:$B,100)))),99,""),""),IF('WSF DASHBOARD'!$B$4="Zone",IF(99<=$D$4,IF(OR('WSF DASHBOARD'!$C$4="",ISNUMBER(SEARCH('WSF DASHBOARD'!$C$4,INDEX(MASTER_ZONES!$B:$B,100)))),99,""),""),"")) | B100: =IFERROR(SMALL($A$2:$A$1365,99),"") | C100: =IF(B100="","",IF('WSF DASHBOARD'!$B$4="Area",INDEX(MASTER_AREAS!$B:$B,B100+1),INDEX(MASTER_ZONES!$B:$B,B100+1))) | F100: =IF('TRANSPORT DASHBOARD'!$B$4="Area",IF(99<=$I$3,IF(OR('TRANSPORT DASHBOARD'!$C$4="",ISNUMBER(SEARCH('TRANSPORT DASHBOARD'!$C$4,INDEX(MASTER_AREAS!$B:$B,100)))),99,""),""),IF('TRANSPORT DASHBOARD'!$B$4="Zone",IF(99<=$I$4,IF(OR('TRANSPORT DASHBOARD'!$C$4="",ISNUMBER(SEARCH('TRANSPORT DASHBOARD'!$C$4,INDEX(MASTER_ZONES!$B:$B,100)))),99,""),""),"")) | G100: =IFERROR(SMALL($F$2:$F$1365,99),"") | H100: =IF(G100="","",IF('TRANSPORT DASHBOARD'!$B$4="Area",INDEX(MASTER_AREAS!$B:$B,G100+1),INDEX(MASTER_ZONES!$B:$B,G100+1)))
...

Sheet CALC_WSF
A1: CALC_WSF — helper calculations for the WSF DASHBOARD (hidden; do not edit) | AW1: Non-reporting cells in scope | AX1: =COUNT(WSF_CELLS_CURRENT!$N:$N)
W2: Area | X2: Rows | Y2: Grand (sel wk) | Z2: Grand (prev wk) | AA2: Cells total | AB2: Cells reported | AC2: % reporting | AD2: Growth | AE2: Score att | AF2: Score pct | AG2: Score growth | AI2: k | AJ2: LARGE AE name | AK2: value | AL2: SMALL AE name | AM2: value | AN2: LARGE AF name | AO2: value | AP2: SMALL AF name | AQ2: value | AR2: LARGE AG name | AS2: value | AT2: SMALL AG name | AU2: value | AW2: Cell detail held for selected week | AX2: =COUNTIF(WSF_CELLS_CURRENT!$A:$A,$B$10)>0
A3: Scope | B3: ='WSF DASHBOARD'!B4 | W3: =IFERROR(INDEX(MASTER_AREAS!$B:$B,2)&"","") | X3: =IF(OR(W3="",$B$10=0),0,COUNTIFS(DATA_WSF!$A:$A,$B$10,DATA_WSF!$C:$C,W3)) | Y3: =IF(X3=0,0,SUMIFS(DATA_WSF!$L:$L,DATA_WSF!$A:$A,$B$10,DATA_WSF!$C:$C,W3)) | Z3: =IF(OR(W3="",$B$10=0),0,SUMIFS(DATA_WSF!$L:$L,DATA_WSF!$A:$A,$B$10-7,DATA_WSF!$C:$C,W3)) | AA3: =IF(X3=0,0,SUMIFS(DATA_WSF!$E:$E,DATA_WSF!$A:$A,$B$10,DATA_WSF!$C:$C,W3)) | AB3: =IF(X3=0,0,SUMIFS(DATA_WSF!$F:$F,DATA_WSF!$A:$A,$B$10,DATA_WSF!$C:$C,W3)) | AC3: =IF(AA3=0,"",AB3/AA3) | AD3: =IF(OR(X3=0,Z3=0),"",Y3/Z3-1) | AE3: =IF(X3=0,"",Y3+ROW()/1000000) | AF3: =IF(AC3="","",AC3+ROW()/1000000000) | AG3: =IF(AD3="","",AD3+ROW()/1000000000) | AI3: 1 | AJ3: =IFERROR(INDEX($W$3:$W$94,MATCH(LARGE($AE$3:$AE$94,1),$AE$3:$AE$94,0)),"") | AK3: =IFERROR(INDEX($Y$3:$Y$94,MATCH(LARGE($AE$3:$AE$94,1),$AE$3:$AE$94,0)),"") | AL3: =IFERROR(INDEX($W$3:$W$94,MATCH(SMALL($AE$3:$AE$94,1),$AE$3:$AE$94,0)),"") | AM3: =IFERROR(INDEX($Y$3:$Y$94,MATCH(SMALL($AE$3:$AE$94,1),$AE$3:$AE$94,0)),"") | AN3: =IFERROR(INDEX($W$3:$W$94,MATCH(LARGE($AF$3:$AF$94,1),$AF$3:$AF$94,0)),"") | AO3: =IFERROR(INDEX($AC$3:$AC$94,MATCH(LARGE($AF$3:$AF$94,1),$AF$3:$AF$94,0)),"") | AP3: =IFERROR(INDEX($W$3:$W$94,MATCH(SMALL($AF$3:$AF$94,1),$AF$3:$AF$94,0)),"") | AQ3: =IFERROR(INDEX($AC$3:$AC$94,MATCH(SMALL($AF$3:$AF$94,1),$AF$3:$AF$94,0)),"") | AR3: =IFERROR(INDEX($W$3:$W$94,MATCH(LARGE($AG$3:$AG$94,1),$AG$3:$AG$94,0)),"") | AS3: =IFERROR(INDEX($AD$3:$AD$94,MATCH(LARGE($AG$3:$AG$94,1),$AG$3:$AG$94,0)),"") | AT3: =IFERROR(INDEX($W$3:$W$94,MATCH(SMALL($AG$3:$AG$94,1),$AG$3:$AG$94,0)),"") | AU3: =IFERROR(INDEX($AD$3:$AD$94,MATCH(SMALL($AG$3:$AG$94,1),$AG$3:$AG$94,0)),"")
